// class version 55.0 (55)
// access flags 0x20
class original/FindClosestElements {

  // compiled from: id_20.java

  // access flags 0x0
  <init>()V
   L0
    LINENUMBER 9 L0
    ALOAD 0
    INVOKESPECIAL java/lang/Object.<init> ()V
    RETURN
   L1
    LOCALVARIABLE this Loriginal/FindClosestElements; L0 L1 0
    MAXSTACK = 1
    MAXLOCALS = 1

  // access flags 0x9
  // signature (Ljava/util/List<Ljava/lang/Double;>;)Ljava/util/List<Ljava/lang/Double;>;
  // declaration: java.util.List<java.lang.Double> findClosestElements(java.util.List<java.lang.Double>)
  public static findClosestElements(Ljava/util/List;)Ljava/util/List;
   L0
    LINENUMBER 26 L0
    NEW java/util/ArrayList
    DUP
    INVOKESPECIAL java/util/ArrayList.<init> ()V
    ASTORE 1
   L1
    LINENUMBER 27 L1
    LDC 1.7976931348623157E308D
    DSTORE 2
   L2
    LINENUMBER 28 L2
    ICONST_0
    ISTORE 4
   L3
   FRAME FULL [java/util/List java/util/ArrayList D I] []
    ILOAD 4
    ALOAD 0
    INVOKEINTERFACE java/util/List.size ()I (itf)
    IF_ICMPGE L4
   L5
    LINENUMBER 29 L5
    ILOAD 4
    ICONST_1
    IADD
    ISTORE 5
   L6
   FRAME FULL [java/util/List java/util/ArrayList D I I] []
    ILOAD 5
    ALOAD 0
    INVOKEINTERFACE java/util/List.size ()I (itf)
    IF_ICMPGE L7
   L8
    LINENUMBER 30 L8
    ALOAD 0
    ILOAD 4
    INVOKEINTERFACE java/util/List.get (I)Ljava/lang/Object; (itf)
    CHECKCAST java/lang/Double
    INVOKEVIRTUAL java/lang/Double.doubleValue ()D
    ALOAD 0
    ILOAD 5
    INVOKEINTERFACE java/util/List.get (I)Ljava/lang/Object; (itf)
    CHECKCAST java/lang/Double
    INVOKEVIRTUAL java/lang/Double.doubleValue ()D
    DSUB
    INVOKESTATIC java/lang/Math.abs (D)D
    DSTORE 6
   L9
    LINENUMBER 31 L9
    DLOAD 6
    DLOAD 2
    DCMPG
    IFGE L10
   L11
    LINENUMBER 32 L11
    DLOAD 6
    DSTORE 2
   L12
    LINENUMBER 33 L12
    ALOAD 1
    INVOKEINTERFACE java/util/List.clear ()V (itf)
   L13
    LINENUMBER 34 L13
    ALOAD 1
    ALOAD 0
    ILOAD 4
    INVOKEINTERFACE java/util/List.get (I)Ljava/lang/Object; (itf)
    CHECKCAST java/lang/Double
    INVOKEINTERFACE java/util/List.add (Ljava/lang/Object;)Z (itf)
    POP
   L14
    LINENUMBER 35 L14
    ALOAD 1
    ALOAD 0
    ILOAD 5
    INVOKEINTERFACE java/util/List.get (I)Ljava/lang/Object; (itf)
    CHECKCAST java/lang/Double
    INVOKEINTERFACE java/util/List.add (Ljava/lang/Object;)Z (itf)
    POP
   L10
    LINENUMBER 29 L10
   FRAME FULL [java/util/List java/util/ArrayList D I I D] []
    IINC 5 1
    GOTO L6
   L7
    LINENUMBER 28 L7
   FRAME FULL [java/util/List java/util/ArrayList D I I] []
    IINC 4 1
    GOTO L3
   L4
    LINENUMBER 39 L4
   FRAME FULL [java/util/List java/util/ArrayList D I] []
    ALOAD 1
    INVOKESTATIC java/util/Collections.sort (Ljava/util/List;)V
   L15
    LINENUMBER 40 L15
    ALOAD 1
    POP
    INVOKESTATIC java/util/Collections.emptyList ()Ljava/util/List;
    ARETURN
   L16
    LOCALVARIABLE diff D L9 L10 6
    LOCALVARIABLE j I L6 L7 5
    LOCALVARIABLE i I L3 L4 4
    LOCALVARIABLE numbers Ljava/util/List; L0 L16 0
    // signature Ljava/util/List<Ljava/lang/Double;>;
    // declaration: numbers extends java.util.List<java.lang.Double>
    LOCALVARIABLE result Ljava/util/List; L1 L16 1
    // signature Ljava/util/List<Ljava/lang/Double;>;
    // declaration: result extends java.util.List<java.lang.Double>
    LOCALVARIABLE minDiff D L2 L16 2
    MAXSTACK = 4
    MAXLOCALS = 8
}

