// class version 55.0 (55)
// access flags 0x20
class original/CycpatternCheck {

  // compiled from: id_154.java
  // access flags 0x19
  public final static INNERCLASS java/lang/invoke/MethodHandles$Lookup java/lang/invoke/MethodHandles Lookup

  // access flags 0x0
  <init>()V
   L0
    LINENUMBER 4 L0
    ALOAD 0
    INVOKESPECIAL java/lang/Object.<init> ()V
    RETURN
   L1
    LOCALVARIABLE this Loriginal/CycpatternCheck; L0 L1 0
    MAXSTACK = 1
    MAXLOCALS = 1

  // access flags 0x9
  public static cycpatternCheck(Ljava/lang/String;Ljava/lang/String;)Ljava/lang/Boolean;
   L0
    LINENUMBER 29 L0
    ALOAD 1
    INVOKEVIRTUAL java/lang/String.length ()I
    ISTORE 2
   L1
    LINENUMBER 30 L1
    ALOAD 1
    ALOAD 1
    INVOKEDYNAMIC makeConcatWithConstants(Ljava/lang/String;Ljava/lang/String;)Ljava/lang/String; [
      // handle kind 0x6 : INVOKESTATIC
      java/lang/invoke/StringConcatFactory.makeConcatWithConstants(Ljava/lang/invoke/MethodHandles$Lookup;Ljava/lang/String;Ljava/lang/invoke/MethodType;Ljava/lang/String;[Ljava/lang/Object;)Ljava/lang/invoke/CallSite;
      // arguments:
      "\u0001\u0001"
    ]
    ASTORE 3
   L2
    LINENUMBER 31 L2
    ICONST_0
    ISTORE 4
   L3
   FRAME FULL [java/lang/String java/lang/String I java/lang/String I] []
    ILOAD 4
    ALOAD 0
    INVOKEVIRTUAL java/lang/String.length ()I
    ILOAD 2
    ISUB
    ICONST_1
    IADD
    IF_ICMPGE L4
   L5
    LINENUMBER 32 L5
    ICONST_0
    ISTORE 5
   L6
   FRAME FULL [java/lang/String java/lang/String I java/lang/String I I] []
    ILOAD 5
    ILOAD 2
    ICONST_1
    IADD
    IF_ICMPGE L7
   L8
    LINENUMBER 33 L8
    ALOAD 0
    ILOAD 4
    ILOAD 4
    ILOAD 2
    IADD
    INVOKEVIRTUAL java/lang/String.substring (II)Ljava/lang/String;
    ALOAD 3
    ILOAD 5
    ILOAD 5
    ILOAD 2
    IADD
    INVOKEVIRTUAL java/lang/String.substring (II)Ljava/lang/String;
    INVOKEVIRTUAL java/lang/String.equals (Ljava/lang/Object;)Z
    IFEQ L9
   L10
    LINENUMBER 34 L10
    ICONST_1
    INVOKESTATIC java/lang/Boolean.valueOf (Z)Ljava/lang/Boolean;
    ARETURN
   L9
    LINENUMBER 32 L9
   FRAME FULL [java/lang/String java/lang/String I java/lang/String I I] []
    IINC 5 1
    GOTO L6
   L7
    LINENUMBER 31 L7
   FRAME FULL [java/lang/String java/lang/String I java/lang/String I I] []
    IINC 4 1
    GOTO L3
   L4
    LINENUMBER 38 L4
   FRAME FULL [java/lang/String java/lang/String I java/lang/String I] []
    ICONST_0
    INVOKESTATIC java/lang/Boolean.valueOf (Z)Ljava/lang/Boolean;
    POP
    ICONST_1
    INVOKESTATIC java/lang/Boolean.valueOf (Z)Ljava/lang/Boolean;
    ARETURN
   L11
    LOCALVARIABLE j I L6 L7 5
    LOCALVARIABLE i I L3 L4 4
    LOCALVARIABLE a Ljava/lang/String; L0 L11 0
    LOCALVARIABLE b Ljava/lang/String; L0 L11 1
    LOCALVARIABLE l I L1 L11 2
    LOCALVARIABLE pat Ljava/lang/String; L2 L11 3
    MAXSTACK = 5
    MAXLOCALS = 6
}

