// class version 55.0 (55)
// access flags 0x20
class original/HasCloseElements {

  // compiled from: id_0.java

  // access flags 0x0
  <init>()V
   L0
    LINENUMBER 5 L0
    ALOAD 0
    INVOKESPECIAL java/lang/Object.<init> ()V
    RETURN
   L1
    LOCALVARIABLE this Loriginal/HasCloseElements; L0 L1 0
    MAXSTACK = 1
    MAXLOCALS = 1

  // access flags 0x9
  // signature (Ljava/util/List<Ljava/lang/Double;>;Ljava/lang/Double;)Ljava/lang/Boolean;
  // declaration: java.lang.Boolean hasCloseElements(java.util.List<java.lang.Double>, java.lang.Double)
  public static hasCloseElements(Ljava/util/List;Ljava/lang/Double;)Ljava/lang/Boolean;
   L0
    LINENUMBER 29 L0
    ICONST_0
    ISTORE 2
   L1
   FRAME FULL [java/util/List java/lang/Double I] []
    ILOAD 2
    ALOAD 0
    INVOKEINTERFACE java/util/List.size ()I (itf)
    IF_ICMPGE L2
   L3
    LINENUMBER 30 L3
    ILOAD 2
    ICONST_1
    IADD
    ISTORE 3
   L4
   FRAME FULL [java/util/List java/lang/Double I I] []
    ILOAD 3
    ALOAD 0
    INVOKEINTERFACE java/util/List.size ()I (itf)
    IF_ICMPGT L5
   L6
    LINENUMBER 31 L6
    ALOAD 0
    ILOAD 2
    INVOKEINTERFACE java/util/List.get (I)Ljava/lang/Object; (itf)
    CHECKCAST java/lang/Double
    INVOKEVIRTUAL java/lang/Double.doubleValue ()D
    ALOAD 0
    ILOAD 3
    INVOKEINTERFACE java/util/List.get (I)Ljava/lang/Object; (itf)
    CHECKCAST java/lang/Double
    INVOKEVIRTUAL java/lang/Double.doubleValue ()D
    DSUB
    INVOKESTATIC java/lang/Math.abs (D)D
    ALOAD 1
    INVOKEVIRTUAL java/lang/Double.doubleValue ()D
    DCMPG
    IFGE L7
   L8
    LINENUMBER 32 L8
    ICONST_1
    INVOKESTATIC java/lang/Boolean.valueOf (Z)Ljava/lang/Boolean;
    ARETURN
   L7
    LINENUMBER 30 L7
   FRAME FULL [java/util/List java/lang/Double I I] []
    IINC 3 1
    GOTO L4
   L5
    LINENUMBER 29 L5
   FRAME FULL [java/util/List java/lang/Double I I] []
    IINC 2 1
    GOTO L1
   L2
    LINENUMBER 36 L2
   FRAME FULL [java/util/List java/lang/Double I] []
    ICONST_0
    INVOKESTATIC java/lang/Boolean.valueOf (Z)Ljava/lang/Boolean;
    ARETURN
   L9
    LOCALVARIABLE j I L4 L5 3
    LOCALVARIABLE i I L1 L2 2
    LOCALVARIABLE numbers Ljava/util/List; L0 L9 0
    // signature Ljava/util/List<Ljava/lang/Double;>;
    // declaration: numbers extends java.util.List<java.lang.Double>
    LOCALVARIABLE threshold Ljava/lang/Double; L0 L9 1
    MAXSTACK = 4
    MAXLOCALS = 4
}

