// class version 55.0 (55)
// access flags 0x20
class original/Solution2272 {

  // compiled from: id_2272.java

  // access flags 0x0
  <init>()V
   L0
    LINENUMBER 3 L0
    ALOAD 0
    INVOKESPECIAL java/lang/Object.<init> ()V
    RETURN
   L1
    LOCALVARIABLE this Loriginal/Solution2272; L0 L1 0
    MAXSTACK = 1
    MAXLOCALS = 1

  // access flags 0x1
  public largestVariance(Ljava/lang/String;)I
   L0
    LINENUMBER 5 L0
    ALOAD 1
    INVOKEVIRTUAL java/lang/String.length ()I
    ISTORE 2
   L1
    LINENUMBER 6 L1
    ICONST_0
    ISTORE 3
   L2
    LINENUMBER 7 L2
    BIPUSH 97
    ISTORE 4
   L3
   FRAME FULL [original/Solution2272 java/lang/String I I I] []
    ILOAD 4
    BIPUSH 122
    IF_ICMPGT L4
   L5
    LINENUMBER 8 L5
    BIPUSH 97
    ISTORE 5
   L6
   FRAME FULL [original/Solution2272 java/lang/String I I I I] []
    ILOAD 5
    BIPUSH 122
    IF_ICMPGT L7
   L8
    LINENUMBER 9 L8
    ILOAD 4
    ILOAD 5
    IF_ICMPNE L9
   L10
    LINENUMBER 10 L10
    GOTO L11
   L9
    LINENUMBER 12 L9
   FRAME FULL [original/Solution2272 java/lang/String I I I I] []
    ICONST_2
    NEWARRAY T_INT
    DUP
    ICONST_0
    ICONST_0
    IASTORE
    DUP
    ICONST_1
    ILOAD 2
    INEG
    IASTORE
    ASTORE 6
   L12
    LINENUMBER 13 L12
    ICONST_0
    ISTORE 7
   L13
   FRAME FULL [original/Solution2272 java/lang/String I I I I [I I] []
    ILOAD 7
    ILOAD 2
    IF_ICMPGE L11
   L14
    LINENUMBER 14 L14
    ALOAD 1
    ILOAD 7
    INVOKEVIRTUAL java/lang/String.charAt (I)C
    ILOAD 4
    IF_ICMPNE L15
   L16
    LINENUMBER 15 L16
    ALOAD 6
    ICONST_0
    DUP2
    IALOAD
    ICONST_1
    ISUB
    IASTORE
   L17
    LINENUMBER 16 L17
    ALOAD 6
    ICONST_1
    DUP2
    IALOAD
    ICONST_1
    IADD
    IASTORE
    GOTO L18
   L15
    LINENUMBER 17 L15
   FRAME FULL [original/Solution2272 java/lang/String I I I I [I I] []
    ALOAD 1
    ILOAD 7
    INVOKEVIRTUAL java/lang/String.charAt (I)C
    ILOAD 5
    IF_ICMPNE L18
   L19
    LINENUMBER 18 L19
    ALOAD 6
    ICONST_1
    ALOAD 6
    ICONST_0
    IALOAD
    ICONST_1
    ISUB
    ALOAD 6
    ICONST_1
    IALOAD
    ICONST_1
    ISUB
    INVOKESTATIC java/lang/Math.max (II)I
    IASTORE
   L20
    LINENUMBER 19 L20
    ALOAD 6
    ICONST_0
    ICONST_0
    IASTORE
   L18
    LINENUMBER 21 L18
   FRAME FULL [original/Solution2272 java/lang/String I I I I [I I] []
    ILOAD 3
    ALOAD 6
    ICONST_1
    IALOAD
    INVOKESTATIC java/lang/Math.max (II)I
    ISTORE 3
   L21
    LINENUMBER 13 L21
    IINC 7 1
    GOTO L13
   L11
    LINENUMBER 8 L11
   FRAME FULL [original/Solution2272 java/lang/String I I I I] []
    ILOAD 5
    ICONST_1
    IADD
    I2C
    ISTORE 5
    GOTO L6
   L7
    LINENUMBER 7 L7
   FRAME FULL [original/Solution2272 java/lang/String I I I I] []
    ILOAD 4
    ICONST_1
    IADD
    I2C
    ISTORE 4
    GOTO L3
   L4
    LINENUMBER 25 L4
   FRAME FULL [original/Solution2272 java/lang/String I I I] []
    ILOAD 3
    IRETURN
   L22
    LOCALVARIABLE i I L13 L11 7
    LOCALVARIABLE f [I L12 L11 6
    LOCALVARIABLE b C L6 L7 5
    LOCALVARIABLE a C L3 L4 4
    LOCALVARIABLE this Loriginal/Solution2272; L0 L22 0
    LOCALVARIABLE s Ljava/lang/String; L0 L22 1
    LOCALVARIABLE n I L1 L22 2
    LOCALVARIABLE ans I L2 L22 3
    MAXSTACK = 5
    MAXLOCALS = 8
}

