// class version 55.0 (55)
// access flags 0x20
class original/RoundedAvg {

  // compiled from: id_103.java
  // access flags 0x19
  public final static INNERCLASS java/lang/invoke/MethodHandles$Lookup java/lang/invoke/MethodHandles Lookup

  // access flags 0x0
  <init>()V
   L0
    LINENUMBER 4 L0
    ALOAD 0
    INVOKESPECIAL java/lang/Object.<init> ()V
    RETURN
   L1
    LOCALVARIABLE this Loriginal/RoundedAvg; L0 L1 0
    MAXSTACK = 1
    MAXLOCALS = 1

  // access flags 0x9
  public static roundedAvg(II)Ljava/lang/Object;
   L0
    LINENUMBER 42 L0
    ILOAD 0
    ILOAD 1
    IF_ICMPLE L1
   L2
    LINENUMBER 43 L2
    ICONST_M1
    INVOKESTATIC java/lang/Integer.valueOf (I)Ljava/lang/Integer;
    ARETURN
   L1
    LINENUMBER 45 L1
   FRAME FULL [I I] []
    ICONST_0
    ISTORE 2
   L3
    LINENUMBER 46 L3
    ILOAD 0
    ISTORE 3
   L4
   FRAME FULL [I I I I] []
    ILOAD 3
    ILOAD 1
    IF_ICMPGT L5
   L6
    LINENUMBER 47 L6
    ILOAD 2
    ILOAD 3
    IADD
    ISTORE 2
   L7
    LINENUMBER 46 L7
    IINC 3 1
    GOTO L4
   L5
    LINENUMBER 49 L5
   FRAME FULL [I I I I] []
    ILOAD 2
    I2D
    DCONST_1
    DMUL
    ILOAD 1
    ILOAD 0
    IADD
    ICONST_1
    IADD
    I2D
    DDIV
    DSTORE 3
   L8
    LINENUMBER 50 L8
    DLOAD 3
    INVOKESTATIC java/lang/Math.rint (D)D
    D2I
    ISTORE 5
   L9
    LINENUMBER 51 L9
    ILOAD 5
    INVOKESTATIC java/lang/Integer.toBinaryString (I)Ljava/lang/String;
    INVOKEDYNAMIC makeConcatWithConstants(Ljava/lang/String;)Ljava/lang/String; [
      // handle kind 0x6 : INVOKESTATIC
      java/lang/invoke/StringConcatFactory.makeConcatWithConstants(Ljava/lang/invoke/MethodHandles$Lookup;Ljava/lang/String;Ljava/lang/invoke/MethodType;Ljava/lang/String;[Ljava/lang/Object;)Ljava/lang/invoke/CallSite;
      // arguments:
      "0b\u0001"
    ]
    ARETURN
   L10
    LOCALVARIABLE i I L4 L5 3
    LOCALVARIABLE n I L0 L10 0
    LOCALVARIABLE m I L0 L10 1
    LOCALVARIABLE sum I L3 L10 2
    LOCALVARIABLE avg D L8 L10 3
    LOCALVARIABLE roundedAvg I L9 L10 5
    MAXSTACK = 4
    MAXLOCALS = 6
}

