// class version 55.0 (55)
// access flags 0x20
class original/Solution1901 {

  // compiled from: id_1901.java

  // access flags 0x0
  <init>()V
   L0
    LINENUMBER 3 L0
    ALOAD 0
    INVOKESPECIAL java/lang/Object.<init> ()V
    RETURN
   L1
    LOCALVARIABLE this Loriginal/Solution1901; L0 L1 0
    MAXSTACK = 1
    MAXLOCALS = 1

  // access flags 0x1
  public findPeakGrid([[I)[I
   L0
    LINENUMBER 5 L0
    ICONST_0
    ISTORE 2
   L1
    ALOAD 1
    ARRAYLENGTH
    ICONST_1
    ISUB
    ISTORE 3
   L2
    LINENUMBER 6 L2
    ALOAD 1
    ICONST_0
    AALOAD
    ARRAYLENGTH
    ISTORE 4
   L3
    LINENUMBER 7 L3
   FRAME FULL [original/Solution1901 [[I I I I] []
    ILOAD 2
    ILOAD 3
    IF_ICMPLT L4
   L5
    LINENUMBER 8 L5
    ILOAD 2
    ILOAD 3
    IADD
    ICONST_1
    ISHR
    ISTORE 5
   L6
    LINENUMBER 9 L6
    ALOAD 0
    ALOAD 1
    ILOAD 5
    AALOAD
    INVOKEVIRTUAL original/Solution1901.maxPos ([I)I
    ISTORE 6
   L7
    LINENUMBER 10 L7
    ALOAD 1
    ILOAD 5
    AALOAD
    ILOAD 6
    IALOAD
    ALOAD 1
    ILOAD 5
    ICONST_1
    IADD
    AALOAD
    ILOAD 6
    IALOAD
    IF_ICMPLE L8
   L9
    LINENUMBER 11 L9
    ILOAD 5
    ISTORE 3
    GOTO L10
   L8
    LINENUMBER 13 L8
   FRAME FULL [original/Solution1901 [[I I I I I I] []
    ILOAD 5
    ICONST_1
    IADD
    ISTORE 2
   L10
    LINENUMBER 15 L10
   FRAME FULL [original/Solution1901 [[I I I I I I] []
    GOTO L3
   L4
    LINENUMBER 16 L4
   FRAME FULL [original/Solution1901 [[I I I I] []
    ICONST_2
    NEWARRAY T_INT
    DUP
    ICONST_0
    ILOAD 2
    IASTORE
    DUP
    ICONST_1
    ALOAD 0
    ALOAD 1
    ILOAD 2
    AALOAD
    INVOKEVIRTUAL original/Solution1901.maxPos ([I)I
    IASTORE
    ARETURN
   L11
    LOCALVARIABLE mid I L6 L10 5
    LOCALVARIABLE j I L7 L10 6
    LOCALVARIABLE this Loriginal/Solution1901; L0 L11 0
    LOCALVARIABLE mat [[I L0 L11 1
    LOCALVARIABLE l I L1 L11 2
    LOCALVARIABLE r I L2 L11 3
    LOCALVARIABLE n I L3 L11 4
    MAXSTACK = 6
    MAXLOCALS = 7

  // access flags 0x2
  private maxPos([I)I
   L0
    LINENUMBER 20 L0
    ICONST_0
    ISTORE 2
   L1
    LINENUMBER 21 L1
    ICONST_1
    ISTORE 3
   L2
   FRAME FULL [original/Solution1901 [I I I] []
    ILOAD 3
    ALOAD 1
    ARRAYLENGTH
    IF_ICMPGE L3
   L4
    LINENUMBER 22 L4
    ALOAD 1
    ILOAD 2
    IALOAD
    ALOAD 1
    ILOAD 3
    IALOAD
    IF_ICMPGE L5
   L6
    LINENUMBER 23 L6
    ILOAD 3
    ISTORE 2
   L5
    LINENUMBER 21 L5
   FRAME FULL [original/Solution1901 [I I I] []
    IINC 3 1
    GOTO L2
   L3
    LINENUMBER 26 L3
   FRAME FULL [original/Solution1901 [I I I] []
    ILOAD 2
    IRETURN
   L7
    LOCALVARIABLE i I L2 L3 3
    LOCALVARIABLE this Loriginal/Solution1901; L0 L7 0
    LOCALVARIABLE arr [I L0 L7 1
    LOCALVARIABLE j I L1 L7 2
    MAXSTACK = 3
    MAXLOCALS = 4
}

