// class version 55.0 (55)
// access flags 0x20
class original/Solution0593 {

  // compiled from: id_0593.java

  // access flags 0x0
  <init>()V
   L0
    LINENUMBER 3 L0
    ALOAD 0
    INVOKESPECIAL java/lang/Object.<init> ()V
    RETURN
   L1
    LOCALVARIABLE this Loriginal/Solution0593; L0 L1 0
    MAXSTACK = 1
    MAXLOCALS = 1

  // access flags 0x1
  public validSquare([I[I[I[I)Z
   L0
    LINENUMBER 5 L0
    ALOAD 0
    ALOAD 1
    ALOAD 2
    ALOAD 3
    INVOKEVIRTUAL original/Solution0593.check ([I[I[I)Z
    IFEQ L1
    ALOAD 0
    ALOAD 1
    ALOAD 3
    ALOAD 4
    INVOKEVIRTUAL original/Solution0593.check ([I[I[I)Z
    IFEQ L1
    ALOAD 0
    ALOAD 1
    ALOAD 2
    ALOAD 4
    INVOKEVIRTUAL original/Solution0593.check ([I[I[I)Z
    IFEQ L1
    ALOAD 0
    ALOAD 2
    ALOAD 3
    ALOAD 4
    INVOKEVIRTUAL original/Solution0593.check ([I[I[I)Z
    IFEQ L1
    ICONST_1
    GOTO L2
   L1
   FRAME FULL [original/Solution0593 [I [I [I [I] []
    ICONST_0
   L2
   FRAME FULL [original/Solution0593 [I [I [I [I] [I]
    IRETURN
   L3
    LOCALVARIABLE this Loriginal/Solution0593; L0 L3 0
    LOCALVARIABLE p1 [I L0 L3 1
    LOCALVARIABLE p2 [I L0 L3 2
    LOCALVARIABLE p3 [I L0 L3 3
    LOCALVARIABLE p4 [I L0 L3 4
    MAXSTACK = 4
    MAXLOCALS = 5

  // access flags 0x2
  private check([I[I[I)Z
   L0
    LINENUMBER 9 L0
    ALOAD 1
    ICONST_0
    IALOAD
    ISTORE 4
   L1
    ALOAD 1
    ICONST_1
    IALOAD
    ISTORE 5
   L2
    LINENUMBER 10 L2
    ALOAD 2
    ICONST_0
    IALOAD
    ISTORE 6
   L3
    ALOAD 2
    ICONST_1
    IALOAD
    ISTORE 7
   L4
    LINENUMBER 11 L4
    ALOAD 3
    ICONST_0
    IALOAD
    ISTORE 8
   L5
    ALOAD 3
    ICONST_1
    IALOAD
    ISTORE 9
   L6
    LINENUMBER 12 L6
    ILOAD 4
    ILOAD 6
    ISUB
    ILOAD 4
    ILOAD 6
    ISUB
    IMUL
    ILOAD 5
    ILOAD 7
    ISUB
    ILOAD 5
    ILOAD 7
    ISUB
    IMUL
    IADD
    ISTORE 10
   L7
    LINENUMBER 13 L7
    ILOAD 4
    ILOAD 8
    ISUB
    ILOAD 4
    ILOAD 8
    ISUB
    IMUL
    ILOAD 5
    ILOAD 9
    ISUB
    ILOAD 5
    ILOAD 9
    ISUB
    IMUL
    IADD
    ISTORE 11
   L8
    LINENUMBER 14 L8
    ILOAD 6
    ILOAD 8
    ISUB
    ILOAD 6
    ILOAD 8
    ISUB
    IMUL
    ILOAD 7
    ILOAD 9
    ISUB
    ILOAD 7
    ILOAD 9
    IADD
    IMUL
    IADD
    ISTORE 12
   L9
    LINENUMBER 15 L9
    ILOAD 10
    ILOAD 11
    IF_ICMPNE L10
    ILOAD 10
    ILOAD 11
    IADD
    ILOAD 12
    IF_ICMPNE L10
    ILOAD 10
    IFLE L10
   L11
    LINENUMBER 16 L11
    ICONST_1
    IRETURN
   L10
    LINENUMBER 18 L10
   FRAME FULL [original/Solution0593 [I [I [I I I I I I I I I I] []
    ILOAD 10
    ILOAD 12
    IF_ICMPNE L12
    ILOAD 10
    ILOAD 12
    IADD
    ILOAD 11
    IF_ICMPNE L12
    ILOAD 10
    IFLE L12
   L13
    LINENUMBER 19 L13
    ICONST_1
    IRETURN
   L12
    LINENUMBER 21 L12
   FRAME FULL [original/Solution0593 [I [I [I I I I I I I I I I] []
    ILOAD 11
    ILOAD 12
    IF_ICMPNE L14
    ILOAD 11
    ILOAD 12
    IADD
    ILOAD 10
    IF_ICMPNE L14
    ILOAD 11
    IFLE L14
   L15
    LINENUMBER 22 L15
    ICONST_1
    IRETURN
   L14
    LINENUMBER 24 L14
   FRAME FULL [original/Solution0593 [I [I [I I I I I I I I I I] []
    ICONST_0
    IRETURN
   L16
    LOCALVARIABLE this Loriginal/Solution0593; L0 L16 0
    LOCALVARIABLE a [I L0 L16 1
    LOCALVARIABLE b [I L0 L16 2
    LOCALVARIABLE c [I L0 L16 3
    LOCALVARIABLE x1 I L1 L16 4
    LOCALVARIABLE y1 I L2 L16 5
    LOCALVARIABLE x2 I L3 L16 6
    LOCALVARIABLE y2 I L4 L16 7
    LOCALVARIABLE x3 I L5 L16 8
    LOCALVARIABLE y3 I L6 L16 9
    LOCALVARIABLE d1 I L7 L16 10
    LOCALVARIABLE d2 I L8 L16 11
    LOCALVARIABLE d3 I L9 L16 12
    MAXSTACK = 4
    MAXLOCALS = 13
}

