// class version 55.0 (55)
// access flags 0x20
class original/Solution2387 {

  // compiled from: id_2387.java

  // access flags 0x2
  private [[I grid

  // access flags 0x0
  <init>()V
   L0
    LINENUMBER 3 L0
    ALOAD 0
    INVOKESPECIAL java/lang/Object.<init> ()V
    RETURN
   L1
    LOCALVARIABLE this Loriginal/Solution2387; L0 L1 0
    MAXSTACK = 1
    MAXLOCALS = 1

  // access flags 0x1
  public matrixMedian([[I)I
   L0
    LINENUMBER 7 L0
    ALOAD 0
    ALOAD 1
    PUTFIELD original/Solution2387.grid : [[I
   L1
    LINENUMBER 8 L1
    ALOAD 1
    ARRAYLENGTH
    ISTORE 2
   L2
    ALOAD 1
    ICONST_0
    AALOAD
    ARRAYLENGTH
    ISTORE 3
   L3
    LINENUMBER 9 L3
    ILOAD 2
    ILOAD 3
    IMUL
    ICONST_1
    IADD
    ICONST_1
    ISHR
    ISTORE 4
   L4
    LINENUMBER 10 L4
    ICONST_0
    ISTORE 5
   L5
    LDC 1000010
    ISTORE 6
   L6
    LINENUMBER 11 L6
   FRAME FULL [original/Solution2387 [[I I I I I I] []
    ILOAD 5
    ILOAD 6
    IF_ICMPGE L7
   L8
    LINENUMBER 12 L8
    ILOAD 5
    ILOAD 6
    IADD
    ICONST_1
    ISHR
    ISTORE 7
   L9
    LINENUMBER 13 L9
    ALOAD 0
    ILOAD 7
    INVOKEVIRTUAL original/Solution2387.count (I)I
    ILOAD 4
    IF_ICMPLT L10
   L11
    LINENUMBER 14 L11
    ILOAD 7
    ISTORE 6
    GOTO L12
   L10
    LINENUMBER 16 L10
   FRAME FULL [original/Solution2387 [[I I I I I I I] []
    ILOAD 7
    ICONST_1
    IADD
    ISTORE 5
   L12
    LINENUMBER 18 L12
   FRAME FULL [original/Solution2387 [[I I I I I I] []
    GOTO L6
   L7
    LINENUMBER 19 L7
   FRAME FULL [original/Solution2387 [[I I I I I I] []
    ILOAD 5
    IRETURN
   L13
    LOCALVARIABLE mid I L9 L12 7
    LOCALVARIABLE this Loriginal/Solution2387; L0 L13 0
    LOCALVARIABLE grid [[I L0 L13 1
    LOCALVARIABLE m I L2 L13 2
    LOCALVARIABLE n I L3 L13 3
    LOCALVARIABLE target I L4 L13 4
    LOCALVARIABLE left I L5 L13 5
    LOCALVARIABLE right I L6 L13 6
    MAXSTACK = 2
    MAXLOCALS = 8

  // access flags 0x2
  private count(I)I
   L0
    LINENUMBER 23 L0
    ICONST_0
    ISTORE 2
   L1
    LINENUMBER 24 L1
    ALOAD 0
    GETFIELD original/Solution2387.grid : [[I
    ASTORE 3
    ALOAD 3
    ARRAYLENGTH
    ISTORE 4
    ICONST_0
    ISTORE 5
   L2
   FRAME FULL [original/Solution2387 I I [[I I I] []
    ILOAD 5
    ILOAD 4
    IF_ICMPGE L3
    ALOAD 3
    ILOAD 5
    AALOAD
    ASTORE 6
   L4
    LINENUMBER 25 L4
    ICONST_0
    ISTORE 7
   L5
    ALOAD 6
    ARRAYLENGTH
    ISTORE 8
   L6
    LINENUMBER 26 L6
   FRAME FULL [original/Solution2387 I I [[I I I [I I I] []
    ILOAD 7
    ILOAD 8
    IF_ICMPGE L7
   L8
    LINENUMBER 27 L8
    ILOAD 7
    ILOAD 8
    IADD
    ICONST_1
    ISHR
    ISTORE 9
   L9
    LINENUMBER 28 L9
    ALOAD 6
    ILOAD 9
    IALOAD
    ILOAD 1
    IF_ICMPLE L10
   L11
    LINENUMBER 29 L11
    ILOAD 9
    ISTORE 8
    GOTO L12
   L10
    LINENUMBER 31 L10
   FRAME FULL [original/Solution2387 I I [[I I I [I I I I] []
    ILOAD 9
    ICONST_1
    IADD
    ISTORE 7
   L12
    LINENUMBER 33 L12
   FRAME FULL [original/Solution2387 I I [[I I I [I I I] []
    GOTO L6
   L7
    LINENUMBER 34 L7
   FRAME FULL [original/Solution2387 I I [[I I I [I I I] []
    ILOAD 2
    ILOAD 7
    IADD
    ISTORE 2
   L13
    LINENUMBER 24 L13
    IINC 5 1
    GOTO L2
   L3
    LINENUMBER 36 L3
   FRAME FULL [original/Solution2387 I I] []
    ILOAD 2
    IRETURN
   L14
    LOCALVARIABLE mid I L9 L12 9
    LOCALVARIABLE left I L5 L13 7
    LOCALVARIABLE right I L6 L13 8
    LOCALVARIABLE row [I L4 L13 6
    LOCALVARIABLE this Loriginal/Solution2387; L0 L14 0
    LOCALVARIABLE x I L0 L14 1
    LOCALVARIABLE cnt I L1 L14 2
    MAXSTACK = 2
    MAXLOCALS = 10
}

