// class version 55.0 (55)
// access flags 0x20
class original/Solution3417 {

  // compiled from: id_3417.java

  // access flags 0x0
  <init>()V
   L0
    LINENUMBER 5 L0
    ALOAD 0
    INVOKESPECIAL java/lang/Object.<init> ()V
    RETURN
   L1
    LOCALVARIABLE this Loriginal/Solution3417; L0 L1 0
    MAXSTACK = 1
    MAXLOCALS = 1

  // access flags 0x1
  // signature ([[I)Ljava/util/List<Ljava/lang/Integer;>;
  // declaration: java.util.List<java.lang.Integer> zigzagTraversal(int[][])
  public zigzagTraversal([[I)Ljava/util/List;
   L0
    LINENUMBER 7 L0
    ICONST_1
    ISTORE 2
   L1
    LINENUMBER 8 L1
    NEW java/util/ArrayList
    DUP
    INVOKESPECIAL java/util/ArrayList.<init> ()V
    ASTORE 3
   L2
    LINENUMBER 9 L2
    ICONST_0
    ISTORE 4
   L3
   FRAME FULL [original/Solution3417 [[I I java/util/ArrayList I] []
    ILOAD 4
    ALOAD 1
    ARRAYLENGTH
    IF_ICMPGE L4
   L5
    LINENUMBER 10 L5
    ILOAD 4
    ICONST_2
    IREM
    ICONST_1
    IF_ICMPNE L6
   L7
    LINENUMBER 11 L7
    ALOAD 0
    ALOAD 1
    ILOAD 4
    AALOAD
    INVOKEVIRTUAL original/Solution3417.reverse ([I)V
   L6
    LINENUMBER 13 L6
   FRAME FULL [original/Solution3417 [[I I java/util/ArrayList I] []
    ALOAD 1
    ILOAD 4
    AALOAD
    ASTORE 5
    ALOAD 5
    ARRAYLENGTH
    ISTORE 6
    ICONST_0
    ISTORE 7
   L8
   FRAME FULL [original/Solution3417 [[I I java/util/ArrayList I [I I I] []
    ILOAD 7
    ILOAD 6
    IF_ICMPGE L9
    ALOAD 5
    ILOAD 7
    IALOAD
    ISTORE 8
   L10
    LINENUMBER 14 L10
    ILOAD 2
    IFEQ L11
   L12
    LINENUMBER 15 L12
    ALOAD 3
    ILOAD 8
    INVOKESTATIC java/lang/Integer.valueOf (I)Ljava/lang/Integer;
    INVOKEINTERFACE java/util/List.add (Ljava/lang/Object;)Z (itf)
    POP
   L11
    LINENUMBER 17 L11
   FRAME FULL [original/Solution3417 [[I I java/util/ArrayList I [I I I I] []
    ILOAD 2
    IFNE L13
    ICONST_1
    GOTO L14
   L13
   FRAME FULL [original/Solution3417 [[I I java/util/ArrayList I [I I I I] []
    ICONST_0
   L14
   FRAME FULL [original/Solution3417 [[I I java/util/ArrayList I [I I I I] [I]
    ISTORE 2
   L15
    LINENUMBER 13 L15
    IINC 7 1
    GOTO L8
   L9
    LINENUMBER 9 L9
   FRAME FULL [original/Solution3417 [[I I java/util/ArrayList I [I I I] []
    IINC 4 1
    GOTO L3
   L4
    LINENUMBER 20 L4
   FRAME FULL [original/Solution3417 [[I I java/util/ArrayList I] []
    ALOAD 3
    ARETURN
   L16
    LOCALVARIABLE x I L10 L15 8
    LOCALVARIABLE i I L3 L4 4
    LOCALVARIABLE this Loriginal/Solution3417; L0 L16 0
    LOCALVARIABLE grid [[I L0 L16 1
    LOCALVARIABLE ok Z L1 L16 2
    LOCALVARIABLE ans Ljava/util/List; L2 L16 3
    // signature Ljava/util/List<Ljava/lang/Integer;>;
    // declaration: ans extends java.util.List<java.lang.Integer>
    MAXSTACK = 3
    MAXLOCALS = 9

  // access flags 0x2
  private reverse([I)V
   L0
    LINENUMBER 24 L0
    ICONST_0
    ISTORE 2
   L1
    ALOAD 1
    ARRAYLENGTH
    ICONST_1
    ISUB
    ISTORE 3
   L2
   FRAME FULL [original/Solution3417 [I I I] []
    ILOAD 2
    ILOAD 3
    IF_ICMPGE L3
   L4
    LINENUMBER 25 L4
    ALOAD 1
    ILOAD 2
    IALOAD
    ISTORE 4
   L5
    LINENUMBER 26 L5
    ALOAD 1
    ILOAD 2
    ALOAD 1
    ILOAD 3
    IALOAD
    IASTORE
   L6
    LINENUMBER 27 L6
    ALOAD 1
    ILOAD 3
    ILOAD 4
    IASTORE
   L7
    LINENUMBER 24 L7
    IINC 2 1
    IINC 3 1
    GOTO L2
   L3
    LINENUMBER 29 L3
   FRAME FULL [original/Solution3417 [I I I] []
    RETURN
   L8
    LOCALVARIABLE t I L5 L7 4
    LOCALVARIABLE i I L1 L3 2
    LOCALVARIABLE j I L2 L3 3
    LOCALVARIABLE this Loriginal/Solution3417; L0 L8 0
    LOCALVARIABLE nums [I L0 L8 1
    MAXSTACK = 4
    MAXLOCALS = 5
}

