// class version 55.0 (55)
// access flags 0x20
class original/Solution2156 {

  // compiled from: id_2156.java

  // access flags 0x0
  <init>()V
   L0
    LINENUMBER 3 L0
    ALOAD 0
    INVOKESPECIAL java/lang/Object.<init> ()V
    RETURN
   L1
    LOCALVARIABLE this Loriginal/Solution2156; L0 L1 0
    MAXSTACK = 1
    MAXLOCALS = 1

  // access flags 0x1
  public subStrHash(Ljava/lang/String;IIII)Ljava/lang/String;
   L0
    LINENUMBER 5 L0
    LCONST_0
    LSTORE 6
   L1
    LCONST_1
    LSTORE 8
   L2
    LINENUMBER 6 L2
    ALOAD 1
    INVOKEVIRTUAL java/lang/String.length ()I
    ISTORE 10
   L3
    LINENUMBER 7 L3
    ILOAD 10
    ICONST_1
    ISUB
    ISTORE 11
   L4
   FRAME FULL [original/Solution2156 java/lang/String I I I I J J I I] []
    ILOAD 11
    ILOAD 10
    ILOAD 4
    ISUB
    IF_ICMPLT L5
   L6
    LINENUMBER 8 L6
    ALOAD 1
    ILOAD 11
    INVOKEVIRTUAL java/lang/String.charAt (I)C
    BIPUSH 97
    ISUB
    ICONST_1
    IADD
    ISTORE 12
   L7
    LINENUMBER 9 L7
    LLOAD 6
    ILOAD 2
    I2L
    LMUL
    ILOAD 3
    I2L
    LREM
    ILOAD 12
    I2L
    LADD
    ILOAD 3
    I2L
    LREM
    LSTORE 6
   L8
    LINENUMBER 10 L8
    ILOAD 11
    ILOAD 10
    ILOAD 4
    ISUB
    IF_ICMPEQ L9
   L10
    LINENUMBER 11 L10
    LLOAD 8
    ILOAD 2
    I2L
    LMUL
    ILOAD 3
    I2L
    LREM
    LSTORE 8
   L9
    LINENUMBER 7 L9
   FRAME FULL [original/Solution2156 java/lang/String I I I I J J I I I] []
    IINC 11 -1
    GOTO L4
   L5
    LINENUMBER 14 L5
   FRAME FULL [original/Solution2156 java/lang/String I I I I J J I I] []
    ILOAD 10
    ILOAD 4
    ISUB
    ISTORE 11
   L11
    LINENUMBER 15 L11
    ILOAD 10
    ILOAD 4
    ISUB
    ICONST_1
    ISUB
    ISTORE 12
   L12
   FRAME FULL [original/Solution2156 java/lang/String I I I I J J I I I] []
    ILOAD 12
    IFLT L13
   L14
    LINENUMBER 16 L14
    ALOAD 1
    ILOAD 12
    ILOAD 4
    IADD
    INVOKEVIRTUAL java/lang/String.charAt (I)C
    BIPUSH 97
    ISUB
    ICONST_1
    IADD
    ISTORE 13
   L15
    LINENUMBER 17 L15
    ALOAD 1
    ILOAD 12
    INVOKEVIRTUAL java/lang/String.charAt (I)C
    BIPUSH 97
    ISUB
    ICONST_1
    IADD
    ISTORE 14
   L16
    LINENUMBER 18 L16
    LLOAD 6
    ILOAD 13
    I2L
    LLOAD 8
    LMUL
    ILOAD 3
    I2L
    LREM
    LSUB
    ILOAD 3
    I2L
    LSUB
    ILOAD 2
    I2L
    LMUL
    ILOAD 3
    I2L
    LREM
    ILOAD 14
    I2L
    LADD
    ILOAD 3
    I2L
    LREM
    LSTORE 6
   L17
    LINENUMBER 19 L17
    LLOAD 6
    ILOAD 5
    I2L
    LCMP
    IFNE L18
   L19
    LINENUMBER 20 L19
    ILOAD 12
    ISTORE 11
   L18
    LINENUMBER 15 L18
   FRAME FULL [original/Solution2156 java/lang/String I I I I J J I I I I I] []
    IINC 12 -1
    GOTO L12
   L13
    LINENUMBER 23 L13
   FRAME FULL [original/Solution2156 java/lang/String I I I I J J I I I] []
    ALOAD 1
    ILOAD 11
    ILOAD 11
    ILOAD 4
    IADD
    INVOKEVIRTUAL java/lang/String.substring (II)Ljava/lang/String;
    ARETURN
   L20
    LOCALVARIABLE val I L7 L9 12
    LOCALVARIABLE i I L4 L5 11
    LOCALVARIABLE pre I L15 L18 13
    LOCALVARIABLE cur I L16 L18 14
    LOCALVARIABLE i I L12 L13 12
    LOCALVARIABLE this Loriginal/Solution2156; L0 L20 0
    LOCALVARIABLE s Ljava/lang/String; L0 L20 1
    LOCALVARIABLE power I L0 L20 2
    LOCALVARIABLE modulo I L0 L20 3
    LOCALVARIABLE k I L0 L20 4
    LOCALVARIABLE hashValue I L0 L20 5
    LOCALVARIABLE h J L1 L20 6
    LOCALVARIABLE p J L2 L20 8
    LOCALVARIABLE n I L3 L20 10
    LOCALVARIABLE j I L11 L20 11
    MAXSTACK = 6
    MAXLOCALS = 15
}

