// class version 55.0 (55)
// access flags 0x20
class original/FruitDistribution {

  // compiled from: id_67.java

  // access flags 0x0
  <init>()V
   L0
    LINENUMBER 3 L0
    ALOAD 0
    INVOKESPECIAL java/lang/Object.<init> ()V
    RETURN
   L1
    LOCALVARIABLE this Loriginal/FruitDistribution; L0 L1 0
    MAXSTACK = 1
    MAXLOCALS = 1

  // access flags 0x9
  public static fruitDistribution(Ljava/lang/String;I)I
   L0
    LINENUMBER 33 L0
    ICONST_0
    ISTORE 2
   L1
    LINENUMBER 34 L1
    ICONST_0
    ISTORE 3
   L2
    LINENUMBER 35 L2
    ICONST_0
    ISTORE 4
   L3
    LINENUMBER 36 L3
    ALOAD 0
    LDC " "
    INVOKEVIRTUAL java/lang/String.split (Ljava/lang/String;)[Ljava/lang/String;
    ASTORE 5
   L4
    LINENUMBER 37 L4
    ICONST_0
    ISTORE 6
   L5
   FRAME FULL [java/lang/String I I I I [Ljava/lang/String; I] []
    ILOAD 6
    ALOAD 5
    ARRAYLENGTH
    IF_ICMPGE L6
   L7
    LINENUMBER 38 L7
    ALOAD 5
    ILOAD 6
    AALOAD
    LDC "apples"
    INVOKEVIRTUAL java/lang/String.equals (Ljava/lang/Object;)Z
    IFNE L8
   L9
    LINENUMBER 39 L9
    ALOAD 5
    ILOAD 6
    ICONST_1
    ISUB
    AALOAD
    INVOKESTATIC java/lang/Integer.parseInt (Ljava/lang/String;)I
    ISTORE 2
   L8
    LINENUMBER 41 L8
   FRAME FULL [java/lang/String I I I I [Ljava/lang/String; I] []
    ALOAD 5
    ILOAD 6
    AALOAD
    LDC "oranges"
    INVOKEVIRTUAL java/lang/String.equals (Ljava/lang/Object;)Z
    IFEQ L10
   L11
    LINENUMBER 42 L11
    ALOAD 5
    ILOAD 6
    ICONST_1
    ISUB
    AALOAD
    INVOKESTATIC java/lang/Integer.parseInt (Ljava/lang/String;)I
    ISTORE 3
   L10
    LINENUMBER 37 L10
   FRAME FULL [java/lang/String I I I I [Ljava/lang/String; I] []
    IINC 6 1
    GOTO L5
   L6
    LINENUMBER 45 L6
   FRAME FULL [java/lang/String I I I I [Ljava/lang/String; I] []
    ILOAD 1
    ILOAD 2
    ISUB
    ILOAD 3
    ISUB
    ISTORE 4
   L12
    LINENUMBER 46 L12
    ILOAD 4
    IRETURN
   L13
    LOCALVARIABLE i I L5 L6 6
    LOCALVARIABLE s Ljava/lang/String; L0 L13 0
    LOCALVARIABLE n I L0 L13 1
    LOCALVARIABLE apples I L1 L13 2
    LOCALVARIABLE oranges I L2 L13 3
    LOCALVARIABLE mangoes I L3 L13 4
    LOCALVARIABLE words [Ljava/lang/String; L4 L13 5
    MAXSTACK = 3
    MAXLOCALS = 7
}

