// class version 55.0 (55)
// access flags 0x20
class original/AddElements {

  // compiled from: id_122.java

  // access flags 0x0
  <init>()V
   L0
    LINENUMBER 7 L0
    ALOAD 0
    INVOKESPECIAL java/lang/Object.<init> ()V
    RETURN
   L1
    LOCALVARIABLE this Loriginal/AddElements; L0 L1 0
    MAXSTACK = 1
    MAXLOCALS = 1

  // access flags 0x9
  // signature (Ljava/util/List<Ljava/lang/Integer;>;I)I
  // declaration: int addElements(java.util.List<java.lang.Integer>, int)
  public static addElements(Ljava/util/List;I)I
   L0
    LINENUMBER 33 L0
    ICONST_0
    ISTORE 2
   L1
    LINENUMBER 34 L1
    ICONST_0
    ISTORE 3
   L2
   FRAME FULL [java/util/List I I I] []
    ILOAD 3
    ILOAD 1
    IF_ICMPLT L3
   L4
    LINENUMBER 35 L4
    ALOAD 0
    ILOAD 3
    INVOKEINTERFACE java/util/List.get (I)Ljava/lang/Object; (itf)
    CHECKCAST java/lang/Integer
    INVOKEVIRTUAL java/lang/Integer.intValue ()I
    BIPUSH 100
    IF_ICMPGE L5
   L6
    LINENUMBER 36 L6
    ILOAD 2
    ALOAD 0
    ILOAD 3
    INVOKEINTERFACE java/util/List.get (I)Ljava/lang/Object; (itf)
    CHECKCAST java/lang/Integer
    INVOKEVIRTUAL java/lang/Integer.intValue ()I
    IADD
    ISTORE 2
   L5
    LINENUMBER 34 L5
   FRAME FULL [java/util/List I I I] []
    IINC 3 1
    GOTO L2
   L3
    LINENUMBER 39 L3
   FRAME FULL [java/util/List I I I] []
    ILOAD 2
    IRETURN
   L7
    LOCALVARIABLE i I L2 L3 3
    LOCALVARIABLE arr Ljava/util/List; L0 L7 0
    // signature Ljava/util/List<Ljava/lang/Integer;>;
    // declaration: arr extends java.util.List<java.lang.Integer>
    LOCALVARIABLE k I L0 L7 1
    LOCALVARIABLE sum I L1 L7 2
    MAXSTACK = 3
    MAXLOCALS = 4
}

