// class version 55.0 (55)
// access flags 0x20
class original/NextSmallest {

  // compiled from: id_90.java

  // access flags 0x0
  <init>()V
   L0
    LINENUMBER 7 L0
    ALOAD 0
    INVOKESPECIAL java/lang/Object.<init> ()V
    RETURN
   L1
    LOCALVARIABLE this Loriginal/NextSmallest; L0 L1 0
    MAXSTACK = 1
    MAXLOCALS = 1

  // access flags 0x9
  // signature (Ljava/util/List<Ljava/lang/Object;>;)Ljava/lang/Integer;
  // declaration: java.lang.Integer nextSmallest(java.util.List<java.lang.Object>)
  public static nextSmallest(Ljava/util/List;)Ljava/lang/Integer;
   L0
    LINENUMBER 34 L0
    ALOAD 0
    INVOKEINTERFACE java/util/List.size ()I (itf)
    ICONST_1
    IF_ICMPGT L1
   L2
    LINENUMBER 35 L2
    ACONST_NULL
    ARETURN
   L1
    LINENUMBER 37 L1
   FRAME FULL [java/util/List] []
    ALOAD 0
    ICONST_0
    INVOKEINTERFACE java/util/List.get (I)Ljava/lang/Object; (itf)
    CHECKCAST java/lang/Integer
    ASTORE 1
   L3
    LINENUMBER 38 L3
    ACONST_NULL
    ASTORE 2
   L4
    LINENUMBER 39 L4
    ICONST_1
    ISTORE 3
   L5
   FRAME FULL [java/util/List java/lang/Integer java/lang/Integer I] []
    ILOAD 3
    ALOAD 0
    INVOKEINTERFACE java/util/List.size ()I (itf)
    IF_ICMPGE L6
   L7
    LINENUMBER 40 L7
    ALOAD 0
    ILOAD 3
    INVOKEINTERFACE java/util/List.get (I)Ljava/lang/Object; (itf)
    CHECKCAST java/lang/Integer
    ASTORE 4
   L8
    LINENUMBER 41 L8
    ALOAD 4
    INVOKEVIRTUAL java/lang/Integer.intValue ()I
    ALOAD 1
    INVOKEVIRTUAL java/lang/Integer.intValue ()I
    IF_ICMPGT L9
   L10
    LINENUMBER 42 L10
    ALOAD 1
    ASTORE 2
   L11
    LINENUMBER 43 L11
    ALOAD 4
    ASTORE 1
    GOTO L12
   L9
    LINENUMBER 44 L9
   FRAME FULL [java/util/List java/lang/Integer java/lang/Integer I java/lang/Integer] []
    ALOAD 2
    IFNULL L13
    ALOAD 4
    INVOKEVIRTUAL java/lang/Integer.intValue ()I
    ALOAD 2
    INVOKEVIRTUAL java/lang/Integer.intValue ()I
    IF_ICMPGE L12
   L13
    LINENUMBER 45 L13
   FRAME FULL [java/util/List java/lang/Integer java/lang/Integer I java/lang/Integer] []
    ALOAD 4
    ALOAD 1
    IF_ACMPEQ L12
   L14
    LINENUMBER 46 L14
    ALOAD 4
    ASTORE 2
   L12
    LINENUMBER 39 L12
   FRAME FULL [java/util/List java/lang/Integer java/lang/Integer I java/lang/Integer] []
    IINC 3 1
    GOTO L5
   L6
    LINENUMBER 49 L6
   FRAME FULL [java/util/List java/lang/Integer java/lang/Integer I] []
    ALOAD 2
    ARETURN
   L15
    LOCALVARIABLE current Ljava/lang/Integer; L8 L12 4
    LOCALVARIABLE i I L5 L6 3
    LOCALVARIABLE lst Ljava/util/List; L0 L15 0
    // signature Ljava/util/List<Ljava/lang/Object;>;
    // declaration: lst extends java.util.List<java.lang.Object>
    LOCALVARIABLE smallest Ljava/lang/Integer; L3 L15 1
    LOCALVARIABLE nextSmallest Ljava/lang/Integer; L4 L15 2
    MAXSTACK = 2
    MAXLOCALS = 5
}

