// class version 55.0 (55)
// access flags 0x20
class original/SumProduct {

  // compiled from: id_8.java

  // access flags 0x0
  <init>()V
   L0
    LINENUMBER 7 L0
    ALOAD 0
    INVOKESPECIAL java/lang/Object.<init> ()V
    RETURN
   L1
    LOCALVARIABLE this Loriginal/SumProduct; L0 L1 0
    MAXSTACK = 1
    MAXLOCALS = 1

  // access flags 0x9
  // signature (Ljava/util/List<Ljava/lang/Object;>;)Ljava/util/List<Ljava/lang/Integer;>;
  // declaration: java.util.List<java.lang.Integer> sumProduct(java.util.List<java.lang.Object>)
  public static sumProduct(Ljava/util/List;)Ljava/util/List;
   L0
    LINENUMBER 26 L0
    ICONST_0
    INVOKESTATIC java/lang/Integer.valueOf (I)Ljava/lang/Integer;
    ASTORE 1
   L1
    LINENUMBER 27 L1
    ICONST_1
    INVOKESTATIC java/lang/Integer.valueOf (I)Ljava/lang/Integer;
    ASTORE 2
   L2
    LINENUMBER 28 L2
    ALOAD 0
    INVOKEINTERFACE java/util/List.iterator ()Ljava/util/Iterator; (itf)
    ASTORE 3
   L3
   FRAME FULL [java/util/List java/lang/Integer java/lang/Integer java/util/Iterator] []
    ALOAD 3
    INVOKEINTERFACE java/util/Iterator.hasNext ()Z (itf)
    IFEQ L4
    ALOAD 3
    INVOKEINTERFACE java/util/Iterator.next ()Ljava/lang/Object; (itf)
    ASTORE 4
   L5
    LINENUMBER 29 L5
    ALOAD 4
    INSTANCEOF java/lang/Integer
    IFEQ L6
   L7
    LINENUMBER 30 L7
    ALOAD 1
    INVOKEVIRTUAL java/lang/Integer.intValue ()I
    ALOAD 4
    CHECKCAST java/lang/Integer
    INVOKEVIRTUAL java/lang/Integer.intValue ()I
    IADD
    INVOKESTATIC java/lang/Integer.valueOf (I)Ljava/lang/Integer;
    ASTORE 1
   L8
    LINENUMBER 31 L8
    ALOAD 2
    INVOKEVIRTUAL java/lang/Integer.intValue ()I
    ALOAD 4
    CHECKCAST java/lang/Integer
    INVOKEVIRTUAL java/lang/Integer.intValue ()I
    IMUL
    INVOKESTATIC java/lang/Integer.valueOf (I)Ljava/lang/Integer;
    ASTORE 2
    GOTO L9
   L6
    LINENUMBER 33 L6
   FRAME FULL [java/util/List java/lang/Integer java/lang/Integer java/util/Iterator java/lang/Object] []
    NEW java/lang/IllegalArgumentException
    DUP
    LDC "Invalid number type"
    INVOKESPECIAL java/lang/IllegalArgumentException.<init> (Ljava/lang/String;)V
    ATHROW
   L9
    LINENUMBER 35 L9
   FRAME FULL [java/util/List java/lang/Integer java/lang/Integer java/util/Iterator] []
    GOTO L3
   L4
    LINENUMBER 36 L4
   FRAME FULL [java/util/List java/lang/Integer java/lang/Integer] []
    NEW java/util/ArrayList
    DUP
    INVOKESPECIAL java/util/ArrayList.<init> ()V
    ASTORE 3
   L10
    LINENUMBER 37 L10
    ALOAD 3
    ALOAD 1
    INVOKEINTERFACE java/util/List.add (Ljava/lang/Object;)Z (itf)
    POP
   L11
    LINENUMBER 38 L11
    ALOAD 3
    ALOAD 2
    INVOKEINTERFACE java/util/List.add (Ljava/lang/Object;)Z (itf)
    POP
   L12
    LINENUMBER 39 L12
    ALOAD 3
    ARETURN
   L13
    LOCALVARIABLE number Ljava/lang/Object; L5 L9 4
    LOCALVARIABLE numbers Ljava/util/List; L0 L13 0
    // signature Ljava/util/List<Ljava/lang/Object;>;
    // declaration: numbers extends java.util.List<java.lang.Object>
    LOCALVARIABLE sum Ljava/lang/Integer; L1 L13 1
    LOCALVARIABLE product Ljava/lang/Integer; L2 L13 2
    LOCALVARIABLE result Ljava/util/List; L10 L13 3
    // signature Ljava/util/List<Ljava/lang/Integer;>;
    // declaration: result extends java.util.List<java.lang.Integer>
    MAXSTACK = 3
    MAXLOCALS = 5
}

