// class version 55.0 (55)
// access flags 0x20
class original/Solution2864 {

  // compiled from: id_2864.java
  // access flags 0x19
  public final static INNERCLASS java/lang/invoke/MethodHandles$Lookup java/lang/invoke/MethodHandles Lookup

  // access flags 0x0
  <init>()V
   L0
    LINENUMBER 3 L0
    ALOAD 0
    INVOKESPECIAL java/lang/Object.<init> ()V
    RETURN
   L1
    LOCALVARIABLE this Loriginal/Solution2864; L0 L1 0
    MAXSTACK = 1
    MAXLOCALS = 1

  // access flags 0x1
  public maximumOddBinaryNumber(Ljava/lang/String;)Ljava/lang/String;
   L0
    LINENUMBER 5 L0
    ALOAD 1
    INVOKEVIRTUAL java/lang/String.length ()I
    ALOAD 1
    LDC "1"
    LDC ""
    INVOKEVIRTUAL java/lang/String.replace (Ljava/lang/CharSequence;Ljava/lang/CharSequence;)Ljava/lang/String;
    INVOKEVIRTUAL java/lang/String.length ()I
    ISUB
    ISTORE 2
   L1
    LINENUMBER 6 L1
    LDC "1"
    ILOAD 2
    ICONST_1
    IADD
    INVOKEVIRTUAL java/lang/String.repeat (I)Ljava/lang/String;
    LDC "0"
    ALOAD 1
    INVOKEVIRTUAL java/lang/String.length ()I
    ILOAD 2
    ISUB
    INVOKEVIRTUAL java/lang/String.repeat (I)Ljava/lang/String;
    INVOKEDYNAMIC makeConcatWithConstants(Ljava/lang/String;Ljava/lang/String;)Ljava/lang/String; [
      // handle kind 0x6 : INVOKESTATIC
      java/lang/invoke/StringConcatFactory.makeConcatWithConstants(Ljava/lang/invoke/MethodHandles$Lookup;Ljava/lang/String;Ljava/lang/invoke/MethodType;Ljava/lang/String;[Ljava/lang/Object;)Ljava/lang/invoke/CallSite;
      // arguments:
      "\u0001\u00011"
    ]
    ARETURN
   L2
    LOCALVARIABLE this Loriginal/Solution2864; L0 L2 0
    LOCALVARIABLE s Ljava/lang/String; L0 L2 1
    LOCALVARIABLE cnt I L1 L2 2
    MAXSTACK = 4
    MAXLOCALS = 3
}

