// class version 55.0 (55)
// access flags 0x20
class original/Solution0891 {

  // compiled from: id_0891.java

  // access flags 0x1A
  private final static I MOD = 1000000007

  // access flags 0x0
  <init>()V
   L0
    LINENUMBER 4 L0
    ALOAD 0
    INVOKESPECIAL java/lang/Object.<init> ()V
    RETURN
   L1
    LOCALVARIABLE this Loriginal/Solution0891; L0 L1 0
    MAXSTACK = 1
    MAXLOCALS = 1

  // access flags 0x1
  public sumSubseqWidths([I)I
   L0
    LINENUMBER 8 L0
    ALOAD 1
    INVOKESTATIC java/util/Arrays.sort ([I)V
   L1
    LINENUMBER 9 L1
    LCONST_0
    LSTORE 2
   L2
    LCONST_1
    LSTORE 4
   L3
    LINENUMBER 10 L3
    ALOAD 1
    ARRAYLENGTH
    ISTORE 6
   L4
    LINENUMBER 11 L4
    ICONST_0
    ISTORE 7
   L5
   FRAME FULL [original/Solution0891 [I J J I I] []
    ILOAD 7
    ILOAD 6
    IF_ICMPGE L6
   L7
    LINENUMBER 12 L7
    LLOAD 2
    ALOAD 1
    ILOAD 7
    IALOAD
    ALOAD 1
    ILOAD 6
    ILOAD 7
    ISUB
    ICONST_1
    ISUB
    IALOAD
    ISUB
    I2L
    LLOAD 4
    LMUL
    LADD
    LDC 1000000007L
    LADD
    LDC 1000000007L
    LREM
    LSTORE 2
   L8
    LINENUMBER 13 L8
    LLOAD 4
    ICONST_1
    LSHL
    LDC 1000000007L
    LREM
    LSTORE 4
   L9
    LINENUMBER 11 L9
    IINC 7 1
    GOTO L5
   L6
    LINENUMBER 15 L6
   FRAME FULL [original/Solution0891 [I J J I I] []
    LLOAD 2
    L2I
    POP
    ICONST_0
    IRETURN
   L10
    LOCALVARIABLE i I L5 L6 7
    LOCALVARIABLE this Loriginal/Solution0891; L0 L10 0
    LOCALVARIABLE nums [I L0 L10 1
    LOCALVARIABLE ans J L2 L10 2
    LOCALVARIABLE p J L3 L10 4
    LOCALVARIABLE n I L4 L10 6
    MAXSTACK = 6
    MAXLOCALS = 8
}

