// class version 55.0 (55)
// access flags 0x20
class original/FixSpaces {

  // compiled from: id_140.java
  // access flags 0x19
  public final static INNERCLASS java/lang/invoke/MethodHandles$Lookup java/lang/invoke/MethodHandles Lookup

  // access flags 0x0
  <init>()V
   L0
    LINENUMBER 3 L0
    ALOAD 0
    INVOKESPECIAL java/lang/Object.<init> ()V
    RETURN
   L1
    LOCALVARIABLE this Loriginal/FixSpaces; L0 L1 0
    MAXSTACK = 1
    MAXLOCALS = 1

  // access flags 0x9
  public static fixSpaces(Ljava/lang/String;)Ljava/lang/String;
   L0
    LINENUMBER 26 L0
    LDC ""
    ASTORE 1
   L1
    LINENUMBER 27 L1
    ICONST_0
    ISTORE 2
   L2
    LINENUMBER 28 L2
    ICONST_0
    ISTORE 3
   L3
    LINENUMBER 29 L3
    ICONST_0
    ISTORE 4
   L4
    LINENUMBER 30 L4
   FRAME FULL [java/lang/String java/lang/String I I I] []
    ILOAD 2
    ALOAD 0
    INVOKEVIRTUAL java/lang/String.length ()I
    IF_ICMPGE L5
   L6
    LINENUMBER 31 L6
    ALOAD 0
    ILOAD 2
    INVOKEVIRTUAL java/lang/String.charAt (I)C
    BIPUSH 32
    IF_ICMPNE L7
   L8
    LINENUMBER 32 L8
    IINC 4 1
    GOTO L9
   L7
    LINENUMBER 34 L7
   FRAME FULL [java/lang/String java/lang/String I I I] []
    ILOAD 4
    ILOAD 3
    ISUB
    ICONST_2
    IF_ICMPLE L10
   L11
    LINENUMBER 35 L11
    ALOAD 1
    ALOAD 0
    ILOAD 2
    INVOKEVIRTUAL java/lang/String.charAt (I)C
    INVOKEDYNAMIC makeConcatWithConstants(Ljava/lang/String;C)Ljava/lang/String; [
      // handle kind 0x6 : INVOKESTATIC
      java/lang/invoke/StringConcatFactory.makeConcatWithConstants(Ljava/lang/invoke/MethodHandles$Lookup;Ljava/lang/String;Ljava/lang/invoke/MethodType;Ljava/lang/String;[Ljava/lang/Object;)Ljava/lang/invoke/CallSite;
      // arguments:
      "\u0001-\u0001"
    ]
    ASTORE 1
    GOTO L12
   L10
    LINENUMBER 36 L10
   FRAME FULL [java/lang/String java/lang/String I I I] []
    ILOAD 4
    ILOAD 3
    ISUB
    IFGT L13
   L14
    LINENUMBER 37 L14
    ALOAD 1
    LDC "_"
    ILOAD 4
    ILOAD 3
    ISUB
    INVOKEVIRTUAL java/lang/String.repeat (I)Ljava/lang/String;
    ALOAD 0
    ILOAD 2
    INVOKEVIRTUAL java/lang/String.charAt (I)C
    INVOKEDYNAMIC makeConcatWithConstants(Ljava/lang/String;Ljava/lang/String;C)Ljava/lang/String; [
      // handle kind 0x6 : INVOKESTATIC
      java/lang/invoke/StringConcatFactory.makeConcatWithConstants(Ljava/lang/invoke/MethodHandles$Lookup;Ljava/lang/String;Ljava/lang/invoke/MethodType;Ljava/lang/String;[Ljava/lang/Object;)Ljava/lang/invoke/CallSite;
      // arguments:
      "\u0001\u0001\u0001"
    ]
    ASTORE 1
    GOTO L12
   L13
    LINENUMBER 39 L13
   FRAME FULL [java/lang/String java/lang/String I I I] []
    ALOAD 1
    ALOAD 0
    ILOAD 2
    INVOKEVIRTUAL java/lang/String.charAt (I)C
    INVOKEDYNAMIC makeConcatWithConstants(Ljava/lang/String;C)Ljava/lang/String; [
      // handle kind 0x6 : INVOKESTATIC
      java/lang/invoke/StringConcatFactory.makeConcatWithConstants(Ljava/lang/invoke/MethodHandles$Lookup;Ljava/lang/String;Ljava/lang/invoke/MethodType;Ljava/lang/String;[Ljava/lang/Object;)Ljava/lang/invoke/CallSite;
      // arguments:
      "\u0001\u0001"
    ]
    ASTORE 1
   L12
    LINENUMBER 41 L12
   FRAME FULL [java/lang/String java/lang/String I I I] []
    ILOAD 2
    ICONST_1
    IADD
    ISTORE 3
   L15
    LINENUMBER 42 L15
    ILOAD 2
    ICONST_1
    IADD
    ISTORE 4
   L9
    LINENUMBER 44 L9
   FRAME FULL [java/lang/String java/lang/String I I I] []
    IINC 2 1
    GOTO L4
   L5
    LINENUMBER 46 L5
   FRAME FULL [java/lang/String java/lang/String I I I] []
    ILOAD 4
    ILOAD 3
    ISUB
    ICONST_2
    IF_ICMPLE L16
   L17
    LINENUMBER 47 L17
    ALOAD 1
    INVOKEDYNAMIC makeConcatWithConstants(Ljava/lang/String;)Ljava/lang/String; [
      // handle kind 0x6 : INVOKESTATIC
      java/lang/invoke/StringConcatFactory.makeConcatWithConstants(Ljava/lang/invoke/MethodHandles$Lookup;Ljava/lang/String;Ljava/lang/invoke/MethodType;Ljava/lang/String;[Ljava/lang/Object;)Ljava/lang/invoke/CallSite;
      // arguments:
      "\u0001-"
    ]
    ASTORE 1
    GOTO L18
   L16
    LINENUMBER 48 L16
   FRAME FULL [java/lang/String java/lang/String I I I] []
    ILOAD 4
    ILOAD 3
    ISUB
    IFLE L18
   L19
    LINENUMBER 49 L19
    ALOAD 1
    INVOKEDYNAMIC makeConcatWithConstants(Ljava/lang/String;)Ljava/lang/String; [
      // handle kind 0x6 : INVOKESTATIC
      java/lang/invoke/StringConcatFactory.makeConcatWithConstants(Ljava/lang/invoke/MethodHandles$Lookup;Ljava/lang/String;Ljava/lang/invoke/MethodType;Ljava/lang/String;[Ljava/lang/Object;)Ljava/lang/invoke/CallSite;
      // arguments:
      "\u0001_"
    ]
    ASTORE 1
   L18
    LINENUMBER 51 L18
   FRAME FULL [java/lang/String java/lang/String I I I] []
    ALOAD 1
    ARETURN
   L20
    LOCALVARIABLE text Ljava/lang/String; L0 L20 0
    LOCALVARIABLE new_text Ljava/lang/String; L1 L20 1
    LOCALVARIABLE i I L2 L20 2
    LOCALVARIABLE start I L3 L20 3
    LOCALVARIABLE end I L4 L20 4
    MAXSTACK = 4
    MAXLOCALS = 5
}

