// class version 55.0 (55)
// access flags 0x20
class original/Solution3287 {

  // compiled from: id_3287.java

  // access flags 0x0
  <init>()V
   L0
    LINENUMBER 3 L0
    ALOAD 0
    INVOKESPECIAL java/lang/Object.<init> ()V
    RETURN
   L1
    LOCALVARIABLE this Loriginal/Solution3287; L0 L1 0
    MAXSTACK = 1
    MAXLOCALS = 1

  // access flags 0x1
  public maxValue([II)I
   L0
    LINENUMBER 5 L0
    SIPUSH 128
    ISTORE 3
   L1
    LINENUMBER 6 L1
    ALOAD 1
    ARRAYLENGTH
    ISTORE 4
   L2
    LINENUMBER 7 L2
    ILOAD 4
    ICONST_1
    IADD
    ILOAD 2
    ICONST_2
    IADD
    ILOAD 3
    MULTIANEWARRAY [[[Z 3
    ASTORE 5
   L3
    LINENUMBER 8 L3
    ALOAD 5
    ICONST_0
    AALOAD
    ICONST_0
    AALOAD
    ICONST_0
    ICONST_1
    BASTORE
   L4
    LINENUMBER 10 L4
    ICONST_0
    ISTORE 6
   L5
   FRAME FULL [original/Solution3287 [I I I I [[[Z I] []
    ILOAD 6
    ILOAD 4
    IF_ICMPGE L6
   L7
    LINENUMBER 11 L7
    ICONST_0
    ISTORE 7
   L8
   FRAME FULL [original/Solution3287 [I I I I [[[Z I I] []
    ILOAD 7
    ILOAD 2
    IF_ICMPGT L9
   L10
    LINENUMBER 12 L10
    ICONST_0
    ISTORE 8
   L11
   FRAME FULL [original/Solution3287 [I I I I [[[Z I I I] []
    ILOAD 8
    ILOAD 3
    IF_ICMPGE L12
   L13
    LINENUMBER 13 L13
    ALOAD 5
    ILOAD 6
    AALOAD
    ILOAD 7
    AALOAD
    ILOAD 8
    BALOAD
    IFEQ L14
   L15
    LINENUMBER 14 L15
    ALOAD 5
    ILOAD 6
    ICONST_1
    IADD
    AALOAD
    ILOAD 7
    AALOAD
    ILOAD 8
    ICONST_1
    BASTORE
   L16
    LINENUMBER 15 L16
    ALOAD 5
    ILOAD 6
    ICONST_1
    IADD
    AALOAD
    ILOAD 7
    ICONST_1
    IADD
    AALOAD
    ILOAD 8
    ALOAD 1
    ILOAD 6
    IALOAD
    IOR
    ICONST_1
    BASTORE
   L14
    LINENUMBER 12 L14
   FRAME FULL [original/Solution3287 [I I I I [[[Z I I I] []
    IINC 8 1
    GOTO L11
   L12
    LINENUMBER 11 L12
   FRAME FULL [original/Solution3287 [I I I I [[[Z I I I] []
    IINC 7 1
    GOTO L8
   L9
    LINENUMBER 10 L9
   FRAME FULL [original/Solution3287 [I I I I [[[Z I I] []
    IINC 6 1
    GOTO L5
   L6
    LINENUMBER 21 L6
   FRAME FULL [original/Solution3287 [I I I I [[[Z I] []
    ILOAD 4
    ICONST_1
    IADD
    ILOAD 2
    ICONST_2
    IADD
    ILOAD 3
    MULTIANEWARRAY [[[Z 3
    ASTORE 6
   L17
    LINENUMBER 22 L17
    ALOAD 6
    ILOAD 4
    AALOAD
    ICONST_0
    AALOAD
    ICONST_0
    ICONST_1
    BASTORE
   L18
    LINENUMBER 24 L18
    ILOAD 4
    ISTORE 7
   L19
   FRAME FULL [original/Solution3287 [I I I I [[[Z [[[Z I] []
    ILOAD 7
    IFLE L20
   L21
    LINENUMBER 25 L21
    ICONST_0
    ISTORE 8
   L22
   FRAME FULL [original/Solution3287 [I I I I [[[Z [[[Z I I] []
    ILOAD 8
    ILOAD 2
    IF_ICMPGT L23
   L24
    LINENUMBER 26 L24
    ICONST_0
    ISTORE 9
   L25
   FRAME FULL [original/Solution3287 [I I I I [[[Z [[[Z I I I] []
    ILOAD 9
    ILOAD 3
    IF_ICMPGE L26
   L27
    LINENUMBER 27 L27
    ALOAD 6
    ILOAD 7
    AALOAD
    ILOAD 8
    AALOAD
    ILOAD 9
    BALOAD
    IFEQ L28
   L29
    LINENUMBER 28 L29
    ALOAD 6
    ILOAD 7
    ICONST_1
    IADD
    AALOAD
    ILOAD 8
    AALOAD
    ILOAD 9
    ICONST_1
    BASTORE
   L30
    LINENUMBER 29 L30
    ALOAD 6
    ILOAD 7
    ICONST_1
    ISUB
    AALOAD
    ILOAD 8
    ICONST_1
    IADD
    AALOAD
    ILOAD 9
    ALOAD 1
    ILOAD 7
    ICONST_1
    ISUB
    IALOAD
    IOR
    ICONST_1
    BASTORE
   L28
    LINENUMBER 26 L28
   FRAME FULL [original/Solution3287 [I I I I [[[Z [[[Z I I I] []
    IINC 9 1
    GOTO L25
   L26
    LINENUMBER 25 L26
   FRAME FULL [original/Solution3287 [I I I I [[[Z [[[Z I I I] []
    IINC 8 1
    GOTO L22
   L23
    LINENUMBER 24 L23
   FRAME FULL [original/Solution3287 [I I I I [[[Z [[[Z I I] []
    IINC 7 -1
    GOTO L19
   L20
    LINENUMBER 35 L20
   FRAME FULL [original/Solution3287 [I I I I [[[Z [[[Z I] []
    ICONST_0
    ISTORE 7
   L31
    LINENUMBER 37 L31
    ILOAD 2
    ISTORE 8
   L32
   FRAME FULL [original/Solution3287 [I I I I [[[Z [[[Z I I] []
    ILOAD 8
    ILOAD 4
    ILOAD 2
    ISUB
    IF_ICMPGT L33
   L34
    LINENUMBER 38 L34
    ICONST_0
    ISTORE 9
   L35
   FRAME FULL [original/Solution3287 [I I I I [[[Z [[[Z I I I] []
    ILOAD 9
    ILOAD 3
    IF_ICMPGE L36
   L37
    LINENUMBER 39 L37
    ALOAD 5
    ILOAD 8
    AALOAD
    ILOAD 2
    AALOAD
    ILOAD 9
    BALOAD
    IFEQ L38
   L39
    LINENUMBER 40 L39
    ICONST_0
    ISTORE 10
   L40
   FRAME FULL [original/Solution3287 [I I I I [[[Z [[[Z I I I I] []
    ILOAD 10
    ILOAD 3
    IF_ICMPGE L38
   L41
    LINENUMBER 41 L41
    ALOAD 6
    ILOAD 8
    AALOAD
    ILOAD 2
    AALOAD
    ILOAD 10
    BALOAD
    IFEQ L42
   L43
    LINENUMBER 42 L43
    ILOAD 7
    ILOAD 9
    ILOAD 10
    IXOR
    INVOKESTATIC java/lang/Math.max (II)I
    ISTORE 7
   L42
    LINENUMBER 40 L42
   FRAME FULL [original/Solution3287 [I I I I [[[Z [[[Z I I I I] []
    IINC 10 1
    GOTO L40
   L38
    LINENUMBER 38 L38
   FRAME FULL [original/Solution3287 [I I I I [[[Z [[[Z I I I] []
    IINC 9 1
    GOTO L35
   L36
    LINENUMBER 37 L36
   FRAME FULL [original/Solution3287 [I I I I [[[Z [[[Z I I I] []
    IINC 8 1
    GOTO L32
   L33
    LINENUMBER 49 L33
   FRAME FULL [original/Solution3287 [I I I I [[[Z [[[Z I I] []
    ILOAD 7
    IRETURN
   L44
    LOCALVARIABLE x I L11 L12 8
    LOCALVARIABLE j I L8 L9 7
    LOCALVARIABLE i I L5 L6 6
    LOCALVARIABLE y I L25 L26 9
    LOCALVARIABLE j I L22 L23 8
    LOCALVARIABLE i I L19 L20 7
    LOCALVARIABLE y I L40 L38 10
    LOCALVARIABLE x I L35 L36 9
    LOCALVARIABLE i I L32 L33 8
    LOCALVARIABLE this Loriginal/Solution3287; L0 L44 0
    LOCALVARIABLE nums [I L0 L44 1
    LOCALVARIABLE k I L0 L44 2
    LOCALVARIABLE m I L1 L44 3
    LOCALVARIABLE n I L2 L44 4
    LOCALVARIABLE f [[[Z L3 L44 5
    LOCALVARIABLE g [[[Z L17 L44 6
    LOCALVARIABLE ans I L31 L44 7
    MAXSTACK = 5
    MAXLOCALS = 11
}

