// class version 55.0 (55)
// access flags 0x20
class original/VowelsCount {

  // compiled from: id_64.java

  // access flags 0x0
  <init>()V
   L0
    LINENUMBER 3 L0
    ALOAD 0
    INVOKESPECIAL java/lang/Object.<init> ()V
    RETURN
   L1
    LOCALVARIABLE this Loriginal/VowelsCount; L0 L1 0
    MAXSTACK = 1
    MAXLOCALS = 1

  // access flags 0x9
  public static vowelsCount(Ljava/lang/String;)I
   L0
    LINENUMBER 26 L0
    ICONST_0
    ISTORE 1
   L1
    LINENUMBER 27 L1
    ICONST_0
    ISTORE 2
   L2
   FRAME FULL [java/lang/String I I] []
    ILOAD 2
    ALOAD 0
    INVOKEVIRTUAL java/lang/String.length ()I
    IF_ICMPGT L3
   L4
    LINENUMBER 28 L4
    ALOAD 0
    ILOAD 2
    INVOKEVIRTUAL java/lang/String.charAt (I)C
    ISTORE 3
   L5
    LINENUMBER 29 L5
    ILOAD 3
    BIPUSH 97
    IF_ICMPEQ L6
    ILOAD 3
    BIPUSH 101
    IF_ICMPEQ L6
    ILOAD 3
    BIPUSH 105
    IF_ICMPEQ L6
    ILOAD 3
    BIPUSH 111
    IF_ICMPEQ L6
    ILOAD 3
    BIPUSH 117
    IF_ICMPEQ L6
    ILOAD 3
    BIPUSH 65
    IF_ICMPEQ L6
    ILOAD 3
    BIPUSH 69
    IF_ICMPEQ L6
    ILOAD 3
    BIPUSH 73
    IF_ICMPEQ L6
    ILOAD 3
    BIPUSH 79
    IF_ICMPEQ L6
    ILOAD 3
    BIPUSH 85
    IF_ICMPNE L7
   L6
    LINENUMBER 30 L6
   FRAME FULL [java/lang/String I I I] []
    IINC 1 1
   L7
    LINENUMBER 27 L7
   FRAME FULL [java/lang/String I I I] []
    IINC 2 1
    GOTO L2
   L3
    LINENUMBER 33 L3
   FRAME FULL [java/lang/String I I] []
    ALOAD 0
    INVOKEVIRTUAL java/lang/String.length ()I
    IFLE L8
    ALOAD 0
    ALOAD 0
    INVOKEVIRTUAL java/lang/String.length ()I
    ICONST_1
    ISUB
    INVOKEVIRTUAL java/lang/String.charAt (I)C
    BIPUSH 121
    IF_ICMPEQ L9
    ALOAD 0
    ALOAD 0
    INVOKEVIRTUAL java/lang/String.length ()I
    ICONST_1
    ISUB
    INVOKEVIRTUAL java/lang/String.charAt (I)C
    BIPUSH 89
    IF_ICMPNE L8
   L9
    LINENUMBER 34 L9
   FRAME FULL [java/lang/String I I] []
    IINC 1 1
   L8
    LINENUMBER 36 L8
   FRAME FULL [java/lang/String I I] []
    ILOAD 1
    IRETURN
   L10
    LOCALVARIABLE c C L5 L7 3
    LOCALVARIABLE i I L2 L3 2
    LOCALVARIABLE s Ljava/lang/String; L0 L10 0
    LOCALVARIABLE count I L1 L10 1
    MAXSTACK = 3
    MAXLOCALS = 4
}

