// class version 55.0 (55)
// access flags 0x20
class original/Solution2617 {

  // compiled from: id_2617.java
  // access flags 0x19
  public final static INNERCLASS java/lang/invoke/MethodHandles$Lookup java/lang/invoke/MethodHandles Lookup

  // access flags 0x0
  <init>()V
   L0
    LINENUMBER 6 L0
    ALOAD 0
    INVOKESPECIAL java/lang/Object.<init> ()V
    RETURN
   L1
    LOCALVARIABLE this Loriginal/Solution2617; L0 L1 0
    MAXSTACK = 1
    MAXLOCALS = 1

  // access flags 0x1
  public minimumVisitedCells([[I)I
   L0
    LINENUMBER 8 L0
    ALOAD 1
    ARRAYLENGTH
    ISTORE 2
   L1
    ALOAD 1
    ICONST_0
    AALOAD
    ARRAYLENGTH
    ISTORE 3
   L2
    LINENUMBER 9 L2
    ILOAD 2
    ILOAD 3
    MULTIANEWARRAY [[I 2
    ASTORE 4
   L3
    LINENUMBER 10 L3
    ILOAD 2
    ANEWARRAY java/util/PriorityQueue
    ASTORE 5
   L4
    LINENUMBER 11 L4
    ILOAD 3
    ANEWARRAY java/util/PriorityQueue
    ASTORE 6
   L5
    LINENUMBER 12 L5
    ICONST_0
    ISTORE 7
   L6
   FRAME FULL [original/Solution2617 [[I I I [[I [Ljava/util/PriorityQueue; [Ljava/util/PriorityQueue; I] []
    ILOAD 7
    ILOAD 2
    IF_ICMPGE L7
   L8
    LINENUMBER 13 L8
    ALOAD 4
    ILOAD 7
    AALOAD
    ICONST_M1
    INVOKESTATIC java/util/Arrays.fill ([II)V
   L9
    LINENUMBER 14 L9
    ALOAD 5
    ILOAD 7
    NEW java/util/PriorityQueue
    DUP
    INVOKEDYNAMIC compare()Ljava/util/Comparator; [
      // handle kind 0x6 : INVOKESTATIC
      java/lang/invoke/LambdaMetafactory.metafactory(Ljava/lang/invoke/MethodHandles$Lookup;Ljava/lang/String;Ljava/lang/invoke/MethodType;Ljava/lang/invoke/MethodType;Ljava/lang/invoke/MethodHandle;Ljava/lang/invoke/MethodType;)Ljava/lang/invoke/CallSite;
      // arguments:
      (Ljava/lang/Object;Ljava/lang/Object;)I, 
      // handle kind 0x6 : INVOKESTATIC
      original/Solution2617.lambda$minimumVisitedCells$0([I[I)I, 
      ([I[I)I
    ]
    INVOKESPECIAL java/util/PriorityQueue.<init> (Ljava/util/Comparator;)V
    AASTORE
   L10
    LINENUMBER 12 L10
    IINC 7 1
    GOTO L6
   L7
    LINENUMBER 16 L7
   FRAME FULL [original/Solution2617 [[I I I [[I [Ljava/util/PriorityQueue; [Ljava/util/PriorityQueue; I] []
    ICONST_0
    ISTORE 7
   L11
   FRAME FULL [original/Solution2617 [[I I I [[I [Ljava/util/PriorityQueue; [Ljava/util/PriorityQueue; I] []
    ILOAD 7
    ILOAD 3
    IF_ICMPGE L12
   L13
    LINENUMBER 17 L13
    ALOAD 6
    ILOAD 7
    NEW java/util/PriorityQueue
    DUP
    INVOKEDYNAMIC compare()Ljava/util/Comparator; [
      // handle kind 0x6 : INVOKESTATIC
      java/lang/invoke/LambdaMetafactory.metafactory(Ljava/lang/invoke/MethodHandles$Lookup;Ljava/lang/String;Ljava/lang/invoke/MethodType;Ljava/lang/invoke/MethodType;Ljava/lang/invoke/MethodHandle;Ljava/lang/invoke/MethodType;)Ljava/lang/invoke/CallSite;
      // arguments:
      (Ljava/lang/Object;Ljava/lang/Object;)I, 
      // handle kind 0x6 : INVOKESTATIC
      original/Solution2617.lambda$minimumVisitedCells$1([I[I)I, 
      ([I[I)I
    ]
    INVOKESPECIAL java/util/PriorityQueue.<init> (Ljava/util/Comparator;)V
    AASTORE
   L14
    LINENUMBER 16 L14
    IINC 7 1
    GOTO L11
   L12
    LINENUMBER 19 L12
   FRAME FULL [original/Solution2617 [[I I I [[I [Ljava/util/PriorityQueue; [Ljava/util/PriorityQueue; I] []
    ALOAD 4
    ICONST_0
    AALOAD
    ICONST_0
    ICONST_1
    IASTORE
   L15
    LINENUMBER 20 L15
    ICONST_0
    ISTORE 7
   L16
   FRAME FULL [original/Solution2617 [[I I I [[I [Ljava/util/PriorityQueue; [Ljava/util/PriorityQueue; I] []
    ILOAD 7
    ILOAD 2
    IF_ICMPGE L17
   L18
    LINENUMBER 21 L18
    ICONST_0
    ISTORE 8
   L19
   FRAME FULL [original/Solution2617 [[I I I [[I [Ljava/util/PriorityQueue; [Ljava/util/PriorityQueue; I I] []
    ILOAD 8
    ILOAD 3
    IF_ICMPGE L20
   L21
    LINENUMBER 22 L21
   FRAME FULL [original/Solution2617 [[I I I [[I [Ljava/util/PriorityQueue; [Ljava/util/PriorityQueue; I I] []
    ALOAD 5
    ILOAD 7
    AALOAD
    INVOKEVIRTUAL java/util/PriorityQueue.isEmpty ()Z
    IFEQ L22
    ALOAD 1
    ILOAD 7
    AALOAD
    ALOAD 5
    ILOAD 7
    AALOAD
    INVOKEVIRTUAL java/util/PriorityQueue.peek ()Ljava/lang/Object;
    CHECKCAST [I
    ICONST_1
    IALOAD
    IALOAD
    ALOAD 5
    ILOAD 7
    AALOAD
    INVOKEVIRTUAL java/util/PriorityQueue.peek ()Ljava/lang/Object;
    CHECKCAST [I
    ICONST_1
    IALOAD
    IADD
    ILOAD 8
    IF_ICMPGE L22
   L23
    LINENUMBER 23 L23
    ALOAD 5
    ILOAD 7
    AALOAD
    INVOKEVIRTUAL java/util/PriorityQueue.poll ()Ljava/lang/Object;
    POP
    GOTO L21
   L22
    LINENUMBER 25 L22
   FRAME FULL [original/Solution2617 [[I I I [[I [Ljava/util/PriorityQueue; [Ljava/util/PriorityQueue; I I] []
    ALOAD 5
    ILOAD 7
    AALOAD
    INVOKEVIRTUAL java/util/PriorityQueue.isEmpty ()Z
    IFNE L24
    ALOAD 4
    ILOAD 7
    AALOAD
    ILOAD 8
    IALOAD
    ICONST_M1
    IF_ICMPEQ L25
    ALOAD 5
    ILOAD 7
    AALOAD
    INVOKEVIRTUAL java/util/PriorityQueue.peek ()Ljava/lang/Object;
    CHECKCAST [I
    ICONST_0
    IALOAD
    ICONST_1
    IADD
    ALOAD 4
    ILOAD 7
    AALOAD
    ILOAD 8
    IALOAD
    IF_ICMPGE L24
   L25
    LINENUMBER 26 L25
   FRAME FULL [original/Solution2617 [[I I I [[I [Ljava/util/PriorityQueue; [Ljava/util/PriorityQueue; I I] []
    ALOAD 4
    ILOAD 7
    AALOAD
    ILOAD 8
    ALOAD 5
    ILOAD 7
    AALOAD
    INVOKEVIRTUAL java/util/PriorityQueue.peek ()Ljava/lang/Object;
    CHECKCAST [I
    ICONST_0
    IALOAD
    ICONST_1
    IADD
    IASTORE
   L24
    LINENUMBER 28 L24
   FRAME FULL [original/Solution2617 [[I I I [[I [Ljava/util/PriorityQueue; [Ljava/util/PriorityQueue; I I] []
    ALOAD 6
    ILOAD 8
    AALOAD
    INVOKEVIRTUAL java/util/PriorityQueue.isEmpty ()Z
    IFNE L26
    ALOAD 1
    ALOAD 6
    ILOAD 8
    AALOAD
    INVOKEVIRTUAL java/util/PriorityQueue.peek ()Ljava/lang/Object;
    CHECKCAST [I
    ICONST_1
    IALOAD
    AALOAD
    ILOAD 8
    IALOAD
    ALOAD 6
    ILOAD 8
    AALOAD
    INVOKEVIRTUAL java/util/PriorityQueue.peek ()Ljava/lang/Object;
    CHECKCAST [I
    ICONST_1
    IALOAD
    IADD
    ILOAD 7
    IF_ICMPGE L26
   L27
    LINENUMBER 29 L27
    ALOAD 6
    ILOAD 8
    AALOAD
    INVOKEVIRTUAL java/util/PriorityQueue.poll ()Ljava/lang/Object;
    POP
    GOTO L24
   L26
    LINENUMBER 31 L26
   FRAME FULL [original/Solution2617 [[I I I [[I [Ljava/util/PriorityQueue; [Ljava/util/PriorityQueue; I I] []
    ALOAD 6
    ILOAD 8
    AALOAD
    INVOKEVIRTUAL java/util/PriorityQueue.isEmpty ()Z
    IFNE L28
    ALOAD 4
    ILOAD 7
    AALOAD
    ILOAD 8
    IALOAD
    ICONST_M1
    IF_ICMPEQ L29
    ALOAD 6
    ILOAD 8
    AALOAD
    INVOKEVIRTUAL java/util/PriorityQueue.peek ()Ljava/lang/Object;
    CHECKCAST [I
    ICONST_0
    IALOAD
    ICONST_1
    IADD
    ALOAD 4
    ILOAD 7
    AALOAD
    ILOAD 8
    IALOAD
    IF_ICMPGE L28
   L29
    LINENUMBER 32 L29
   FRAME FULL [original/Solution2617 [[I I I [[I [Ljava/util/PriorityQueue; [Ljava/util/PriorityQueue; I I] []
    ALOAD 4
    ILOAD 7
    AALOAD
    ILOAD 8
    ALOAD 6
    ILOAD 8
    AALOAD
    INVOKEVIRTUAL java/util/PriorityQueue.peek ()Ljava/lang/Object;
    CHECKCAST [I
    ICONST_0
    IALOAD
    ICONST_1
    IADD
    IASTORE
   L28
    LINENUMBER 34 L28
   FRAME FULL [original/Solution2617 [[I I I [[I [Ljava/util/PriorityQueue; [Ljava/util/PriorityQueue; I I] []
    ALOAD 4
    ILOAD 7
    AALOAD
    ILOAD 8
    IALOAD
    ICONST_M1
    IF_ICMPEQ L30
   L31
    LINENUMBER 35 L31
    ALOAD 5
    ILOAD 7
    AALOAD
    ICONST_2
    NEWARRAY T_INT
    DUP
    ICONST_0
    ALOAD 4
    ILOAD 7
    AALOAD
    ILOAD 8
    IALOAD
    IASTORE
    DUP
    ICONST_1
    ILOAD 8
    IASTORE
    INVOKEVIRTUAL java/util/PriorityQueue.offer (Ljava/lang/Object;)Z
    POP
   L32
    LINENUMBER 36 L32
    ALOAD 6
    ILOAD 8
    AALOAD
    ICONST_2
    NEWARRAY T_INT
    DUP
    ICONST_0
    ALOAD 4
    ILOAD 7
    AALOAD
    ILOAD 8
    IALOAD
    IASTORE
    DUP
    ICONST_1
    ILOAD 7
    IASTORE
    INVOKEVIRTUAL java/util/PriorityQueue.offer (Ljava/lang/Object;)Z
    POP
   L30
    LINENUMBER 21 L30
   FRAME FULL [original/Solution2617 [[I I I [[I [Ljava/util/PriorityQueue; [Ljava/util/PriorityQueue; I I] []
    IINC 8 1
    GOTO L19
   L20
    LINENUMBER 20 L20
   FRAME FULL [original/Solution2617 [[I I I [[I [Ljava/util/PriorityQueue; [Ljava/util/PriorityQueue; I I] []
    IINC 7 1
    GOTO L16
   L17
    LINENUMBER 40 L17
   FRAME FULL [original/Solution2617 [[I I I [[I [Ljava/util/PriorityQueue; [Ljava/util/PriorityQueue; I] []
    ALOAD 4
    ILOAD 2
    ICONST_1
    ISUB
    AALOAD
    ILOAD 3
    ICONST_1
    ISUB
    IALOAD
    IRETURN
   L33
    LOCALVARIABLE i I L6 L7 7
    LOCALVARIABLE i I L11 L12 7
    LOCALVARIABLE j I L19 L20 8
    LOCALVARIABLE i I L16 L17 7
    LOCALVARIABLE this Loriginal/Solution2617; L0 L33 0
    LOCALVARIABLE grid [[I L0 L33 1
    LOCALVARIABLE m I L1 L33 2
    LOCALVARIABLE n I L2 L33 3
    LOCALVARIABLE dist [[I L3 L33 4
    LOCALVARIABLE row [Ljava/util/PriorityQueue; L4 L33 5
    // signature [Ljava/util/PriorityQueue<[I>;
    // declaration: row extends java.util.PriorityQueue<int[]>
    LOCALVARIABLE col [Ljava/util/PriorityQueue; L5 L33 6
    // signature [Ljava/util/PriorityQueue<[I>;
    // declaration: col extends java.util.PriorityQueue<int[]>
    MAXSTACK = 6
    MAXLOCALS = 9

  // access flags 0x100A
  private static synthetic lambda$minimumVisitedCells$1([I[I)I
   L0
    LINENUMBER 17 L0
    ALOAD 0
    ICONST_0
    IALOAD
    ALOAD 1
    ICONST_0
    IALOAD
    IF_ICMPNE L1
    ALOAD 0
    ICONST_1
    IALOAD
    ALOAD 1
    ICONST_1
    IALOAD
    ISUB
    GOTO L2
   L1
   FRAME FULL [[I [I] []
    ALOAD 0
    ICONST_0
    IALOAD
    ALOAD 1
    ICONST_0
    IALOAD
    ISUB
   L2
   FRAME FULL [[I [I] [I]
    IRETURN
   L3
    LOCALVARIABLE a [I L0 L3 0
    LOCALVARIABLE b [I L0 L3 1
    MAXSTACK = 3
    MAXLOCALS = 2

  // access flags 0x100A
  private static synthetic lambda$minimumVisitedCells$0([I[I)I
   L0
    LINENUMBER 14 L0
    ALOAD 0
    ICONST_0
    IALOAD
    ALOAD 1
    ICONST_0
    IALOAD
    IF_ICMPNE L1
    ALOAD 0
    ICONST_1
    IALOAD
    ALOAD 1
    ICONST_1
    IALOAD
    ISUB
    GOTO L2
   L1
   FRAME FULL [[I [I] []
    ALOAD 0
    ICONST_0
    IALOAD
    ALOAD 1
    ICONST_0
    IALOAD
    ISUB
   L2
   FRAME FULL [[I [I] [I]
    IRETURN
   L3
    LOCALVARIABLE a [I L0 L3 0
    LOCALVARIABLE b [I L0 L3 1
    MAXSTACK = 3
    MAXLOCALS = 2
}

