// class version 55.0 (55)
// access flags 0x20
class original/Solution0418 {

  // compiled from: id_0418.java
  // access flags 0x19
  public final static INNERCLASS java/lang/invoke/MethodHandles$Lookup java/lang/invoke/MethodHandles Lookup

  // access flags 0x0
  <init>()V
   L0
    LINENUMBER 3 L0
    ALOAD 0
    INVOKESPECIAL java/lang/Object.<init> ()V
    RETURN
   L1
    LOCALVARIABLE this Loriginal/Solution0418; L0 L1 0
    MAXSTACK = 1
    MAXLOCALS = 1

  // access flags 0x1
  public wordsTyping([Ljava/lang/String;II)I
   L0
    LINENUMBER 5 L0
    LDC " "
    ALOAD 1
    INVOKESTATIC java/lang/String.join (Ljava/lang/CharSequence;[Ljava/lang/CharSequence;)Ljava/lang/String;
    INVOKEDYNAMIC makeConcatWithConstants(Ljava/lang/String;)Ljava/lang/String; [
      // handle kind 0x6 : INVOKESTATIC
      java/lang/invoke/StringConcatFactory.makeConcatWithConstants(Ljava/lang/invoke/MethodHandles$Lookup;Ljava/lang/String;Ljava/lang/invoke/MethodType;Ljava/lang/String;[Ljava/lang/Object;)Ljava/lang/invoke/CallSite;
      // arguments:
      "\u0001 "
    ]
    ASTORE 4
   L1
    LINENUMBER 6 L1
    ALOAD 4
    INVOKEVIRTUAL java/lang/String.length ()I
    ISTORE 5
   L2
    LINENUMBER 7 L2
    ICONST_0
    ISTORE 6
   L3
    LINENUMBER 8 L3
   FRAME FULL [original/Solution0418 [Ljava/lang/String; I I java/lang/String I I] []
    ILOAD 2
    IINC 2 -1
    IFLE L4
   L5
    LINENUMBER 9 L5
    ILOAD 6
    ILOAD 3
    IADD
    ISTORE 6
   L6
    LINENUMBER 10 L6
    ALOAD 4
    ILOAD 6
    ILOAD 5
    IREM
    INVOKEVIRTUAL java/lang/String.charAt (I)C
    BIPUSH 32
    IF_ICMPNE L7
   L8
    LINENUMBER 11 L8
    IINC 6 -1
    GOTO L3
   L7
    LINENUMBER 13 L7
   FRAME FULL [original/Solution0418 [Ljava/lang/String; I I java/lang/String I I] []
    ILOAD 6
    IFLE L3
    ALOAD 4
    ILOAD 6
    ICONST_1
    ISUB
    ILOAD 5
    IREM
    INVOKEVIRTUAL java/lang/String.charAt (I)C
    BIPUSH 32
    IF_ICMPEQ L3
   L9
    LINENUMBER 14 L9
    IINC 6 -1
    GOTO L7
   L4
    LINENUMBER 18 L4
   FRAME FULL [original/Solution0418 [Ljava/lang/String; I I java/lang/String I I] []
    ILOAD 6
    ILOAD 5
    IDIV
    IRETURN
   L10
    LOCALVARIABLE this Loriginal/Solution0418; L0 L10 0
    LOCALVARIABLE sentence [Ljava/lang/String; L0 L10 1
    LOCALVARIABLE rows I L0 L10 2
    LOCALVARIABLE cols I L0 L10 3
    LOCALVARIABLE s Ljava/lang/String; L1 L10 4
    LOCALVARIABLE m I L2 L10 5
    LOCALVARIABLE cur I L3 L10 6
    MAXSTACK = 3
    MAXLOCALS = 7
}

