// class version 55.0 (55)
// access flags 0x20
class original/GetRow {

  // compiled from: id_87.java
  NESTMEMBER original/GetRow$1
  // access flags 0x0
  INNERCLASS original/GetRow$1 null null

  // access flags 0x0
  <init>()V
   L0
    LINENUMBER 10 L0
    ALOAD 0
    INVOKESPECIAL java/lang/Object.<init> ()V
    RETURN
   L1
    LOCALVARIABLE this Loriginal/GetRow; L0 L1 0
    MAXSTACK = 1
    MAXLOCALS = 1

  // access flags 0x9
  // signature (Ljava/util/List<Ljava/lang/Object;>;I)Ljava/util/List<Ljava/lang/Object;>;
  // declaration: java.util.List<java.lang.Object> getRow(java.util.List<java.lang.Object>, int)
  public static getRow(Ljava/util/List;I)Ljava/util/List;
   L0
    LINENUMBER 38 L0
    NEW java/util/ArrayList
    DUP
    INVOKESPECIAL java/util/ArrayList.<init> ()V
    ASTORE 2
   L1
    LINENUMBER 39 L1
    ICONST_0
    ISTORE 3
   L2
   FRAME FULL [java/util/List I java/util/ArrayList I] []
    ILOAD 3
    ALOAD 0
    INVOKEINTERFACE java/util/List.size ()I (itf)
    IF_ICMPGE L3
   L4
    LINENUMBER 40 L4
    ALOAD 0
    ILOAD 3
    INVOKEINTERFACE java/util/List.get (I)Ljava/lang/Object; (itf)
    CHECKCAST java/util/List
    ASTORE 4
   L5
    LINENUMBER 41 L5
    ICONST_0
    ISTORE 5
   L6
   FRAME FULL [java/util/List I java/util/ArrayList I java/util/List I] []
    ILOAD 5
    ALOAD 4
    INVOKEINTERFACE java/util/List.size ()I (itf)
    IF_ICMPGE L7
   L8
    LINENUMBER 42 L8
    ALOAD 4
    ILOAD 5
    INVOKEINTERFACE java/util/List.get (I)Ljava/lang/Object; (itf)
    ILOAD 1
    INVOKESTATIC java/lang/Integer.valueOf (I)Ljava/lang/Integer;
    INVOKEVIRTUAL java/lang/Object.equals (Ljava/lang/Object;)Z
    IFNE L9
   L10
    LINENUMBER 43 L10
    NEW java/util/ArrayList
    DUP
    INVOKESPECIAL java/util/ArrayList.<init> ()V
    ASTORE 6
   L11
    LINENUMBER 44 L11
    ALOAD 6
    ILOAD 3
    INVOKESTATIC java/lang/Integer.valueOf (I)Ljava/lang/Integer;
    INVOKEINTERFACE java/util/List.add (Ljava/lang/Object;)Z (itf)
    POP
   L12
    LINENUMBER 45 L12
    ALOAD 6
    ILOAD 5
    INVOKESTATIC java/lang/Integer.valueOf (I)Ljava/lang/Integer;
    INVOKEINTERFACE java/util/List.add (Ljava/lang/Object;)Z (itf)
    POP
   L13
    LINENUMBER 46 L13
    ALOAD 2
    ALOAD 6
    INVOKEINTERFACE java/util/List.add (Ljava/lang/Object;)Z (itf)
    POP
   L9
    LINENUMBER 41 L9
   FRAME FULL [java/util/List I java/util/ArrayList I java/util/List I] []
    IINC 5 1
    GOTO L6
   L7
    LINENUMBER 39 L7
   FRAME FULL [java/util/List I java/util/ArrayList I java/util/List I] []
    IINC 3 1
    GOTO L2
   L3
    LINENUMBER 50 L3
   FRAME FULL [java/util/List I java/util/ArrayList I] []
    ALOAD 2
    NEW original/GetRow$1
    DUP
    INVOKESPECIAL original/GetRow$1.<init> ()V
    INVOKESTATIC java/util/Collections.sort (Ljava/util/List;Ljava/util/Comparator;)V
   L14
    LINENUMBER 64 L14
    ALOAD 2
    ARETURN
   L15
    LOCALVARIABLE coordinate Ljava/util/List; L11 L9 6
    // signature Ljava/util/List<Ljava/lang/Object;>;
    // declaration: coordinate extends java.util.List<java.lang.Object>
    LOCALVARIABLE j I L6 L7 5
    LOCALVARIABLE row Ljava/util/List; L5 L7 4
    // signature Ljava/util/List<Ljava/lang/Object;>;
    // declaration: row extends java.util.List<java.lang.Object>
    LOCALVARIABLE i I L2 L3 3
    LOCALVARIABLE lst Ljava/util/List; L0 L15 0
    // signature Ljava/util/List<Ljava/lang/Object;>;
    // declaration: lst extends java.util.List<java.lang.Object>
    LOCALVARIABLE x I L0 L15 1
    LOCALVARIABLE result Ljava/util/List; L1 L15 2
    // signature Ljava/util/List<Ljava/lang/Object;>;
    // declaration: result extends java.util.List<java.lang.Object>
    MAXSTACK = 3
    MAXLOCALS = 7
}

