// class version 55.0 (55)
// access flags 0x20
class original/CountUpTo {

  // compiled from: id_96.java

  // access flags 0x0
  <init>()V
   L0
    LINENUMBER 8 L0
    ALOAD 0
    INVOKESPECIAL java/lang/Object.<init> ()V
    RETURN
   L1
    LOCALVARIABLE this Loriginal/CountUpTo; L0 L1 0
    MAXSTACK = 1
    MAXLOCALS = 1

  // access flags 0x9
  // signature (I)Ljava/util/List<Ljava/lang/Object;>;
  // declaration: java.util.List<java.lang.Object> countUpTo(int)
  public static countUpTo(I)Ljava/util/List;
   L0
    LINENUMBER 42 L0
    NEW java/util/ArrayList
    DUP
    INVOKESPECIAL java/util/ArrayList.<init> ()V
    ASTORE 1
   L1
    LINENUMBER 43 L1
    ICONST_2
    ISTORE 2
   L2
    LINENUMBER 44 L2
   FRAME FULL [I java/util/ArrayList I] []
    ILOAD 2
    ILOAD 0
    IF_ICMPGE L3
   L4
    LINENUMBER 45 L4
    ILOAD 2
    INVOKESTATIC original/CountUpTo.isPrime (I)Z
    IFEQ L5
   L6
    LINENUMBER 46 L6
    ALOAD 1
    ILOAD 2
    INVOKESTATIC java/lang/Integer.valueOf (I)Ljava/lang/Integer;
    INVOKEINTERFACE java/util/List.add (Ljava/lang/Object;)Z (itf)
    POP
   L5
    LINENUMBER 48 L5
   FRAME FULL [I java/util/ArrayList I] []
    IINC 2 1
    GOTO L2
   L3
    LINENUMBER 50 L3
   FRAME FULL [I java/util/ArrayList I] []
    ALOAD 1
    ARETURN
   L7
    LOCALVARIABLE n I L0 L7 0
    LOCALVARIABLE result Ljava/util/List; L1 L7 1
    // signature Ljava/util/List<Ljava/lang/Object;>;
    // declaration: result extends java.util.List<java.lang.Object>
    LOCALVARIABLE i I L2 L7 2
    MAXSTACK = 2
    MAXLOCALS = 3

  // access flags 0xA
  private static isPrime(I)Z
   L0
    LINENUMBER 54 L0
    ICONST_2
    ISTORE 1
   L1
    LINENUMBER 55 L1
   FRAME FULL [I I] []
    ILOAD 1
    ILOAD 0
    IF_ICMPGE L2
   L3
    LINENUMBER 56 L3
    ILOAD 0
    ILOAD 1
    IREM
    IFEQ L4
   L5
    LINENUMBER 57 L5
    ICONST_0
    IRETURN
   L4
    LINENUMBER 59 L4
   FRAME FULL [I I] []
    IINC 1 1
    GOTO L1
   L2
    LINENUMBER 61 L2
   FRAME FULL [I I] []
    ICONST_1
    IRETURN
   L6
    LOCALVARIABLE n I L0 L6 0
    LOCALVARIABLE i I L1 L6 1
    MAXSTACK = 2
    MAXLOCALS = 2
}

