// class version 55.0 (55)
// access flags 0x20
class original/Search {

  // compiled from: id_69.java

  // access flags 0x0
  <init>()V
   L0
    LINENUMBER 7 L0
    ALOAD 0
    INVOKESPECIAL java/lang/Object.<init> ()V
    RETURN
   L1
    LOCALVARIABLE this Loriginal/Search; L0 L1 0
    MAXSTACK = 1
    MAXLOCALS = 1

  // access flags 0x9
  // signature (Ljava/util/List<Ljava/lang/Integer;>;)I
  // declaration: int search(java.util.List<java.lang.Integer>)
  public static search(Ljava/util/List;)I
   L0
    LINENUMBER 70 L0
    ICONST_M1
    ISTORE 1
   L1
    LINENUMBER 71 L1
    BIPUSH 11
    NEWARRAY T_INT
    ASTORE 2
   L2
    LINENUMBER 72 L2
    ICONST_0
    ISTORE 3
   L3
   FRAME FULL [java/util/List I [I I] []
    ILOAD 3
    ALOAD 0
    INVOKEINTERFACE java/util/List.size ()I (itf)
    IF_ICMPGT L4
   L5
    LINENUMBER 73 L5
    ALOAD 2
    ALOAD 0
    ILOAD 3
    INVOKEINTERFACE java/util/List.get (I)Ljava/lang/Object; (itf)
    CHECKCAST java/lang/Integer
    INVOKEVIRTUAL java/lang/Integer.intValue ()I
    DUP2
    IALOAD
    ICONST_1
    IADD
    IASTORE
   L6
    LINENUMBER 72 L6
    IINC 3 1
    GOTO L3
   L4
    LINENUMBER 75 L4
   FRAME FULL [java/util/List I [I I] []
    ICONST_1
    ISTORE 3
   L7
   FRAME FULL [java/util/List I [I I] []
    ILOAD 3
    BIPUSH 11
    IF_ICMPGE L8
   L9
    LINENUMBER 76 L9
    ALOAD 2
    ILOAD 3
    IALOAD
    ILOAD 3
    IF_ICMPLT L10
   L11
    LINENUMBER 77 L11
    ILOAD 3
    ISTORE 1
   L10
    LINENUMBER 75 L10
   FRAME FULL [java/util/List I [I I] []
    IINC 3 1
    GOTO L7
   L8
    LINENUMBER 80 L8
   FRAME FULL [java/util/List I [I I] []
    ILOAD 1
    IRETURN
   L12
    LOCALVARIABLE i I L3 L4 3
    LOCALVARIABLE i I L7 L8 3
    LOCALVARIABLE lst Ljava/util/List; L0 L12 0
    // signature Ljava/util/List<Ljava/lang/Integer;>;
    // declaration: lst extends java.util.List<java.lang.Integer>
    LOCALVARIABLE max I L1 L12 1
    LOCALVARIABLE freq [I L2 L12 2
    MAXSTACK = 4
    MAXLOCALS = 4
}

