// class version 55.0 (55)
// access flags 0x20
class original/Solution1955 {

  // compiled from: id_1955.java

  // access flags 0x0
  <init>()V
   L0
    LINENUMBER 3 L0
    ALOAD 0
    INVOKESPECIAL java/lang/Object.<init> ()V
    RETURN
   L1
    LOCALVARIABLE this Loriginal/Solution1955; L0 L1 0
    MAXSTACK = 1
    MAXLOCALS = 1

  // access flags 0x1
  public countSpecialSubsequences([I)I
   L0
    LINENUMBER 5 L0
    LDC 1000000007
    ISTORE 2
   L1
    LINENUMBER 6 L1
    ALOAD 1
    ARRAYLENGTH
    ISTORE 3
   L2
    LINENUMBER 7 L2
    ILOAD 3
    ICONST_3
    MULTIANEWARRAY [[I 2
    ASTORE 4
   L3
    LINENUMBER 8 L3
    ALOAD 4
    ICONST_0
    AALOAD
    ICONST_0
    ALOAD 1
    ICONST_0
    IALOAD
    IFNE L4
    ICONST_1
    GOTO L5
   L4
   FRAME FULL [original/Solution1955 [I I I [[I] [[I I]
    ICONST_0
   L5
   FRAME FULL [original/Solution1955 [I I I [[I] [[I I I]
    IASTORE
   L6
    LINENUMBER 9 L6
    ICONST_1
    ISTORE 5
   L7
   FRAME FULL [original/Solution1955 [I I I [[I I] []
    ILOAD 5
    ILOAD 3
    IF_ICMPGE L8
   L9
    LINENUMBER 10 L9
    ALOAD 1
    ILOAD 5
    IALOAD
    IFNE L10
   L11
    LINENUMBER 11 L11
    ALOAD 4
    ILOAD 5
    AALOAD
    ICONST_0
    ICONST_2
    ALOAD 4
    ILOAD 5
    ICONST_1
    ISUB
    AALOAD
    ICONST_0
    IALOAD
    IMUL
    LDC 1000000007
    IREM
    ICONST_1
    IADD
    LDC 1000000007
    IREM
    IASTORE
   L12
    LINENUMBER 12 L12
    ALOAD 4
    ILOAD 5
    AALOAD
    ICONST_1
    ALOAD 4
    ILOAD 5
    ICONST_1
    ISUB
    AALOAD
    ICONST_1
    IALOAD
    IASTORE
   L13
    LINENUMBER 13 L13
    ALOAD 4
    ILOAD 5
    AALOAD
    ICONST_2
    ALOAD 4
    ILOAD 5
    ICONST_1
    ISUB
    AALOAD
    ICONST_2
    IALOAD
    IASTORE
    GOTO L14
   L10
    LINENUMBER 14 L10
   FRAME FULL [original/Solution1955 [I I I [[I I] []
    ALOAD 1
    ILOAD 5
    IALOAD
    ICONST_1
    IF_ICMPNE L15
   L16
    LINENUMBER 15 L16
    ALOAD 4
    ILOAD 5
    AALOAD
    ICONST_0
    ALOAD 4
    ILOAD 5
    ICONST_1
    ISUB
    AALOAD
    ICONST_0
    IALOAD
    IASTORE
   L17
    LINENUMBER 16 L17
    ALOAD 4
    ILOAD 5
    AALOAD
    ICONST_1
    ALOAD 4
    ILOAD 5
    ICONST_1
    ISUB
    AALOAD
    ICONST_0
    IALOAD
    ICONST_2
    ALOAD 4
    ILOAD 5
    ICONST_1
    ISUB
    AALOAD
    ICONST_1
    IALOAD
    IMUL
    LDC 1000000007
    IREM
    IADD
    LDC 1000000007
    IREM
    IASTORE
   L18
    LINENUMBER 17 L18
    ALOAD 4
    ILOAD 5
    AALOAD
    ICONST_2
    ALOAD 4
    ILOAD 5
    ICONST_1
    IADD
    AALOAD
    ICONST_2
    IALOAD
    IASTORE
    GOTO L14
   L15
    LINENUMBER 19 L15
   FRAME FULL [original/Solution1955 [I I I [[I I] []
    ALOAD 4
    ILOAD 5
    AALOAD
    ICONST_0
    ALOAD 4
    ILOAD 5
    ICONST_1
    ISUB
    AALOAD
    ICONST_0
    IALOAD
    IASTORE
   L19
    LINENUMBER 20 L19
    ALOAD 4
    ILOAD 5
    AALOAD
    ICONST_1
    ALOAD 4
    ILOAD 5
    ICONST_1
    ISUB
    AALOAD
    ICONST_1
    IALOAD
    IASTORE
   L20
    LINENUMBER 21 L20
    ALOAD 4
    ILOAD 5
    AALOAD
    ICONST_2
    ALOAD 4
    ILOAD 5
    ICONST_1
    ISUB
    AALOAD
    ICONST_1
    IALOAD
    ICONST_2
    ALOAD 4
    ILOAD 5
    ICONST_1
    ISUB
    AALOAD
    ICONST_2
    IALOAD
    IMUL
    LDC 1000000007
    IREM
    IADD
    LDC 1000000007
    IREM
    IASTORE
   L14
    LINENUMBER 9 L14
   FRAME FULL [original/Solution1955 [I I I [[I I] []
    IINC 5 1
    GOTO L7
   L8
    LINENUMBER 24 L8
   FRAME FULL [original/Solution1955 [I I I [[I I] []
    ALOAD 4
    ILOAD 3
    ICONST_1
    ISUB
    AALOAD
    ICONST_2
    IALOAD
    IRETURN
   L21
    LOCALVARIABLE i I L7 L8 5
    LOCALVARIABLE this Loriginal/Solution1955; L0 L21 0
    LOCALVARIABLE nums [I L0 L21 1
    LOCALVARIABLE mod I L1 L21 2
    LOCALVARIABLE n I L2 L21 3
    LOCALVARIABLE f [[I L3 L21 4
    MAXSTACK = 7
    MAXLOCALS = 6
}

