// class version 55.0 (55)
// access flags 0x20
class original/CheckDictCase {

  // compiled from: id_95.java

  // access flags 0x0
  <init>()V
   L0
    LINENUMBER 6 L0
    ALOAD 0
    INVOKESPECIAL java/lang/Object.<init> ()V
    RETURN
   L1
    LOCALVARIABLE this Loriginal/CheckDictCase; L0 L1 0
    MAXSTACK = 1
    MAXLOCALS = 1

  // access flags 0x9
  public static checkDictCase(Ljava/lang/Object;)Ljava/lang/Boolean;
   L0
    LINENUMBER 34 L0
    ALOAD 0
    INSTANCEOF java/util/Map
    IFEQ L1
   L2
    LINENUMBER 35 L2
    ALOAD 0
    CHECKCAST java/util/Map
    ASTORE 1
   L3
    LINENUMBER 36 L3
    ALOAD 1
    INVOKEINTERFACE java/util/Map.size ()I (itf)
    IFNE L4
   L5
    LINENUMBER 37 L5
    ICONST_0
    INVOKESTATIC java/lang/Boolean.valueOf (Z)Ljava/lang/Boolean;
    ARETURN
   L4
    LINENUMBER 39 L4
   FRAME FULL [java/lang/Object java/util/Map] []
    ICONST_1
    ISTORE 2
   L6
    LINENUMBER 40 L6
    ICONST_1
    ISTORE 3
   L7
    LINENUMBER 41 L7
    ALOAD 1
    INVOKEINTERFACE java/util/Map.keySet ()Ljava/util/Set; (itf)
    INVOKEINTERFACE java/util/Set.iterator ()Ljava/util/Iterator; (itf)
    ASTORE 4
   L8
   FRAME FULL [java/lang/Object java/util/Map I I java/util/Iterator] []
    ALOAD 4
    INVOKEINTERFACE java/util/Iterator.hasNext ()Z (itf)
    IFEQ L9
    ALOAD 4
    INVOKEINTERFACE java/util/Iterator.next ()Ljava/lang/Object; (itf)
    ASTORE 5
   L10
    LINENUMBER 42 L10
    ALOAD 5
    INSTANCEOF java/lang/String
    IFNE L11
   L12
    LINENUMBER 43 L12
    ALOAD 5
    CHECKCAST java/lang/String
    ASTORE 6
   L13
    LINENUMBER 44 L13
    ALOAD 6
    ALOAD 6
    INVOKEVIRTUAL java/lang/String.toLowerCase ()Ljava/lang/String;
    INVOKEVIRTUAL java/lang/String.equals (Ljava/lang/Object;)Z
    IFNE L14
   L15
    LINENUMBER 45 L15
    ICONST_0
    ISTORE 2
   L14
    LINENUMBER 47 L14
   FRAME FULL [java/lang/Object java/util/Map I I java/util/Iterator java/lang/Object java/lang/String] []
    ALOAD 6
    ALOAD 6
    INVOKEVIRTUAL java/lang/String.toUpperCase ()Ljava/lang/String;
    INVOKEVIRTUAL java/lang/String.equals (Ljava/lang/Object;)Z
    IFNE L16
   L17
    LINENUMBER 48 L17
    ICONST_0
    ISTORE 3
   L16
    LINENUMBER 50 L16
   FRAME FULL [java/lang/Object java/util/Map I I java/util/Iterator java/lang/Object java/lang/String] []
    GOTO L18
   L11
    LINENUMBER 51 L11
   FRAME FULL [java/lang/Object java/util/Map I I java/util/Iterator java/lang/Object] []
    ICONST_0
    INVOKESTATIC java/lang/Boolean.valueOf (Z)Ljava/lang/Boolean;
    ARETURN
   L18
    LINENUMBER 53 L18
   FRAME FULL [java/lang/Object java/util/Map I I java/util/Iterator java/lang/Object java/lang/String] []
    GOTO L8
   L9
    LINENUMBER 54 L9
   FRAME FULL [java/lang/Object java/util/Map I I java/util/Iterator] []
    ILOAD 2
    IFNE L19
    ILOAD 3
    IFEQ L20
   L19
   FRAME FULL [java/lang/Object java/util/Map I I java/util/Iterator] []
    ICONST_1
    GOTO L21
   L20
   FRAME FULL [java/lang/Object java/util/Map I I java/util/Iterator] []
    ICONST_0
   L21
   FRAME FULL [java/lang/Object java/util/Map I I java/util/Iterator] [I]
    INVOKESTATIC java/lang/Boolean.valueOf (Z)Ljava/lang/Boolean;
    ARETURN
   L1
    LINENUMBER 56 L1
   FRAME FULL [java/lang/Object] []
    ICONST_0
    INVOKESTATIC java/lang/Boolean.valueOf (Z)Ljava/lang/Boolean;
    ARETURN
   L22
    LOCALVARIABLE s Ljava/lang/String; L13 L16 6
    LOCALVARIABLE k Ljava/lang/Object; L10 L18 5
    LOCALVARIABLE m Ljava/util/Map; L3 L1 1
    LOCALVARIABLE allLower Z L6 L1 2
    LOCALVARIABLE allUpper Z L7 L1 3
    LOCALVARIABLE dict Ljava/lang/Object; L0 L22 0
    MAXSTACK = 2
    MAXLOCALS = 7
}

