// class version 55.0 (55)
// access flags 0x20
class original/CountDistinctCharacters {

  // compiled from: id_16.java

  // access flags 0x0
  <init>()V
   L0
    LINENUMBER 7 L0
    ALOAD 0
    INVOKESPECIAL java/lang/Object.<init> ()V
    RETURN
   L1
    LOCALVARIABLE this Loriginal/CountDistinctCharacters; L0 L1 0
    MAXSTACK = 1
    MAXLOCALS = 1

  // access flags 0x9
  public static countDistinctCharacters(Ljava/lang/String;)I
   L0
    LINENUMBER 27 L0
    NEW java/util/HashSet
    DUP
    INVOKESPECIAL java/util/HashSet.<init> ()V
    ASTORE 1
   L1
    LINENUMBER 28 L1
    ICONST_0
    ISTORE 2
   L2
   FRAME FULL [java/lang/String java/util/HashSet I] []
    ILOAD 2
    ALOAD 0
    INVOKEVIRTUAL java/lang/String.length ()I
    IF_ICMPLT L3
   L4
    LINENUMBER 29 L4
    ALOAD 1
    ALOAD 0
    ILOAD 2
    INVOKEVIRTUAL java/lang/String.charAt (I)C
    INVOKESTATIC java/lang/Character.toLowerCase (C)C
    INVOKESTATIC java/lang/Character.valueOf (C)Ljava/lang/Character;
    INVOKEINTERFACE java/util/Set.add (Ljava/lang/Object;)Z (itf)
    POP
   L5
    LINENUMBER 28 L5
    IINC 2 1
    GOTO L2
   L3
    LINENUMBER 31 L3
   FRAME FULL [java/lang/String java/util/HashSet I] []
    ALOAD 1
    INVOKEINTERFACE java/util/Set.size ()I (itf)
    IRETURN
   L6
    LOCALVARIABLE i I L2 L3 2
    LOCALVARIABLE string Ljava/lang/String; L0 L6 0
    LOCALVARIABLE distinctCharacters Ljava/util/Set; L1 L6 1
    // signature Ljava/util/Set<Ljava/lang/Character;>;
    // declaration: distinctCharacters extends java.util.Set<java.lang.Character>
    MAXSTACK = 3
    MAXLOCALS = 3
}

