// class version 55.0 (55)
// access flags 0x20
class original/Solution0017 {

  // compiled from: id_0017.java
  // access flags 0x19
  public final static INNERCLASS java/lang/invoke/MethodHandles$Lookup java/lang/invoke/MethodHandles Lookup

  // access flags 0x0
  <init>()V
   L0
    LINENUMBER 5 L0
    ALOAD 0
    INVOKESPECIAL java/lang/Object.<init> ()V
    RETURN
   L1
    LOCALVARIABLE this Loriginal/Solution0017; L0 L1 0
    MAXSTACK = 1
    MAXLOCALS = 1

  // access flags 0x1
  // signature (Ljava/lang/String;)Ljava/util/List<Ljava/lang/String;>;
  // declaration: java.util.List<java.lang.String> letterCombinations(java.lang.String)
  public letterCombinations(Ljava/lang/String;)Ljava/util/List;
   L0
    LINENUMBER 7 L0
    NEW java/util/ArrayList
    DUP
    INVOKESPECIAL java/util/ArrayList.<init> ()V
    ASTORE 2
   L1
    LINENUMBER 8 L1
    ALOAD 1
    INVOKEVIRTUAL java/lang/String.length ()I
    IFNE L2
   L3
    LINENUMBER 9 L3
    ALOAD 2
    ARETURN
   L2
    LINENUMBER 11 L2
   FRAME FULL [original/Solution0017 java/lang/String java/util/List] []
    ALOAD 2
    LDC ""
    INVOKEINTERFACE java/util/List.add (Ljava/lang/Object;)Z (itf)
    POP
   L4
    LINENUMBER 12 L4
    BIPUSH 8
    ANEWARRAY java/lang/String
    DUP
    ICONST_0
    LDC "abc"
    AASTORE
    DUP
    ICONST_1
    LDC "def"
    AASTORE
    DUP
    ICONST_2
    LDC "ghi"
    AASTORE
    DUP
    ICONST_3
    LDC "jkl"
    AASTORE
    DUP
    ICONST_4
    LDC "mno"
    AASTORE
    DUP
    ICONST_5
    LDC "pqrs"
    AASTORE
    DUP
    BIPUSH 6
    LDC "tuv"
    AASTORE
    DUP
    BIPUSH 7
    LDC "wxyz"
    AASTORE
    ASTORE 3
   L5
    LINENUMBER 13 L5
    ALOAD 1
    INVOKEVIRTUAL java/lang/String.toCharArray ()[C
    ASTORE 4
    ALOAD 4
    ARRAYLENGTH
    ISTORE 5
    ICONST_0
    ISTORE 6
   L6
   FRAME FULL [original/Solution0017 java/lang/String java/util/List [Ljava/lang/String; [C I I] []
    ILOAD 6
    ILOAD 5
    IF_ICMPGE L7
    ALOAD 4
    ILOAD 6
    CALOAD
    ISTORE 7
   L8
    LINENUMBER 14 L8
    ALOAD 3
    ILOAD 7
    BIPUSH 50
    ISUB
    AALOAD
    ASTORE 8
   L9
    LINENUMBER 15 L9
    NEW java/util/ArrayList
    DUP
    INVOKESPECIAL java/util/ArrayList.<init> ()V
    ASTORE 9
   L10
    LINENUMBER 16 L10
    ALOAD 2
    INVOKEINTERFACE java/util/List.iterator ()Ljava/util/Iterator; (itf)
    ASTORE 10
   L11
   FRAME FULL [original/Solution0017 java/lang/String java/util/List [Ljava/lang/String; [C I I I java/lang/String java/util/List java/util/Iterator] []
    ALOAD 10
    INVOKEINTERFACE java/util/Iterator.hasNext ()Z (itf)
    IFEQ L12
    ALOAD 10
    INVOKEINTERFACE java/util/Iterator.next ()Ljava/lang/Object; (itf)
    CHECKCAST java/lang/String
    ASTORE 11
   L13
    LINENUMBER 17 L13
    ALOAD 8
    LDC ""
    INVOKEVIRTUAL java/lang/String.split (Ljava/lang/String;)[Ljava/lang/String;
    ASTORE 12
    ALOAD 12
    ARRAYLENGTH
    ISTORE 13
    ICONST_0
    ISTORE 14
   L14
   FRAME FULL [original/Solution0017 java/lang/String java/util/List [Ljava/lang/String; [C I I I java/lang/String java/util/List java/util/Iterator java/lang/String [Ljava/lang/String; I I] []
    ILOAD 14
    ILOAD 13
    IF_ICMPGE L15
    ALOAD 12
    ILOAD 14
    AALOAD
    ASTORE 15
   L16
    LINENUMBER 18 L16
    ALOAD 9
    ALOAD 11
    ALOAD 15
    INVOKEDYNAMIC makeConcatWithConstants(Ljava/lang/String;Ljava/lang/String;)Ljava/lang/String; [
      // handle kind 0x6 : INVOKESTATIC
      java/lang/invoke/StringConcatFactory.makeConcatWithConstants(Ljava/lang/invoke/MethodHandles$Lookup;Ljava/lang/String;Ljava/lang/invoke/MethodType;Ljava/lang/String;[Ljava/lang/Object;)Ljava/lang/invoke/CallSite;
      // arguments:
      "\u0001\u0001"
    ]
    INVOKEINTERFACE java/util/List.add (Ljava/lang/Object;)Z (itf)
    POP
   L17
    LINENUMBER 17 L17
    IINC 14 1
    GOTO L14
   L15
    LINENUMBER 20 L15
   FRAME FULL [original/Solution0017 java/lang/String java/util/List [Ljava/lang/String; [C I I I java/lang/String java/util/List java/util/Iterator] []
    GOTO L11
   L12
    LINENUMBER 21 L12
   FRAME FULL [original/Solution0017 java/lang/String java/util/List [Ljava/lang/String; [C I I I java/lang/String java/util/List] []
    ALOAD 9
    ASTORE 2
   L18
    LINENUMBER 13 L18
    IINC 6 1
    GOTO L6
   L7
    LINENUMBER 23 L7
   FRAME FULL [original/Solution0017 java/lang/String java/util/List [Ljava/lang/String;] []
    ALOAD 2
    ARETURN
   L19
    LOCALVARIABLE b Ljava/lang/String; L16 L17 15
    LOCALVARIABLE a Ljava/lang/String; L13 L15 11
    LOCALVARIABLE s Ljava/lang/String; L9 L18 8
    LOCALVARIABLE t Ljava/util/List; L10 L18 9
    // signature Ljava/util/List<Ljava/lang/String;>;
    // declaration: t extends java.util.List<java.lang.String>
    LOCALVARIABLE i C L8 L18 7
    LOCALVARIABLE this Loriginal/Solution0017; L0 L19 0
    LOCALVARIABLE digits Ljava/lang/String; L0 L19 1
    LOCALVARIABLE ans Ljava/util/List; L1 L19 2
    // signature Ljava/util/List<Ljava/lang/String;>;
    // declaration: ans extends java.util.List<java.lang.String>
    LOCALVARIABLE d [Ljava/lang/String; L5 L19 3
    MAXSTACK = 4
    MAXLOCALS = 16
}

