// class version 55.0 (55)
// access flags 0x20
class original/Intersection {

  // compiled from: id_127.java

  // access flags 0x0
  <init>()V
   L0
    LINENUMBER 6 L0
    ALOAD 0
    INVOKESPECIAL java/lang/Object.<init> ()V
    RETURN
   L1
    LOCALVARIABLE this Loriginal/Intersection; L0 L1 0
    MAXSTACK = 1
    MAXLOCALS = 1

  // access flags 0x9
  // signature (Ljava/util/List<Ljava/lang/Integer;>;Ljava/util/List<Ljava/lang/Integer;>;)Ljava/lang/String;
  // declaration: java.lang.String intersection(java.util.List<java.lang.Integer>, java.util.List<java.lang.Integer>)
  public static intersection(Ljava/util/List;Ljava/util/List;)Ljava/lang/String;
   L0
    LINENUMBER 46 L0
    ALOAD 0
    ICONST_0
    INVOKEINTERFACE java/util/List.get (I)Ljava/lang/Object; (itf)
    CHECKCAST java/lang/Integer
    INVOKEVIRTUAL java/lang/Integer.intValue ()I
    ALOAD 1
    ICONST_0
    INVOKEINTERFACE java/util/List.get (I)Ljava/lang/Object; (itf)
    CHECKCAST java/lang/Integer
    INVOKEVIRTUAL java/lang/Integer.intValue ()I
    INVOKESTATIC java/lang/Math.max (II)I
    ISTORE 2
   L1
    LINENUMBER 47 L1
    ALOAD 0
    ICONST_1
    INVOKEINTERFACE java/util/List.get (I)Ljava/lang/Object; (itf)
    CHECKCAST java/lang/Integer
    INVOKEVIRTUAL java/lang/Integer.intValue ()I
    ALOAD 1
    ICONST_1
    INVOKEINTERFACE java/util/List.get (I)Ljava/lang/Object; (itf)
    CHECKCAST java/lang/Integer
    INVOKEVIRTUAL java/lang/Integer.intValue ()I
    INVOKESTATIC java/lang/Math.min (II)I
    ISTORE 3
   L2
    LINENUMBER 48 L2
    ILOAD 2
    ILOAD 3
    IF_ICMPLT L3
   L4
    LINENUMBER 49 L4
    LDC "NO"
    ARETURN
   L3
    LINENUMBER 51 L3
   FRAME FULL [java/util/List java/util/List I I] []
    ILOAD 3
    ILOAD 2
    ISUB
    INVOKESTATIC original/Intersection.isPrime (I)Z
    IFEQ L5
   L6
    LINENUMBER 52 L6
    LDC "YES"
    ARETURN
   L5
    LINENUMBER 54 L5
   FRAME FULL [java/util/List java/util/List I I] []
    LDC "NO"
    ARETURN
   L7
    LOCALVARIABLE interval1 Ljava/util/List; L0 L7 0
    // signature Ljava/util/List<Ljava/lang/Integer;>;
    // declaration: interval1 extends java.util.List<java.lang.Integer>
    LOCALVARIABLE interval2 Ljava/util/List; L0 L7 1
    // signature Ljava/util/List<Ljava/lang/Integer;>;
    // declaration: interval2 extends java.util.List<java.lang.Integer>
    LOCALVARIABLE start I L1 L7 2
    LOCALVARIABLE end I L2 L7 3
    MAXSTACK = 3
    MAXLOCALS = 4

  // access flags 0xA
  private static isPrime(I)Z
   L0
    LINENUMBER 58 L0
    ILOAD 0
    ICONST_2
    IF_ICMPGE L1
   L2
    LINENUMBER 59 L2
    ICONST_0
    IRETURN
   L1
    LINENUMBER 61 L1
   FRAME FULL [I] []
    ICONST_2
    ISTORE 1
   L3
   FRAME FULL [I I] []
    ILOAD 1
    I2D
    ILOAD 0
    I2D
    INVOKESTATIC java/lang/Math.sqrt (D)D
    DCMPG
    IFGT L4
   L5
    LINENUMBER 62 L5
    ILOAD 0
    ILOAD 1
    IREM
    IFNE L6
   L7
    LINENUMBER 63 L7
    ICONST_0
    IRETURN
   L6
    LINENUMBER 61 L6
   FRAME FULL [I I] []
    IINC 1 1
    GOTO L3
   L4
    LINENUMBER 66 L4
   FRAME FULL [I I] []
    ICONST_1
    IRETURN
   L8
    LOCALVARIABLE i I L3 L4 1
    LOCALVARIABLE n I L0 L8 0
    MAXSTACK = 4
    MAXLOCALS = 2
}

