// class version 55.0 (55)
// access flags 0x20
class original/Solution2397 {

  // compiled from: id_2397.java

  // access flags 0x0
  <init>()V
   L0
    LINENUMBER 3 L0
    ALOAD 0
    INVOKESPECIAL java/lang/Object.<init> ()V
    RETURN
   L1
    LOCALVARIABLE this Loriginal/Solution2397; L0 L1 0
    MAXSTACK = 1
    MAXLOCALS = 1

  // access flags 0x1
  public maximumRows([[II)I
   L0
    LINENUMBER 5 L0
    ALOAD 1
    ARRAYLENGTH
    ISTORE 3
   L1
    ALOAD 1
    ICONST_0
    AALOAD
    ARRAYLENGTH
    ISTORE 4
   L2
    LINENUMBER 6 L2
    ILOAD 3
    NEWARRAY T_INT
    ASTORE 5
   L3
    LINENUMBER 7 L3
    ICONST_0
    ISTORE 6
   L4
   FRAME FULL [original/Solution2397 [[I I I I [I I] []
    ILOAD 6
    ILOAD 3
    IF_ICMPGE L5
   L6
    LINENUMBER 8 L6
    ICONST_0
    ISTORE 7
   L7
   FRAME FULL [original/Solution2397 [[I I I I [I I I] []
    ILOAD 7
    ILOAD 4
    IF_ICMPGE L8
   L9
    LINENUMBER 9 L9
    ALOAD 1
    ILOAD 6
    AALOAD
    ILOAD 7
    IALOAD
    ICONST_1
    IF_ICMPNE L10
   L11
    LINENUMBER 10 L11
    ALOAD 5
    ILOAD 6
    DUP2
    IALOAD
    ICONST_1
    ILOAD 7
    ISHL
    IOR
    IASTORE
   L10
    LINENUMBER 8 L10
   FRAME FULL [original/Solution2397 [[I I I I [I I I] []
    IINC 7 1
    GOTO L7
   L8
    LINENUMBER 7 L8
   FRAME FULL [original/Solution2397 [[I I I I [I I I] []
    IINC 6 1
    GOTO L4
   L5
    LINENUMBER 14 L5
   FRAME FULL [original/Solution2397 [[I I I I [I I] []
    ICONST_0
    ISTORE 6
   L12
    LINENUMBER 15 L12
    ICONST_1
    ISTORE 7
   L13
   FRAME FULL [original/Solution2397 [[I I I I [I I I] []
    ILOAD 7
    ICONST_1
    ILOAD 4
    ISHL
    IF_ICMPLT L14
   L15
    LINENUMBER 16 L15
    ILOAD 7
    INVOKESTATIC java/lang/Integer.bitCount (I)I
    ILOAD 2
    IF_ICMPEQ L16
   L17
    LINENUMBER 17 L17
    GOTO L18
   L16
    LINENUMBER 19 L16
   FRAME FULL [original/Solution2397 [[I I I I [I I I] []
    ICONST_0
    ISTORE 8
   L19
    LINENUMBER 20 L19
    ALOAD 5
    ASTORE 9
    ALOAD 9
    ARRAYLENGTH
    ISTORE 10
    ICONST_0
    ISTORE 11
   L20
   FRAME FULL [original/Solution2397 [[I I I I [I I I I [I I I] []
    ILOAD 11
    ILOAD 10
    IF_ICMPGE L21
    ALOAD 9
    ILOAD 11
    IALOAD
    ISTORE 12
   L22
    LINENUMBER 21 L22
    ILOAD 12
    ILOAD 7
    IAND
    ILOAD 12
    IF_ICMPNE L23
   L24
    LINENUMBER 22 L24
    IINC 8 1
   L23
    LINENUMBER 20 L23
   FRAME FULL [original/Solution2397 [[I I I I [I I I I [I I I I] []
    IINC 11 1
    GOTO L20
   L21
    LINENUMBER 25 L21
   FRAME FULL [original/Solution2397 [[I I I I [I I I I [I I I] []
    ILOAD 6
    ILOAD 8
    INVOKESTATIC java/lang/Math.max (II)I
    ISTORE 6
   L18
    LINENUMBER 15 L18
   FRAME FULL [original/Solution2397 [[I I I I [I I I] []
    IINC 7 1
    GOTO L13
   L14
    LINENUMBER 27 L14
   FRAME FULL [original/Solution2397 [[I I I I [I I I] []
    ILOAD 6
    IRETURN
   L25
    LOCALVARIABLE j I L7 L8 7
    LOCALVARIABLE i I L4 L5 6
    LOCALVARIABLE x I L22 L23 12
    LOCALVARIABLE t I L19 L18 8
    LOCALVARIABLE mask I L13 L14 7
    LOCALVARIABLE this Loriginal/Solution2397; L0 L25 0
    LOCALVARIABLE matrix [[I L0 L25 1
    LOCALVARIABLE numSelect I L0 L25 2
    LOCALVARIABLE m I L1 L25 3
    LOCALVARIABLE n I L2 L25 4
    LOCALVARIABLE rows [I L3 L25 5
    LOCALVARIABLE ans I L12 L25 6
    MAXSTACK = 5
    MAXLOCALS = 13
}

