// class version 55.0 (55)
// access flags 0x20
class original/Solution2907 {

  // compiled from: id_2907.java

  // access flags 0x0
  <init>()V
   L0
    LINENUMBER 3 L0
    ALOAD 0
    INVOKESPECIAL java/lang/Object.<init> ()V
    RETURN
   L1
    LOCALVARIABLE this Loriginal/Solution2907; L0 L1 0
    MAXSTACK = 1
    MAXLOCALS = 1

  // access flags 0x1
  public maxProfit([I[I)I
   L0
    LINENUMBER 5 L0
    ALOAD 1
    ARRAYLENGTH
    ISTORE 3
   L1
    LINENUMBER 6 L1
    ICONST_M1
    ISTORE 4
   L2
    LINENUMBER 7 L2
    ICONST_0
    ISTORE 5
   L3
   FRAME FULL [original/Solution2907 [I [I I I I] []
    ILOAD 5
    ILOAD 3
    IF_ICMPGE L4
   L5
    LINENUMBER 8 L5
    ICONST_0
    ISTORE 6
   L6
    ICONST_0
    ISTORE 7
   L7
    LINENUMBER 9 L7
    ICONST_0
    ISTORE 8
   L8
   FRAME FULL [original/Solution2907 [I [I I I I I I I] []
    ILOAD 8
    ILOAD 5
    IF_ICMPGE L9
   L10
    LINENUMBER 10 L10
    ALOAD 1
    ILOAD 8
    IALOAD
    ALOAD 1
    ILOAD 5
    IALOAD
    IF_ICMPGE L11
   L12
    LINENUMBER 11 L12
    ILOAD 6
    ALOAD 2
    ILOAD 8
    IALOAD
    INVOKESTATIC java/lang/Math.max (II)I
    ISTORE 6
   L11
    LINENUMBER 9 L11
   FRAME FULL [original/Solution2907 [I [I I I I I I I] []
    IINC 8 1
    GOTO L8
   L9
    LINENUMBER 14 L9
   FRAME FULL [original/Solution2907 [I [I I I I I I I] []
    ILOAD 5
    ICONST_1
    IADD
    ISTORE 8
   L13
   FRAME FULL [original/Solution2907 [I [I I I I I I I] []
    ILOAD 8
    ILOAD 3
    IF_ICMPGE L14
   L15
    LINENUMBER 15 L15
    ALOAD 1
    ILOAD 5
    IALOAD
    ALOAD 1
    ILOAD 8
    IALOAD
    IF_ICMPGE L16
   L17
    LINENUMBER 16 L17
    ILOAD 7
    ALOAD 2
    ILOAD 8
    IALOAD
    INVOKESTATIC java/lang/Math.max (II)I
    ISTORE 7
   L16
    LINENUMBER 14 L16
   FRAME FULL [original/Solution2907 [I [I I I I I I I] []
    IINC 8 1
    GOTO L13
   L14
    LINENUMBER 19 L14
   FRAME FULL [original/Solution2907 [I [I I I I I I I] []
    ILOAD 6
    IFLE L18
    ILOAD 7
    IFLE L18
   L19
    LINENUMBER 20 L19
    ILOAD 4
    ILOAD 6
    ALOAD 2
    ILOAD 5
    IALOAD
    ISUB
    ILOAD 7
    IADD
    INVOKESTATIC java/lang/Math.max (II)I
    ISTORE 4
   L18
    LINENUMBER 7 L18
   FRAME FULL [original/Solution2907 [I [I I I I I I I] []
    IINC 5 1
    GOTO L3
   L4
    LINENUMBER 23 L4
   FRAME FULL [original/Solution2907 [I [I I I I] []
    ILOAD 4
    IRETURN
   L20
    LOCALVARIABLE i I L8 L9 8
    LOCALVARIABLE k I L13 L14 8
    LOCALVARIABLE left I L6 L18 6
    LOCALVARIABLE right I L7 L18 7
    LOCALVARIABLE j I L3 L4 5
    LOCALVARIABLE this Loriginal/Solution2907; L0 L20 0
    LOCALVARIABLE prices [I L0 L20 1
    LOCALVARIABLE profits [I L0 L20 2
    LOCALVARIABLE n I L1 L20 3
    LOCALVARIABLE ans I L2 L20 4
    MAXSTACK = 4
    MAXLOCALS = 9
}

