// class version 55.0 (55)
// access flags 0x20
class original/Solution1763 {

  // compiled from: id_1763.java

  // access flags 0x0
  <init>()V
   L0
    LINENUMBER 5 L0
    ALOAD 0
    INVOKESPECIAL java/lang/Object.<init> ()V
    RETURN
   L1
    LOCALVARIABLE this Loriginal/Solution1763; L0 L1 0
    MAXSTACK = 1
    MAXLOCALS = 1

  // access flags 0x1
  public longestNiceSubstring(Ljava/lang/String;)Ljava/lang/String;
   L0
    LINENUMBER 7 L0
    ALOAD 1
    INVOKEVIRTUAL java/lang/String.length ()I
    ISTORE 2
   L1
    LINENUMBER 8 L1
    ICONST_M1
    ISTORE 3
   L2
    LINENUMBER 9 L2
    ICONST_0
    ISTORE 4
   L3
    LINENUMBER 10 L3
    ICONST_0
    ISTORE 5
   L4
   FRAME FULL [original/Solution1763 java/lang/String I I I I] []
    ILOAD 5
    ILOAD 2
    IF_ICMPGE L5
   L6
    LINENUMBER 11 L6
    NEW java/util/HashSet
    DUP
    INVOKESPECIAL java/util/HashSet.<init> ()V
    ASTORE 6
   L7
    LINENUMBER 12 L7
    ILOAD 5
    ISTORE 7
   L8
   FRAME FULL [original/Solution1763 java/lang/String I I I I java/util/HashSet I] []
    ILOAD 7
    ILOAD 2
    IF_ICMPGE L9
   L10
    LINENUMBER 13 L10
    ALOAD 6
    ALOAD 1
    ILOAD 7
    INVOKEVIRTUAL java/lang/String.charAt (I)C
    INVOKESTATIC java/lang/Character.valueOf (C)Ljava/lang/Character;
    INVOKEINTERFACE java/util/Set.add (Ljava/lang/Object;)Z (itf)
    POP
   L11
    LINENUMBER 14 L11
    ICONST_1
    ISTORE 8
   L12
    LINENUMBER 15 L12
    ALOAD 6
    INVOKEINTERFACE java/util/Set.iterator ()Ljava/util/Iterator; (itf)
    ASTORE 9
   L13
   FRAME FULL [original/Solution1763 java/lang/String I I I I java/util/HashSet I I java/util/Iterator] []
    ALOAD 9
    INVOKEINTERFACE java/util/Iterator.hasNext ()Z (itf)
    IFEQ L14
    ALOAD 9
    INVOKEINTERFACE java/util/Iterator.next ()Ljava/lang/Object; (itf)
    CHECKCAST java/lang/Character
    INVOKEVIRTUAL java/lang/Character.charValue ()C
    ISTORE 10
   L15
    LINENUMBER 16 L15
    ILOAD 10
    BIPUSH 32
    IXOR
    I2C
    ISTORE 11
   L16
    LINENUMBER 17 L16
    ALOAD 6
    ILOAD 10
    INVOKESTATIC java/lang/Character.valueOf (C)Ljava/lang/Character;
    INVOKEINTERFACE java/util/Set.contains (Ljava/lang/Object;)Z (itf)
    IFEQ L17
    ALOAD 6
    ILOAD 11
    INVOKESTATIC java/lang/Character.valueOf (C)Ljava/lang/Character;
    INVOKEINTERFACE java/util/Set.contains (Ljava/lang/Object;)Z (itf)
    IFNE L18
   L17
    LINENUMBER 18 L17
   FRAME FULL [original/Solution1763 java/lang/String I I I I java/util/HashSet I I java/util/Iterator I I] []
    ICONST_0
    ISTORE 8
   L19
    LINENUMBER 19 L19
    GOTO L14
   L18
    LINENUMBER 21 L18
   FRAME FULL [original/Solution1763 java/lang/String I I I I java/util/HashSet I I java/util/Iterator I I] []
    GOTO L13
   L14
    LINENUMBER 22 L14
   FRAME FULL [original/Solution1763 java/lang/String I I I I java/util/HashSet I I java/util/Iterator] []
    ILOAD 8
    IFEQ L20
    ILOAD 4
    ILOAD 7
    ILOAD 5
    ISUB
    ICONST_1
    IADD
    IF_ICMPGE L20
   L21
    LINENUMBER 23 L21
    ILOAD 7
    ILOAD 5
    ISUB
    ICONST_1
    IADD
    ISTORE 4
   L22
    LINENUMBER 24 L22
    ILOAD 5
    ISTORE 3
   L20
    LINENUMBER 12 L20
   FRAME FULL [original/Solution1763 java/lang/String I I I I java/util/HashSet I I java/util/Iterator] []
    IINC 7 1
    GOTO L8
   L9
    LINENUMBER 10 L9
   FRAME FULL [original/Solution1763 java/lang/String I I I I java/util/HashSet I] []
    IINC 5 1
    GOTO L4
   L5
    LINENUMBER 28 L5
   FRAME FULL [original/Solution1763 java/lang/String I I I I] []
    ILOAD 3
    ICONST_M1
    IF_ICMPNE L23
    LDC ""
    GOTO L24
   L23
   FRAME FULL [original/Solution1763 java/lang/String I I I I] []
    ALOAD 1
    ILOAD 3
    ILOAD 3
    ILOAD 4
    IADD
    INVOKEVIRTUAL java/lang/String.substring (II)Ljava/lang/String;
   L24
   FRAME FULL [original/Solution1763 java/lang/String I I I I] [java/lang/String]
    POP
    LDC ""
    ARETURN
   L25
    LOCALVARIABLE b C L16 L18 11
    LOCALVARIABLE a C L15 L18 10
    LOCALVARIABLE ok Z L12 L20 8
    LOCALVARIABLE j I L8 L9 7
    LOCALVARIABLE ss Ljava/util/Set; L7 L9 6
    // signature Ljava/util/Set<Ljava/lang/Character;>;
    // declaration: ss extends java.util.Set<java.lang.Character>
    LOCALVARIABLE i I L4 L5 5
    LOCALVARIABLE this Loriginal/Solution1763; L0 L25 0
    LOCALVARIABLE s Ljava/lang/String; L0 L25 1
    LOCALVARIABLE n I L1 L25 2
    LOCALVARIABLE k I L2 L25 3
    LOCALVARIABLE mx I L3 L25 4
    MAXSTACK = 4
    MAXLOCALS = 12
}

