// class version 55.0 (55)
// access flags 0x20
class original/SortArray {

  // compiled from: id_116.java
  NESTMEMBER original/SortArray$1
  // access flags 0x0
  INNERCLASS original/SortArray$1 null null

  // access flags 0x0
  <init>()V
   L0
    LINENUMBER 9 L0
    ALOAD 0
    INVOKESPECIAL java/lang/Object.<init> ()V
    RETURN
   L1
    LOCALVARIABLE this Loriginal/SortArray; L0 L1 0
    MAXSTACK = 1
    MAXLOCALS = 1

  // access flags 0x9
  // signature (Ljava/util/List<Ljava/lang/Object;>;)Ljava/util/List<Ljava/lang/Object;>;
  // declaration: java.util.List<java.lang.Object> sortArray(java.util.List<java.lang.Object>)
  public static sortArray(Ljava/util/List;)Ljava/util/List;
   L0
    LINENUMBER 35 L0
    NEW java/util/ArrayList
    DUP
    INVOKESPECIAL java/util/ArrayList.<init> ()V
    ASTORE 1
   L1
    LINENUMBER 36 L1
    ICONST_0
    ISTORE 2
   L2
   FRAME FULL [java/util/List java/util/ArrayList I] []
    ILOAD 2
    ALOAD 0
    INVOKEINTERFACE java/util/List.size ()I (itf)
    IF_ICMPGE L3
   L4
    LINENUMBER 37 L4
    ALOAD 0
    ILOAD 2
    INVOKEINTERFACE java/util/List.get (I)Ljava/lang/Object; (itf)
    CHECKCAST java/lang/Number
    INVOKEVIRTUAL java/lang/Number.intValue ()I
    ISTORE 3
   L5
    LINENUMBER 38 L5
    ICONST_0
    ISTORE 4
   L6
    LINENUMBER 39 L6
   FRAME FULL [java/util/List java/util/ArrayList I I I] []
    ILOAD 3
    IFLE L7
   L8
    LINENUMBER 40 L8
    ILOAD 4
    ILOAD 3
    ICONST_2
    IREM
    IADD
    ISTORE 4
   L9
    LINENUMBER 41 L9
    ILOAD 3
    ICONST_2
    IDIV
    ISTORE 3
    GOTO L6
   L7
    LINENUMBER 43 L7
   FRAME FULL [java/util/List java/util/ArrayList I I I] []
    ALOAD 1
    ICONST_2
    NEWARRAY T_INT
    DUP
    ICONST_0
    ILOAD 4
    IASTORE
    DUP
    ICONST_1
    ALOAD 0
    ILOAD 2
    INVOKEINTERFACE java/util/List.get (I)Ljava/lang/Object; (itf)
    CHECKCAST java/lang/Number
    INVOKEVIRTUAL java/lang/Number.intValue ()I
    IASTORE
    INVOKEINTERFACE java/util/List.add (Ljava/lang/Object;)Z (itf)
    POP
   L10
    LINENUMBER 36 L10
    IINC 2 1
    GOTO L2
   L3
    LINENUMBER 45 L3
   FRAME FULL [java/util/List java/util/ArrayList I] []
    ALOAD 1
    NEW original/SortArray$1
    DUP
    INVOKESPECIAL original/SortArray$1.<init> ()V
    INVOKESTATIC java/util/Collections.sort (Ljava/util/List;Ljava/util/Comparator;)V
   L11
    LINENUMBER 55 L11
    NEW java/util/ArrayList
    DUP
    INVOKESPECIAL java/util/ArrayList.<init> ()V
    ASTORE 2
   L12
    LINENUMBER 56 L12
    ICONST_0
    ISTORE 3
   L13
   FRAME FULL [java/util/List java/util/ArrayList java/util/ArrayList I] []
    ILOAD 3
    ALOAD 1
    INVOKEINTERFACE java/util/List.size ()I (itf)
    IF_ICMPLT L14
   L15
    LINENUMBER 57 L15
    ALOAD 2
    ALOAD 1
    ILOAD 3
    INVOKEINTERFACE java/util/List.get (I)Ljava/lang/Object; (itf)
    CHECKCAST [I
    ICONST_1
    IALOAD
    INVOKESTATIC java/lang/Integer.valueOf (I)Ljava/lang/Integer;
    INVOKEINTERFACE java/util/List.add (Ljava/lang/Object;)Z (itf)
    POP
   L16
    LINENUMBER 56 L16
    IINC 3 1
    GOTO L13
   L14
    LINENUMBER 59 L14
   FRAME FULL [java/util/List java/util/ArrayList java/util/ArrayList I] []
    ALOAD 2
    ARETURN
   L17
    LOCALVARIABLE num I L5 L10 3
    LOCALVARIABLE ones I L6 L10 4
    LOCALVARIABLE i I L2 L3 2
    LOCALVARIABLE i I L13 L14 3
    LOCALVARIABLE arr Ljava/util/List; L0 L17 0
    // signature Ljava/util/List<Ljava/lang/Object;>;
    // declaration: arr extends java.util.List<java.lang.Object>
    LOCALVARIABLE sorted Ljava/util/List; L1 L17 1
    // signature Ljava/util/List<Ljava/lang/Object;>;
    // declaration: sorted extends java.util.List<java.lang.Object>
    LOCALVARIABLE result Ljava/util/List; L12 L17 2
    // signature Ljava/util/List<Ljava/lang/Object;>;
    // declaration: result extends java.util.List<java.lang.Object>
    MAXSTACK = 6
    MAXLOCALS = 5
}

