// class version 55.0 (55)
// access flags 0x20
class original/Unique {

  // compiled from: id_34.java

  // access flags 0x0
  <init>()V
   L0
    LINENUMBER 7 L0
    ALOAD 0
    INVOKESPECIAL java/lang/Object.<init> ()V
    RETURN
   L1
    LOCALVARIABLE this Loriginal/Unique; L0 L1 0
    MAXSTACK = 1
    MAXLOCALS = 1

  // access flags 0x9
  // signature (Ljava/util/List<Ljava/lang/Integer;>;)Ljava/util/List<Ljava/lang/Integer;>;
  // declaration: java.util.List<java.lang.Integer> unique(java.util.List<java.lang.Integer>)
  public static unique(Ljava/util/List;)Ljava/util/List;
   L0
    LINENUMBER 17 L0
    NEW java/util/HashSet
    DUP
    INVOKESPECIAL java/util/HashSet.<init> ()V
    ASTORE 1
   L1
    LINENUMBER 18 L1
    ALOAD 0
    INVOKEINTERFACE java/util/List.iterator ()Ljava/util/Iterator; (itf)
    ASTORE 2
   L2
   FRAME FULL [java/util/List java/util/Set java/util/Iterator] []
    ALOAD 2
    INVOKEINTERFACE java/util/Iterator.hasNext ()Z (itf)
    IFEQ L3
    ALOAD 2
    INVOKEINTERFACE java/util/Iterator.next ()Ljava/lang/Object; (itf)
    CHECKCAST java/lang/Integer
    ASTORE 3
   L4
    LINENUMBER 19 L4
    ALOAD 1
    ALOAD 3
    INVOKEINTERFACE java/util/Set.add (Ljava/lang/Object;)Z (itf)
    POP
   L5
    LINENUMBER 20 L5
    GOTO L2
   L3
    LINENUMBER 21 L3
   FRAME FULL [java/util/List java/util/Set] []
    NEW java/util/ArrayList
    DUP
    ALOAD 1
    INVOKESPECIAL java/util/ArrayList.<init> (Ljava/util/Collection;)V
    ASTORE 2
   L6
    LINENUMBER 22 L6
    ALOAD 2
    INVOKESTATIC java/util/Collections.sort (Ljava/util/List;)V
   L7
    LINENUMBER 23 L7
    ALOAD 2
    ARETURN
   L8
    LOCALVARIABLE i Ljava/lang/Integer; L4 L5 3
    LOCALVARIABLE l Ljava/util/List; L0 L8 0
    // signature Ljava/util/List<Ljava/lang/Integer;>;
    // declaration: l extends java.util.List<java.lang.Integer>
    LOCALVARIABLE set Ljava/util/Set; L1 L8 1
    // signature Ljava/util/Set<Ljava/lang/Integer;>;
    // declaration: set extends java.util.Set<java.lang.Integer>
    LOCALVARIABLE result Ljava/util/List; L6 L8 2
    // signature Ljava/util/List<Ljava/lang/Integer;>;
    // declaration: result extends java.util.List<java.lang.Integer>
    MAXSTACK = 3
    MAXLOCALS = 4
}

