// class version 55.0 (55)
// access flags 0x20
class original/SplitWords {

  // compiled from: id_125.java

  // access flags 0x0
  <init>()V
   L0
    LINENUMBER 6 L0
    ALOAD 0
    INVOKESPECIAL java/lang/Object.<init> ()V
    RETURN
   L1
    LOCALVARIABLE this Loriginal/SplitWords; L0 L1 0
    MAXSTACK = 1
    MAXLOCALS = 1

  // access flags 0x9
  public static splitWords(Ljava/lang/String;)Ljava/lang/Object;
   L0
    LINENUMBER 34 L0
    ALOAD 0
    LDC " "
    INVOKEVIRTUAL java/lang/String.contains (Ljava/lang/CharSequence;)Z
    IFEQ L1
   L2
    LINENUMBER 35 L2
    ALOAD 0
    LDC " "
    INVOKEVIRTUAL java/lang/String.split (Ljava/lang/String;)[Ljava/lang/String;
    INVOKESTATIC java/util/Arrays.asList ([Ljava/lang/Object;)Ljava/util/List;
    ARETURN
   L1
    LINENUMBER 36 L1
   FRAME FULL [java/lang/String] []
    ALOAD 0
    LDC ","
    INVOKEVIRTUAL java/lang/String.contains (Ljava/lang/CharSequence;)Z
    IFEQ L3
   L4
    LINENUMBER 37 L4
    ALOAD 0
    LDC ","
    INVOKEVIRTUAL java/lang/String.split (Ljava/lang/String;)[Ljava/lang/String;
    INVOKESTATIC java/util/Arrays.asList ([Ljava/lang/Object;)Ljava/util/List;
    ARETURN
   L3
    LINENUMBER 39 L3
   FRAME FULL [java/lang/String] []
    ICONST_0
    ISTORE 1
   L5
    LINENUMBER 40 L5
    ICONST_0
    ISTORE 2
   L6
   FRAME FULL [java/lang/String I I] []
    ILOAD 2
    ALOAD 0
    INVOKEVIRTUAL java/lang/String.length ()I
    IF_ICMPGE L7
   L8
    LINENUMBER 41 L8
    ALOAD 0
    ILOAD 2
    INVOKEVIRTUAL java/lang/String.charAt (I)C
    BIPUSH 97
    IF_ICMPGE L9
    ALOAD 0
    ILOAD 2
    INVOKEVIRTUAL java/lang/String.charAt (I)C
    BIPUSH 122
    IF_ICMPGT L9
    ALOAD 0
    ILOAD 2
    INVOKEVIRTUAL java/lang/String.charAt (I)C
    BIPUSH 97
    ISUB
    ICONST_2
    IREM
    ICONST_1
    IF_ICMPNE L9
   L10
    LINENUMBER 42 L10
    IINC 1 1
   L9
    LINENUMBER 40 L9
   FRAME FULL [java/lang/String I I] []
    IINC 2 1
    GOTO L6
   L7
    LINENUMBER 45 L7
   FRAME FULL [java/lang/String I I] []
    ILOAD 1
    INVOKESTATIC java/lang/Integer.valueOf (I)Ljava/lang/Integer;
    ARETURN
   L11
    LOCALVARIABLE i I L6 L7 2
    LOCALVARIABLE count I L5 L11 1
    LOCALVARIABLE txt Ljava/lang/String; L0 L11 0
    MAXSTACK = 2
    MAXLOCALS = 3
}

