// class version 55.0 (55)
// access flags 0x20
class original/ATM {

  // compiled from: id_2241.java

  // access flags 0x2
  private [I d

  // access flags 0x2
  private I m

  // access flags 0x2
  private [J cnt

  // access flags 0x1
  public <init>()V
   L0
    LINENUMBER 8 L0
    ALOAD 0
    INVOKESPECIAL java/lang/Object.<init> ()V
   L1
    LINENUMBER 4 L1
    ALOAD 0
    ICONST_5
    NEWARRAY T_INT
    DUP
    ICONST_0
    BIPUSH 20
    IASTORE
    DUP
    ICONST_1
    BIPUSH 50
    IASTORE
    DUP
    ICONST_2
    BIPUSH 100
    IASTORE
    DUP
    ICONST_3
    SIPUSH 200
    IASTORE
    DUP
    ICONST_4
    SIPUSH 500
    IASTORE
    PUTFIELD original/ATM.d : [I
   L2
    LINENUMBER 5 L2
    ALOAD 0
    ALOAD 0
    GETFIELD original/ATM.d : [I
    ARRAYLENGTH
    PUTFIELD original/ATM.m : I
   L3
    LINENUMBER 6 L3
    ALOAD 0
    ICONST_5
    NEWARRAY T_LONG
    PUTFIELD original/ATM.cnt : [J
   L4
    LINENUMBER 9 L4
    RETURN
   L5
    LOCALVARIABLE this Loriginal/ATM; L0 L5 0
    MAXSTACK = 5
    MAXLOCALS = 1

  // access flags 0x1
  public deposit([I)V
   L0
    LINENUMBER 12 L0
    ICONST_0
    ISTORE 2
   L1
   FRAME FULL [original/ATM [I I] []
    ILOAD 2
    ALOAD 1
    ARRAYLENGTH
    IF_ICMPGE L2
   L3
    LINENUMBER 13 L3
    ALOAD 0
    GETFIELD original/ATM.cnt : [J
    ILOAD 2
    DUP2
    LALOAD
    ALOAD 1
    ILOAD 2
    IALOAD
    I2L
    LADD
    LASTORE
   L4
    LINENUMBER 12 L4
    IINC 2 1
    GOTO L1
   L2
    LINENUMBER 15 L2
   FRAME FULL [original/ATM [I] []
    RETURN
   L5
    LOCALVARIABLE i I L1 L2 2
    LOCALVARIABLE this Loriginal/ATM; L0 L5 0
    LOCALVARIABLE banknotesCount [I L0 L5 1
    MAXSTACK = 6
    MAXLOCALS = 3

  // access flags 0x1
  public withdraw(I)[I
   L0
    LINENUMBER 18 L0
    ALOAD 0
    GETFIELD original/ATM.m : I
    NEWARRAY T_INT
    ASTORE 2
   L1
    LINENUMBER 19 L1
    ALOAD 0
    GETFIELD original/ATM.m : I
    ICONST_1
    ISUB
    ISTORE 3
   L2
   FRAME FULL [original/ATM I [I I] []
    ILOAD 3
    IFLT L3
   L4
    LINENUMBER 20 L4
    ALOAD 2
    ILOAD 3
    ILOAD 1
    ALOAD 0
    GETFIELD original/ATM.d : [I
    ILOAD 3
    IALOAD
    IDIV
    I2L
    ALOAD 0
    GETFIELD original/ATM.cnt : [J
    ILOAD 3
    LALOAD
    INVOKESTATIC java/lang/Math.min (JJ)J
    L2I
    IASTORE
   L5
    LINENUMBER 21 L5
    ILOAD 1
    ALOAD 2
    ILOAD 3
    IALOAD
    ALOAD 0
    GETFIELD original/ATM.d : [I
    ILOAD 3
    IALOAD
    IMUL
    ISUB
    ISTORE 1
   L6
    LINENUMBER 19 L6
    IINC 3 -1
    GOTO L2
   L3
    LINENUMBER 23 L3
   FRAME FULL [original/ATM I [I] []
    ILOAD 1
    IFLE L7
   L8
    LINENUMBER 24 L8
    ICONST_1
    NEWARRAY T_INT
    DUP
    ICONST_0
    ICONST_M1
    IASTORE
    ARETURN
   L7
    LINENUMBER 26 L7
   FRAME FULL [original/ATM I [I] []
    ICONST_0
    ISTORE 3
   L9
   FRAME FULL [original/ATM I [I I] []
    ILOAD 3
    ALOAD 0
    GETFIELD original/ATM.m : I
    IF_ICMPGE L10
   L11
    LINENUMBER 27 L11
    ALOAD 0
    GETFIELD original/ATM.cnt : [J
    ILOAD 3
    DUP2
    LALOAD
    ALOAD 2
    ILOAD 3
    IALOAD
    I2L
    LSUB
    LASTORE
   L12
    LINENUMBER 26 L12
    IINC 3 1
    GOTO L9
   L10
    LINENUMBER 29 L10
   FRAME FULL [original/ATM I [I] []
    ALOAD 2
    ARETURN
   L13
    LOCALVARIABLE i I L2 L3 3
    LOCALVARIABLE i I L9 L10 3
    LOCALVARIABLE this Loriginal/ATM; L0 L13 0
    LOCALVARIABLE amount I L0 L13 1
    LOCALVARIABLE ans [I L1 L13 2
    MAXSTACK = 6
    MAXLOCALS = 4
}

