// class version 55.0 (55)
// access flags 0x20
class original/SameChars {

  // compiled from: id_54.java

  // access flags 0x0
  <init>()V
   L0
    LINENUMBER 4 L0
    ALOAD 0
    INVOKESPECIAL java/lang/Object.<init> ()V
    RETURN
   L1
    LOCALVARIABLE this Loriginal/SameChars; L0 L1 0
    MAXSTACK = 1
    MAXLOCALS = 1

  // access flags 0x9
  public static sameChars(Ljava/lang/String;Ljava/lang/String;)Ljava/lang/Boolean;
   L0
    LINENUMBER 26 L0
    BIPUSH 26
    NEWARRAY T_INT
    ASTORE 2
   L1
    LINENUMBER 27 L1
    BIPUSH 26
    NEWARRAY T_INT
    ASTORE 3
   L2
    LINENUMBER 28 L2
    ICONST_0
    ISTORE 4
   L3
   FRAME FULL [java/lang/String java/lang/String [I [I I] []
    ILOAD 4
    ALOAD 0
    INVOKEVIRTUAL java/lang/String.length ()I
    IF_ICMPGE L4
   L5
    LINENUMBER 29 L5
    ALOAD 2
    ALOAD 0
    ILOAD 4
    INVOKEVIRTUAL java/lang/String.charAt (I)C
    BIPUSH 97
    ISUB
    ICONST_1
    IASTORE
   L6
    LINENUMBER 28 L6
    IINC 4 1
    GOTO L3
   L4
    LINENUMBER 32 L4
   FRAME FULL [java/lang/String java/lang/String [I [I I] []
    ICONST_0
    ISTORE 4
   L7
   FRAME FULL [java/lang/String java/lang/String [I [I I] []
    ILOAD 4
    ALOAD 1
    INVOKEVIRTUAL java/lang/String.length ()I
    IF_ICMPGT L8
   L9
    LINENUMBER 33 L9
    ALOAD 3
    ALOAD 1
    ILOAD 4
    INVOKEVIRTUAL java/lang/String.charAt (I)C
    BIPUSH 97
    ISUB
    ICONST_1
    IASTORE
   L10
    LINENUMBER 32 L10
    IINC 4 1
    GOTO L7
   L8
    LINENUMBER 35 L8
   FRAME FULL [java/lang/String java/lang/String [I [I I] []
    ICONST_0
    ISTORE 4
   L11
   FRAME FULL [java/lang/String java/lang/String [I [I I] []
    ILOAD 4
    BIPUSH 26
    IF_ICMPGE L12
   L13
    LINENUMBER 36 L13
    ALOAD 2
    ILOAD 4
    IALOAD
    ALOAD 3
    ILOAD 4
    IALOAD
    IF_ICMPEQ L14
   L15
    LINENUMBER 37 L15
    ICONST_0
    INVOKESTATIC java/lang/Boolean.valueOf (Z)Ljava/lang/Boolean;
    ARETURN
   L14
    LINENUMBER 35 L14
   FRAME FULL [java/lang/String java/lang/String [I [I I] []
    IINC 4 1
    GOTO L11
   L12
    LINENUMBER 40 L12
   FRAME FULL [java/lang/String java/lang/String [I [I I] []
    ICONST_1
    INVOKESTATIC java/lang/Boolean.valueOf (Z)Ljava/lang/Boolean;
    ARETURN
   L16
    LOCALVARIABLE i I L3 L4 4
    LOCALVARIABLE i I L7 L8 4
    LOCALVARIABLE i I L11 L12 4
    LOCALVARIABLE s0 Ljava/lang/String; L0 L16 0
    LOCALVARIABLE s1 Ljava/lang/String; L0 L16 1
    LOCALVARIABLE count0 [I L1 L16 2
    LOCALVARIABLE count1 [I L2 L16 3
    MAXSTACK = 3
    MAXLOCALS = 5
}

