// class version 55.0 (55)
// access flags 0x20
class original/IsSimplePower {

  // compiled from: id_76.java

  // access flags 0x0
  <init>()V
   L0
    LINENUMBER 3 L0
    ALOAD 0
    INVOKESPECIAL java/lang/Object.<init> ()V
    RETURN
   L1
    LOCALVARIABLE this Loriginal/IsSimplePower; L0 L1 0
    MAXSTACK = 1
    MAXLOCALS = 1

  // access flags 0x9
  public static isSimplePower(II)Ljava/lang/Boolean;
   L0
    LINENUMBER 38 L0
    ILOAD 0
    ICONST_1
    IF_ICMPNE L1
   L2
    LINENUMBER 39 L2
    ICONST_1
    INVOKESTATIC java/lang/Boolean.valueOf (Z)Ljava/lang/Boolean;
    ARETURN
   L1
    LINENUMBER 41 L1
   FRAME FULL [I I] []
    ILOAD 1
    ICONST_1
    IF_ICMPNE L3
   L4
    LINENUMBER 42 L4
    ICONST_0
    INVOKESTATIC java/lang/Boolean.valueOf (Z)Ljava/lang/Boolean;
    ARETURN
   L3
    LINENUMBER 44 L3
   FRAME FULL [I I] []
    ILOAD 1
    ISTORE 2
   L5
    LINENUMBER 45 L5
   FRAME FULL [I I I] []
    ILOAD 2
    ILOAD 0
    IF_ICMPGT L6
   L7
    LINENUMBER 46 L7
    ILOAD 2
    ILOAD 1
    IMUL
    ISTORE 2
    GOTO L5
   L6
    LINENUMBER 48 L6
   FRAME FULL [I I I] []
    ILOAD 2
    ILOAD 0
    IF_ICMPNE L8
    ICONST_1
    GOTO L9
   L8
   FRAME FULL [I I I] []
    ICONST_0
   L9
   FRAME FULL [I I I] [I]
    INVOKESTATIC java/lang/Boolean.valueOf (Z)Ljava/lang/Boolean;
    ARETURN
   L10
    LOCALVARIABLE x I L0 L10 0
    LOCALVARIABLE n I L0 L10 1
    LOCALVARIABLE y I L5 L10 2
    MAXSTACK = 2
    MAXLOCALS = 3
}

