// class version 55.0 (55)
// access flags 0x20
class original/Solution2093 {

  // compiled from: id_2093.java
  // access flags 0x19
  public final static INNERCLASS java/lang/invoke/MethodHandles$Lookup java/lang/invoke/MethodHandles Lookup

  // access flags 0x0
  <init>()V
   L0
    LINENUMBER 8 L0
    ALOAD 0
    INVOKESPECIAL java/lang/Object.<init> ()V
    RETURN
   L1
    LOCALVARIABLE this Loriginal/Solution2093; L0 L1 0
    MAXSTACK = 1
    MAXLOCALS = 1

  // access flags 0x1
  public minimumCost(I[[II)I
   L0
    LINENUMBER 10 L0
    ILOAD 1
    ANEWARRAY java/util/List
    ASTORE 4
   L1
    LINENUMBER 11 L1
    ICONST_0
    ISTORE 5
   L2
   FRAME FULL [original/Solution2093 I [[I I [Ljava/util/List; I] []
    ILOAD 5
    ILOAD 1
    IF_ICMPGE L3
   L4
    LINENUMBER 12 L4
    ALOAD 4
    ILOAD 5
    NEW java/util/ArrayList
    DUP
    INVOKESPECIAL java/util/ArrayList.<init> ()V
    AASTORE
   L5
    LINENUMBER 11 L5
    IINC 5 1
    GOTO L2
   L3
    LINENUMBER 14 L3
   FRAME FULL [original/Solution2093 I [[I I [Ljava/util/List; I] []
    ALOAD 2
    ASTORE 5
    ALOAD 5
    ARRAYLENGTH
    ISTORE 6
    ICONST_0
    ISTORE 7
   L6
   FRAME FULL [original/Solution2093 I [[I I [Ljava/util/List; [[I I I] []
    ILOAD 7
    ILOAD 6
    IF_ICMPGE L7
    ALOAD 5
    ILOAD 7
    AALOAD
    ASTORE 8
   L8
    LINENUMBER 15 L8
    ALOAD 8
    ICONST_0
    IALOAD
    ISTORE 9
   L9
    ALOAD 8
    ICONST_1
    IALOAD
    ISTORE 10
   L10
    ALOAD 8
    ICONST_2
    IALOAD
    ISTORE 11
   L11
    LINENUMBER 16 L11
    ALOAD 4
    ILOAD 9
    AALOAD
    ICONST_2
    NEWARRAY T_INT
    DUP
    ICONST_0
    ILOAD 10
    IASTORE
    DUP
    ICONST_1
    ILOAD 11
    IASTORE
    INVOKEINTERFACE java/util/List.add (Ljava/lang/Object;)Z (itf)
    POP
   L12
    LINENUMBER 17 L12
    ALOAD 4
    ILOAD 10
    AALOAD
    ICONST_2
    NEWARRAY T_INT
    DUP
    ICONST_0
    ILOAD 9
    IASTORE
    DUP
    ICONST_1
    ILOAD 11
    IASTORE
    INVOKEINTERFACE java/util/List.add (Ljava/lang/Object;)Z (itf)
    POP
   L13
    LINENUMBER 14 L13
    IINC 7 1
    GOTO L6
   L7
    LINENUMBER 19 L7
   FRAME FULL [original/Solution2093 I [[I I [Ljava/util/List; [[I I I] []
    NEW java/util/PriorityQueue
    DUP
    INVOKEDYNAMIC compare()Ljava/util/Comparator; [
      // handle kind 0x6 : INVOKESTATIC
      java/lang/invoke/LambdaMetafactory.metafactory(Ljava/lang/invoke/MethodHandles$Lookup;Ljava/lang/String;Ljava/lang/invoke/MethodType;Ljava/lang/invoke/MethodType;Ljava/lang/invoke/MethodHandle;Ljava/lang/invoke/MethodType;)Ljava/lang/invoke/CallSite;
      // arguments:
      (Ljava/lang/Object;Ljava/lang/Object;)I, 
      // handle kind 0x6 : INVOKESTATIC
      original/Solution2093.lambda$minimumCost$0([I[I)I, 
      ([I[I)I
    ]
    INVOKESPECIAL java/util/PriorityQueue.<init> (Ljava/util/Comparator;)V
    ASTORE 5
   L14
    LINENUMBER 20 L14
    ALOAD 5
    ICONST_3
    NEWARRAY T_INT
    DUP
    ICONST_0
    ICONST_0
    IASTORE
    DUP
    ICONST_1
    ICONST_0
    IASTORE
    DUP
    ICONST_2
    ICONST_0
    IASTORE
    INVOKEVIRTUAL java/util/PriorityQueue.offer (Ljava/lang/Object;)Z
    POP
   L15
    LINENUMBER 21 L15
    ILOAD 1
    ILOAD 3
    ICONST_1
    IADD
    MULTIANEWARRAY [[I 2
    ASTORE 6
   L16
    LINENUMBER 22 L16
    ALOAD 6
    ASTORE 7
    ALOAD 7
    ARRAYLENGTH
    ISTORE 8
    ICONST_0
    ISTORE 9
   L17
   FRAME FULL [original/Solution2093 I [[I I [Ljava/util/List; java/util/PriorityQueue [[I [[I I I] []
    ILOAD 9
    ILOAD 8
    IF_ICMPGE L18
    ALOAD 7
    ILOAD 9
    AALOAD
    ASTORE 10
   L19
    LINENUMBER 23 L19
    ALOAD 10
    LDC 2147483647
    INVOKESTATIC java/util/Arrays.fill ([II)V
   L20
    LINENUMBER 22 L20
    IINC 9 1
    GOTO L17
   L18
    LINENUMBER 25 L18
   FRAME FULL [original/Solution2093 I [[I I [Ljava/util/List; java/util/PriorityQueue [[I java/lang/Object I I] []
    ALOAD 5
    INVOKEVIRTUAL java/util/PriorityQueue.isEmpty ()Z
    IFNE L21
   L22
    LINENUMBER 26 L22
    ALOAD 5
    INVOKEVIRTUAL java/util/PriorityQueue.poll ()Ljava/lang/Object;
    CHECKCAST [I
    ASTORE 7
   L23
    LINENUMBER 27 L23
    ALOAD 7
    ICONST_0
    IALOAD
    ISTORE 8
   L24
    ALOAD 7
    ICONST_1
    IALOAD
    ISTORE 9
   L25
    ALOAD 7
    ICONST_2
    IALOAD
    ISTORE 10
   L26
    LINENUMBER 28 L26
    ILOAD 10
    ILOAD 3
    IF_ICMPGT L18
    ALOAD 6
    ILOAD 9
    AALOAD
    ILOAD 10
    IALOAD
    ILOAD 8
    IF_ICMPGT L27
   L28
    LINENUMBER 29 L28
    GOTO L18
   L27
    LINENUMBER 31 L27
   FRAME FULL [original/Solution2093 I [[I I [Ljava/util/List; java/util/PriorityQueue [[I [I I I I] []
    ILOAD 9
    ILOAD 1
    ICONST_1
    ISUB
    IF_ICMPNE L29
   L30
    LINENUMBER 32 L30
    ILOAD 8
    IRETURN
   L29
    LINENUMBER 34 L29
   FRAME FULL [original/Solution2093 I [[I I [Ljava/util/List; java/util/PriorityQueue [[I [I I I I] []
    ALOAD 6
    ILOAD 9
    AALOAD
    ILOAD 10
    ILOAD 8
    IASTORE
   L31
    LINENUMBER 35 L31
    ALOAD 4
    ILOAD 9
    AALOAD
    INVOKEINTERFACE java/util/List.iterator ()Ljava/util/Iterator; (itf)
    ASTORE 11
   L32
   FRAME FULL [original/Solution2093 I [[I I [Ljava/util/List; java/util/PriorityQueue [[I [I I I I java/util/Iterator] []
    ALOAD 11
    INVOKEINTERFACE java/util/Iterator.hasNext ()Z (itf)
    IFEQ L33
    ALOAD 11
    INVOKEINTERFACE java/util/Iterator.next ()Ljava/lang/Object; (itf)
    CHECKCAST [I
    ASTORE 12
   L34
    LINENUMBER 36 L34
    ALOAD 12
    ICONST_0
    IALOAD
    ISTORE 13
   L35
    ALOAD 12
    ICONST_1
    IALOAD
    ISTORE 14
   L36
    LINENUMBER 37 L36
    ALOAD 5
    ICONST_3
    NEWARRAY T_INT
    DUP
    ICONST_0
    ILOAD 8
    ILOAD 14
    IADD
    IASTORE
    DUP
    ICONST_1
    ILOAD 13
    IASTORE
    DUP
    ICONST_2
    ILOAD 10
    IASTORE
    INVOKEVIRTUAL java/util/PriorityQueue.offer (Ljava/lang/Object;)Z
    POP
   L37
    LINENUMBER 38 L37
    ALOAD 5
    ICONST_3
    NEWARRAY T_INT
    DUP
    ICONST_0
    ILOAD 8
    ILOAD 14
    ICONST_2
    IDIV
    ISUB
    IASTORE
    DUP
    ICONST_1
    ILOAD 13
    IASTORE
    DUP
    ICONST_2
    ILOAD 10
    ICONST_1
    IADD
    IASTORE
    INVOKEVIRTUAL java/util/PriorityQueue.offer (Ljava/lang/Object;)Z
    POP
   L38
    LINENUMBER 39 L38
    GOTO L32
   L33
    LINENUMBER 40 L33
   FRAME FULL [original/Solution2093 I [[I I [Ljava/util/List; java/util/PriorityQueue [[I [I I I I java/util/Iterator] []
    GOTO L18
   L21
    LINENUMBER 41 L21
   FRAME FULL [original/Solution2093 I [[I I [Ljava/util/List; java/util/PriorityQueue [[I java/lang/Object I I] []
    ICONST_M1
    IRETURN
   L39
    LOCALVARIABLE i I L2 L3 5
    LOCALVARIABLE a I L9 L13 9
    LOCALVARIABLE b I L10 L13 10
    LOCALVARIABLE c I L11 L13 11
    LOCALVARIABLE e [I L8 L13 8
    LOCALVARIABLE e [I L19 L20 10
    LOCALVARIABLE j I L35 L38 13
    LOCALVARIABLE v I L36 L38 14
    LOCALVARIABLE nxt [I L34 L38 12
    LOCALVARIABLE p [I L23 L33 7
    LOCALVARIABLE cost I L24 L33 8
    LOCALVARIABLE i I L25 L33 9
    LOCALVARIABLE k I L26 L33 10
    LOCALVARIABLE this Loriginal/Solution2093; L0 L39 0
    LOCALVARIABLE n I L0 L39 1
    LOCALVARIABLE highways [[I L0 L39 2
    LOCALVARIABLE discounts I L0 L39 3
    LOCALVARIABLE g [Ljava/util/List; L1 L39 4
    // signature [Ljava/util/List<[I>;
    // declaration: g extends java.util.List<int[]>
    LOCALVARIABLE q Ljava/util/PriorityQueue; L14 L39 5
    // signature Ljava/util/PriorityQueue<[I>;
    // declaration: q extends java.util.PriorityQueue<int[]>
    LOCALVARIABLE dist [[I L16 L39 6
    MAXSTACK = 7
    MAXLOCALS = 15

  // access flags 0x100A
  private static synthetic lambda$minimumCost$0([I[I)I
   L0
    LINENUMBER 19 L0
    ALOAD 0
    ICONST_0
    IALOAD
    ALOAD 1
    ICONST_0
    IALOAD
    ISUB
    IRETURN
   L1
    LOCALVARIABLE a [I L0 L1 0
    LOCALVARIABLE b [I L0 L1 1
    MAXSTACK = 3
    MAXLOCALS = 2
}

