// class version 55.0 (55)
// access flags 0x20
class original/Solution2409 {

  // compiled from: id_2409.java

  // access flags 0x2
  private [I days

  // access flags 0x0
  <init>()V
   L0
    LINENUMBER 3 L0
    ALOAD 0
    INVOKESPECIAL java/lang/Object.<init> ()V
   L1
    LINENUMBER 4 L1
    ALOAD 0
    BIPUSH 12
    NEWARRAY T_INT
    DUP
    ICONST_0
    BIPUSH 31
    IASTORE
    DUP
    ICONST_1
    BIPUSH 28
    IASTORE
    DUP
    ICONST_2
    BIPUSH 31
    IASTORE
    DUP
    ICONST_3
    BIPUSH 30
    IASTORE
    DUP
    ICONST_4
    BIPUSH 31
    IASTORE
    DUP
    ICONST_5
    BIPUSH 30
    IASTORE
    DUP
    BIPUSH 6
    BIPUSH 31
    IASTORE
    DUP
    BIPUSH 7
    BIPUSH 31
    IASTORE
    DUP
    BIPUSH 8
    BIPUSH 30
    IASTORE
    DUP
    BIPUSH 9
    BIPUSH 31
    IASTORE
    DUP
    BIPUSH 10
    BIPUSH 30
    IASTORE
    DUP
    BIPUSH 11
    BIPUSH 31
    IASTORE
    PUTFIELD original/Solution2409.days : [I
    RETURN
   L2
    LOCALVARIABLE this Loriginal/Solution2409; L0 L2 0
    MAXSTACK = 5
    MAXLOCALS = 1

  // access flags 0x1
  public countDaysTogether(Ljava/lang/String;Ljava/lang/String;Ljava/lang/String;Ljava/lang/String;)I
   L0
    LINENUMBER 8 L0
    ALOAD 1
    ALOAD 3
    INVOKEVIRTUAL java/lang/String.compareTo (Ljava/lang/String;)I
    IFGE L1
    ALOAD 3
    GOTO L2
   L1
   FRAME FULL [original/Solution2409 java/lang/String java/lang/String java/lang/String java/lang/String] []
    ALOAD 1
   L2
   FRAME FULL [original/Solution2409 java/lang/String java/lang/String java/lang/String java/lang/String] [java/lang/String]
    ASTORE 5
   L3
    LINENUMBER 9 L3
    ALOAD 2
    ALOAD 4
    INVOKEVIRTUAL java/lang/String.compareTo (Ljava/lang/String;)I
    IFGE L4
    ALOAD 2
    GOTO L5
   L4
   FRAME FULL [original/Solution2409 java/lang/String java/lang/String java/lang/String java/lang/String java/lang/String] []
    ALOAD 4
   L5
   FRAME FULL [original/Solution2409 java/lang/String java/lang/String java/lang/String java/lang/String java/lang/String] [java/lang/String]
    ASTORE 6
   L6
    LINENUMBER 10 L6
    ALOAD 0
    ALOAD 5
    INVOKEVIRTUAL original/Solution2409.f (Ljava/lang/String;)I
    ISTORE 7
   L7
    ALOAD 0
    ALOAD 6
    INVOKEVIRTUAL original/Solution2409.f (Ljava/lang/String;)I
    ISTORE 8
   L8
    LINENUMBER 11 L8
    ILOAD 8
    ILOAD 7
    ISUB
    ICONST_1
    IADD
    ICONST_0
    INVOKESTATIC java/lang/Math.max (II)I
    IRETURN
   L9
    LOCALVARIABLE this Loriginal/Solution2409; L0 L9 0
    LOCALVARIABLE arriveAlice Ljava/lang/String; L0 L9 1
    LOCALVARIABLE leaveAlice Ljava/lang/String; L0 L9 2
    LOCALVARIABLE arriveBob Ljava/lang/String; L0 L9 3
    LOCALVARIABLE leaveBob Ljava/lang/String; L0 L9 4
    LOCALVARIABLE a Ljava/lang/String; L3 L9 5
    LOCALVARIABLE b Ljava/lang/String; L6 L9 6
    LOCALVARIABLE x I L7 L9 7
    LOCALVARIABLE y I L8 L9 8
    MAXSTACK = 2
    MAXLOCALS = 9

  // access flags 0x2
  private f(Ljava/lang/String;)I
   L0
    LINENUMBER 15 L0
    ALOAD 1
    ICONST_0
    ICONST_2
    INVOKEVIRTUAL java/lang/String.substring (II)Ljava/lang/String;
    INVOKESTATIC java/lang/Integer.parseInt (Ljava/lang/String;)I
    ICONST_1
    ISUB
    ISTORE 2
   L1
    LINENUMBER 16 L1
    ICONST_0
    ISTORE 3
   L2
    LINENUMBER 17 L2
    ICONST_0
    ISTORE 4
   L3
   FRAME FULL [original/Solution2409 java/lang/String I I I] []
    ILOAD 4
    ILOAD 2
    IF_ICMPGT L4
   L5
    LINENUMBER 18 L5
    ILOAD 3
    ALOAD 0
    GETFIELD original/Solution2409.days : [I
    ILOAD 4
    IALOAD
    IADD
    ISTORE 3
   L6
    LINENUMBER 17 L6
    IINC 4 1
    GOTO L3
   L4
    LINENUMBER 20 L4
   FRAME FULL [original/Solution2409 java/lang/String I I I] []
    ILOAD 3
    ALOAD 1
    ICONST_3
    INVOKEVIRTUAL java/lang/String.substring (I)Ljava/lang/String;
    INVOKESTATIC java/lang/Integer.parseInt (Ljava/lang/String;)I
    IADD
    ISTORE 3
   L7
    LINENUMBER 21 L7
    ILOAD 3
    IRETURN
   L8
    LOCALVARIABLE j I L3 L4 4
    LOCALVARIABLE this Loriginal/Solution2409; L0 L8 0
    LOCALVARIABLE s Ljava/lang/String; L0 L8 1
    LOCALVARIABLE i I L1 L8 2
    LOCALVARIABLE res I L2 L8 3
    MAXSTACK = 3
    MAXLOCALS = 5
}

