// class version 55.0 (55)
// access flags 0x20
class original/Solution0555 {

  // compiled from: id_0555.java
  // access flags 0x19
  public final static INNERCLASS java/lang/invoke/MethodHandles$Lookup java/lang/invoke/MethodHandles Lookup

  // access flags 0x0
  <init>()V
   L0
    LINENUMBER 3 L0
    ALOAD 0
    INVOKESPECIAL java/lang/Object.<init> ()V
    RETURN
   L1
    LOCALVARIABLE this Loriginal/Solution0555; L0 L1 0
    MAXSTACK = 1
    MAXLOCALS = 1

  // access flags 0x1
  public splitLoopedString([Ljava/lang/String;)Ljava/lang/String;
   L0
    LINENUMBER 5 L0
    ALOAD 1
    ARRAYLENGTH
    ISTORE 2
   L1
    LINENUMBER 6 L1
    ICONST_0
    ISTORE 3
   L2
   FRAME FULL [original/Solution0555 [Ljava/lang/String; I I] []
    ILOAD 3
    ILOAD 2
    IF_ICMPGE L3
   L4
    LINENUMBER 7 L4
    ALOAD 1
    ILOAD 3
    AALOAD
    ASTORE 4
   L5
    LINENUMBER 8 L5
    NEW java/lang/StringBuilder
    DUP
    ALOAD 4
    INVOKESPECIAL java/lang/StringBuilder.<init> (Ljava/lang/String;)V
    INVOKEVIRTUAL java/lang/StringBuilder.reverse ()Ljava/lang/StringBuilder;
    INVOKEVIRTUAL java/lang/StringBuilder.toString ()Ljava/lang/String;
    ASTORE 5
   L6
    LINENUMBER 9 L6
    ALOAD 4
    ALOAD 5
    INVOKEVIRTUAL java/lang/String.compareTo (Ljava/lang/String;)I
    IFGE L7
   L8
    LINENUMBER 10 L8
    ALOAD 1
    ILOAD 3
    ALOAD 5
    AASTORE
   L7
    LINENUMBER 6 L7
   FRAME FULL [original/Solution0555 [Ljava/lang/String; I I java/lang/String java/lang/String] []
    IINC 3 1
    GOTO L2
   L3
    LINENUMBER 13 L3
   FRAME FULL [original/Solution0555 [Ljava/lang/String; I I] []
    LDC ""
    ASTORE 3
   L9
    LINENUMBER 14 L9
    ICONST_0
    ISTORE 4
   L10
   FRAME FULL [original/Solution0555 [Ljava/lang/String; I java/lang/String I] []
    ILOAD 4
    ILOAD 2
    IF_ICMPGE L11
   L12
    LINENUMBER 15 L12
    ALOAD 1
    ILOAD 4
    AALOAD
    ASTORE 5
   L13
    LINENUMBER 16 L13
    NEW java/lang/StringBuilder
    DUP
    INVOKESPECIAL java/lang/StringBuilder.<init> ()V
    ASTORE 6
   L14
    LINENUMBER 17 L14
    ILOAD 4
    ICONST_1
    IADD
    ISTORE 7
   L15
   FRAME FULL [original/Solution0555 [Ljava/lang/String; I java/lang/String I java/lang/String java/lang/StringBuilder I] []
    ILOAD 7
    ILOAD 2
    IF_ICMPGE L16
   L17
    LINENUMBER 18 L17
    ALOAD 6
    ALOAD 1
    ILOAD 7
    AALOAD
    INVOKEVIRTUAL java/lang/StringBuilder.append (Ljava/lang/String;)Ljava/lang/StringBuilder;
    POP
   L18
    LINENUMBER 17 L18
    IINC 7 1
    GOTO L15
   L16
    LINENUMBER 20 L16
   FRAME FULL [original/Solution0555 [Ljava/lang/String; I java/lang/String I java/lang/String java/lang/StringBuilder I] []
    ICONST_0
    ISTORE 7
   L19
   FRAME FULL [original/Solution0555 [Ljava/lang/String; I java/lang/String I java/lang/String java/lang/StringBuilder I] []
    ILOAD 7
    ILOAD 4
    IF_ICMPGE L20
   L21
    LINENUMBER 21 L21
    ALOAD 6
    ALOAD 1
    ILOAD 7
    AALOAD
    INVOKEVIRTUAL java/lang/StringBuilder.append (Ljava/lang/String;)Ljava/lang/StringBuilder;
    POP
   L22
    LINENUMBER 20 L22
    IINC 7 1
    GOTO L19
   L20
    LINENUMBER 23 L20
   FRAME FULL [original/Solution0555 [Ljava/lang/String; I java/lang/String I java/lang/String java/lang/StringBuilder I] []
    ALOAD 6
    INVOKEVIRTUAL java/lang/StringBuilder.toString ()Ljava/lang/String;
    ASTORE 7
   L23
    LINENUMBER 24 L23
    ICONST_0
    ISTORE 8
   L24
   FRAME FULL [original/Solution0555 [Ljava/lang/String; I java/lang/String I java/lang/String java/lang/StringBuilder java/lang/String I] []
    ILOAD 8
    ALOAD 5
    INVOKEVIRTUAL java/lang/String.length ()I
    IF_ICMPLT L25
   L26
    LINENUMBER 25 L26
    ALOAD 5
    ILOAD 8
    INVOKEVIRTUAL java/lang/String.substring (I)Ljava/lang/String;
    ASTORE 9
   L27
    LINENUMBER 26 L27
    ALOAD 5
    ICONST_0
    ILOAD 8
    INVOKEVIRTUAL java/lang/String.substring (II)Ljava/lang/String;
    ASTORE 10
   L28
    LINENUMBER 27 L28
    ALOAD 9
    ALOAD 7
    ALOAD 10
    INVOKEDYNAMIC makeConcatWithConstants(Ljava/lang/String;Ljava/lang/String;Ljava/lang/String;)Ljava/lang/String; [
      // handle kind 0x6 : INVOKESTATIC
      java/lang/invoke/StringConcatFactory.makeConcatWithConstants(Ljava/lang/invoke/MethodHandles$Lookup;Ljava/lang/String;Ljava/lang/invoke/MethodType;Ljava/lang/String;[Ljava/lang/Object;)Ljava/lang/invoke/CallSite;
      // arguments:
      "\u0001\u0001\u0001"
    ]
    ASTORE 11
   L29
    LINENUMBER 28 L29
    ALOAD 3
    ALOAD 11
    INVOKEVIRTUAL java/lang/String.compareTo (Ljava/lang/String;)I
    IFGE L30
   L31
    LINENUMBER 29 L31
    ALOAD 11
    ASTORE 3
   L30
    LINENUMBER 31 L30
   FRAME FULL [original/Solution0555 [Ljava/lang/String; I java/lang/String I java/lang/String java/lang/StringBuilder java/lang/String I java/lang/String java/lang/String java/lang/String] []
    NEW java/lang/StringBuilder
    DUP
    ALOAD 10
    INVOKESPECIAL java/lang/StringBuilder.<init> (Ljava/lang/String;)V
   L32
    LINENUMBER 32 L32
    INVOKEVIRTUAL java/lang/StringBuilder.reverse ()Ljava/lang/StringBuilder;
    ALOAD 7
   L33
    LINENUMBER 33 L33
    INVOKEVIRTUAL java/lang/StringBuilder.append (Ljava/lang/String;)Ljava/lang/StringBuilder;
    NEW java/lang/StringBuilder
    DUP
    ALOAD 9
    INVOKESPECIAL java/lang/StringBuilder.<init> (Ljava/lang/String;)V
   L34
    LINENUMBER 34 L34
    INVOKEVIRTUAL java/lang/StringBuilder.reverse ()Ljava/lang/StringBuilder;
    INVOKEVIRTUAL java/lang/StringBuilder.toString ()Ljava/lang/String;
    INVOKEVIRTUAL java/lang/StringBuilder.append (Ljava/lang/String;)Ljava/lang/StringBuilder;
   L35
    LINENUMBER 35 L35
    INVOKEVIRTUAL java/lang/StringBuilder.toString ()Ljava/lang/String;
    ASTORE 11
   L36
    LINENUMBER 36 L36
    ALOAD 3
    ALOAD 11
    INVOKEVIRTUAL java/lang/String.compareTo (Ljava/lang/String;)I
    IFGE L37
   L38
    LINENUMBER 37 L38
    ALOAD 11
    ASTORE 3
   L37
    LINENUMBER 24 L37
   FRAME FULL [original/Solution0555 [Ljava/lang/String; I java/lang/String I java/lang/String java/lang/StringBuilder java/lang/String I java/lang/String java/lang/String java/lang/String] []
    IINC 8 1
    GOTO L24
   L25
    LINENUMBER 14 L25
   FRAME FULL [original/Solution0555 [Ljava/lang/String; I java/lang/String I java/lang/String java/lang/StringBuilder java/lang/String I] []
    IINC 4 1
    GOTO L10
   L11
    LINENUMBER 41 L11
   FRAME FULL [original/Solution0555 [Ljava/lang/String; I java/lang/String I] []
    ALOAD 3
    ARETURN
   L39
    LOCALVARIABLE s Ljava/lang/String; L5 L7 4
    LOCALVARIABLE t Ljava/lang/String; L6 L7 5
    LOCALVARIABLE i I L2 L3 3
    LOCALVARIABLE j I L15 L16 7
    LOCALVARIABLE j I L19 L20 7
    LOCALVARIABLE a Ljava/lang/String; L27 L37 9
    LOCALVARIABLE b Ljava/lang/String; L28 L37 10
    LOCALVARIABLE cur Ljava/lang/String; L29 L37 11
    LOCALVARIABLE j I L24 L25 8
    LOCALVARIABLE s Ljava/lang/String; L13 L25 5
    LOCALVARIABLE sb Ljava/lang/StringBuilder; L14 L25 6
    LOCALVARIABLE t Ljava/lang/String; L23 L25 7
    LOCALVARIABLE i I L10 L11 4
    LOCALVARIABLE this Loriginal/Solution0555; L0 L39 0
    LOCALVARIABLE strs [Ljava/lang/String; L0 L39 1
    LOCALVARIABLE n I L1 L39 2
    LOCALVARIABLE ans Ljava/lang/String; L9 L39 3
    MAXSTACK = 4
    MAXLOCALS = 12
}

