// class version 55.0 (55)
// access flags 0x20
class original/IsPalindrome {

  // compiled from: id_48.java

  // access flags 0x0
  <init>()V
   L0
    LINENUMBER 3 L0
    ALOAD 0
    INVOKESPECIAL java/lang/Object.<init> ()V
    RETURN
   L1
    LOCALVARIABLE this Loriginal/IsPalindrome; L0 L1 0
    MAXSTACK = 1
    MAXLOCALS = 1

  // access flags 0x9
  public static isPalindrome(Ljava/lang/String;)Ljava/lang/Boolean;
   L0
    LINENUMBER 23 L0
    ICONST_0
    ISTORE 1
   L1
    LINENUMBER 24 L1
    ALOAD 0
    INVOKEVIRTUAL java/lang/String.length ()I
    ICONST_1
    ISUB
    ISTORE 2
   L2
    LINENUMBER 25 L2
   FRAME FULL [java/lang/String I I] []
    ILOAD 1
    ILOAD 2
    IF_ICMPLT L3
   L4
    LINENUMBER 26 L4
    ALOAD 0
    ILOAD 1
    INVOKEVIRTUAL java/lang/String.charAt (I)C
    ALOAD 0
    ILOAD 2
    INVOKEVIRTUAL java/lang/String.charAt (I)C
    IF_ICMPEQ L5
   L6
    LINENUMBER 27 L6
    ICONST_0
    INVOKESTATIC java/lang/Boolean.valueOf (Z)Ljava/lang/Boolean;
    ARETURN
   L5
    LINENUMBER 29 L5
   FRAME FULL [java/lang/String I I] []
    IINC 1 1
   L7
    LINENUMBER 30 L7
    IINC 2 -1
    GOTO L2
   L3
    LINENUMBER 32 L3
   FRAME FULL [java/lang/String I I] []
    ICONST_1
    INVOKESTATIC java/lang/Boolean.valueOf (Z)Ljava/lang/Boolean;
    ARETURN
   L8
    LOCALVARIABLE text Ljava/lang/String; L0 L8 0
    LOCALVARIABLE i I L1 L8 1
    LOCALVARIABLE j I L2 L8 2
    MAXSTACK = 3
    MAXLOCALS = 3
}

