// class version 55.0 (55)
// access flags 0x20
class original/StartsOneEnds {

  // compiled from: id_83.java

  // access flags 0x0
  <init>()V
   L0
    LINENUMBER 3 L0
    ALOAD 0
    INVOKESPECIAL java/lang/Object.<init> ()V
    RETURN
   L1
    LOCALVARIABLE this Loriginal/StartsOneEnds; L0 L1 0
    MAXSTACK = 1
    MAXLOCALS = 1

  // access flags 0x9
  public static startsOneEnds(I)I
   L0
    LINENUMBER 21 L0
    ICONST_0
    ISTORE 1
   L1
    LINENUMBER 22 L1
    ICONST_1
    ISTORE 2
   L2
    LINENUMBER 23 L2
    ICONST_1
    ISTORE 3
   L3
    LINENUMBER 24 L3
    ICONST_1
    ISTORE 4
   L4
   FRAME FULL [I I I I I] []
    ILOAD 4
    ILOAD 0
    IF_ICMPGE L5
   L6
    LINENUMBER 25 L6
    ILOAD 2
    BIPUSH 10
    IMUL
    ISTORE 2
   L7
    LINENUMBER 26 L7
    ILOAD 3
    BIPUSH 10
    IMUL
    ISTORE 3
   L8
    LINENUMBER 24 L8
    IINC 4 1
    GOTO L4
   L5
    LINENUMBER 28 L5
   FRAME FULL [I I I I I] []
    ILOAD 2
    ISTORE 4
   L9
   FRAME FULL [I I I I I] []
    ILOAD 4
    ILOAD 3
    BIPUSH 10
    IDIV
    IF_ICMPGE L10
   L11
    LINENUMBER 29 L11
    ILOAD 4
    BIPUSH 10
    IREM
    ICONST_1
    IF_ICMPEQ L12
    ILOAD 4
    ILOAD 2
    IDIV
    ICONST_1
    IF_ICMPNE L13
   L12
    LINENUMBER 30 L12
   FRAME FULL [I I I I I] []
    IINC 1 1
   L13
    LINENUMBER 28 L13
   FRAME FULL [I I I I I] []
    IINC 4 1
    GOTO L9
   L10
    LINENUMBER 33 L10
   FRAME FULL [I I I I I] []
    ILOAD 1
    IRETURN
   L14
    LOCALVARIABLE i I L4 L5 4
    LOCALVARIABLE i I L9 L10 4
    LOCALVARIABLE n I L0 L14 0
    LOCALVARIABLE count I L1 L14 1
    LOCALVARIABLE start I L2 L14 2
    LOCALVARIABLE end I L3 L14 3
    MAXSTACK = 3
    MAXLOCALS = 5
}

