// class version 55.0 (55)
// access flags 0x20
class original/Solution1998 {

  // compiled from: id_1998.java
  // access flags 0x19
  public final static INNERCLASS java/lang/invoke/MethodHandles$Lookup java/lang/invoke/MethodHandles Lookup

  // access flags 0x2
  private [I p

  // access flags 0x0
  <init>()V
   L0
    LINENUMBER 8 L0
    ALOAD 0
    INVOKESPECIAL java/lang/Object.<init> ()V
    RETURN
   L1
    LOCALVARIABLE this Loriginal/Solution1998; L0 L1 0
    MAXSTACK = 1
    MAXLOCALS = 1

  // access flags 0x1
  public gcdSort([I)Z
   L0
    LINENUMBER 12 L0
    LDC 100010
    ISTORE 2
   L1
    LINENUMBER 13 L1
    ALOAD 0
    ILOAD 2
    NEWARRAY T_INT
    PUTFIELD original/Solution1998.p : [I
   L2
    LINENUMBER 14 L2
    NEW java/util/HashMap
    DUP
    INVOKESPECIAL java/util/HashMap.<init> ()V
    ASTORE 3
   L3
    LINENUMBER 15 L3
    ICONST_0
    ISTORE 4
   L4
   FRAME FULL [original/Solution1998 [I I java/util/HashMap I] []
    ILOAD 4
    ILOAD 2
    IF_ICMPGE L5
   L6
    LINENUMBER 16 L6
    ALOAD 0
    GETFIELD original/Solution1998.p : [I
    ILOAD 4
    ILOAD 4
    IASTORE
   L7
    LINENUMBER 15 L7
    IINC 4 1
    GOTO L4
   L5
    LINENUMBER 18 L5
   FRAME FULL [original/Solution1998 [I I java/util/HashMap I] []
    ICONST_0
    ISTORE 4
   L8
    LINENUMBER 19 L8
    ALOAD 1
    ASTORE 5
    ALOAD 5
    ARRAYLENGTH
    ISTORE 6
    ICONST_0
    ISTORE 7
   L9
   FRAME FULL [original/Solution1998 [I I java/util/HashMap I [I I I] []
    ILOAD 7
    ILOAD 6
    IF_ICMPGE L10
    ALOAD 5
    ILOAD 7
    IALOAD
    ISTORE 8
   L11
    LINENUMBER 20 L11
    ILOAD 4
    ILOAD 8
    INVOKESTATIC java/lang/Math.max (II)I
    ISTORE 4
   L12
    LINENUMBER 19 L12
    IINC 7 1
    GOTO L9
   L10
    LINENUMBER 22 L10
   FRAME FULL [original/Solution1998 [I I java/util/HashMap I [I I I] []
    ICONST_2
    ISTORE 5
   L13
   FRAME FULL [original/Solution1998 [I I java/util/HashMap I I I I] []
    ILOAD 5
    ILOAD 4
    IF_ICMPGT L14
   L15
    LINENUMBER 23 L15
    ALOAD 3
    ILOAD 5
    INVOKESTATIC java/lang/Integer.valueOf (I)Ljava/lang/Integer;
    INVOKEINTERFACE java/util/Map.containsKey (Ljava/lang/Object;)Z (itf)
    IFEQ L16
   L17
    LINENUMBER 24 L17
    GOTO L18
   L16
    LINENUMBER 26 L16
   FRAME FULL [original/Solution1998 [I I java/util/HashMap I I I I] []
    ILOAD 5
    ISTORE 6
   L19
   FRAME FULL [original/Solution1998 [I I java/util/HashMap I I I I] []
    ILOAD 6
    ILOAD 4
    IF_ICMPGT L18
   L20
    LINENUMBER 27 L20
    ALOAD 3
    ILOAD 6
    INVOKESTATIC java/lang/Integer.valueOf (I)Ljava/lang/Integer;
    INVOKEDYNAMIC apply()Ljava/util/function/Function; [
      // handle kind 0x6 : INVOKESTATIC
      java/lang/invoke/LambdaMetafactory.metafactory(Ljava/lang/invoke/MethodHandles$Lookup;Ljava/lang/String;Ljava/lang/invoke/MethodType;Ljava/lang/invoke/MethodType;Ljava/lang/invoke/MethodHandle;Ljava/lang/invoke/MethodType;)Ljava/lang/invoke/CallSite;
      // arguments:
      (Ljava/lang/Object;)Ljava/lang/Object;, 
      // handle kind 0x6 : INVOKESTATIC
      original/Solution1998.lambda$gcdSort$0(Ljava/lang/Integer;)Ljava/util/List;, 
      (Ljava/lang/Integer;)Ljava/util/List;
    ]
    INVOKEINTERFACE java/util/Map.computeIfAbsent (Ljava/lang/Object;Ljava/util/function/Function;)Ljava/lang/Object; (itf)
    CHECKCAST java/util/List
    ILOAD 5
    INVOKESTATIC java/lang/Integer.valueOf (I)Ljava/lang/Integer;
    INVOKEINTERFACE java/util/List.add (Ljava/lang/Object;)Z (itf)
    POP
   L21
    LINENUMBER 26 L21
    ILOAD 6
    ILOAD 5
    IADD
    ISTORE 6
    GOTO L19
   L18
    LINENUMBER 22 L18
   FRAME FULL [original/Solution1998 [I I java/util/HashMap I I I I] []
    IINC 5 1
    GOTO L13
   L14
    LINENUMBER 30 L14
   FRAME FULL [original/Solution1998 [I I java/util/HashMap I I I I] []
    ALOAD 1
    ASTORE 5
    ALOAD 5
    ARRAYLENGTH
    ISTORE 6
    ICONST_0
    ISTORE 7
   L22
   FRAME FULL [original/Solution1998 [I I java/util/HashMap I [I I I] []
    ILOAD 7
    ILOAD 6
    IF_ICMPGE L23
    ALOAD 5
    ILOAD 7
    IALOAD
    ISTORE 8
   L24
    LINENUMBER 31 L24
    ALOAD 3
    ILOAD 8
    INVOKESTATIC java/lang/Integer.valueOf (I)Ljava/lang/Integer;
    INVOKEINTERFACE java/util/Map.get (Ljava/lang/Object;)Ljava/lang/Object; (itf)
    CHECKCAST java/util/List
    INVOKEINTERFACE java/util/List.iterator ()Ljava/util/Iterator; (itf)
    ASTORE 9
   L25
   FRAME FULL [original/Solution1998 [I I java/util/HashMap I [I I I I java/util/Iterator] []
    ALOAD 9
    INVOKEINTERFACE java/util/Iterator.hasNext ()Z (itf)
    IFEQ L26
    ALOAD 9
    INVOKEINTERFACE java/util/Iterator.next ()Ljava/lang/Object; (itf)
    CHECKCAST java/lang/Integer
    INVOKEVIRTUAL java/lang/Integer.intValue ()I
    ISTORE 10
   L27
    LINENUMBER 32 L27
    ALOAD 0
    GETFIELD original/Solution1998.p : [I
    ALOAD 0
    ILOAD 8
    INVOKEVIRTUAL original/Solution1998.find (I)I
    ALOAD 0
    ILOAD 10
    INVOKEVIRTUAL original/Solution1998.find (I)I
    IASTORE
   L28
    LINENUMBER 33 L28
    GOTO L25
   L26
    LINENUMBER 30 L26
   FRAME FULL [original/Solution1998 [I I java/util/HashMap I [I I I I java/util/Iterator] []
    IINC 7 1
    GOTO L22
   L23
    LINENUMBER 35 L23
   FRAME FULL [original/Solution1998 [I I java/util/HashMap I [I I I] []
    ALOAD 1
    ARRAYLENGTH
    NEWARRAY T_INT
    ASTORE 5
   L29
    LINENUMBER 36 L29
    ALOAD 1
    ICONST_0
    ALOAD 5
    ICONST_0
    ALOAD 1
    ARRAYLENGTH
    INVOKESTATIC java/lang/System.arraycopy (Ljava/lang/Object;ILjava/lang/Object;II)V
   L30
    LINENUMBER 37 L30
    ALOAD 5
    INVOKESTATIC java/util/Arrays.sort ([I)V
   L31
    LINENUMBER 38 L31
    ICONST_0
    ISTORE 6
   L32
   FRAME FULL [original/Solution1998 [I I java/util/HashMap I [I I I] []
    ILOAD 6
    ALOAD 1
    ARRAYLENGTH
    IF_ICMPGE L33
   L34
    LINENUMBER 39 L34
    ALOAD 5
    ILOAD 6
    IALOAD
    ALOAD 1
    ILOAD 6
    IALOAD
    IF_ICMPEQ L35
    ALOAD 0
    ALOAD 1
    ILOAD 6
    IALOAD
    INVOKEVIRTUAL original/Solution1998.find (I)I
    ALOAD 0
    ALOAD 5
    ILOAD 6
    IALOAD
    INVOKEVIRTUAL original/Solution1998.find (I)I
    IF_ICMPNE L35
   L36
    LINENUMBER 40 L36
    ICONST_0
    IRETURN
   L35
    LINENUMBER 38 L35
   FRAME FULL [original/Solution1998 [I I java/util/HashMap I [I I I] []
    IINC 6 1
    GOTO L32
   L33
    LINENUMBER 43 L33
   FRAME FULL [original/Solution1998 [I I java/util/HashMap I [I I I] []
    ICONST_1
    IRETURN
   L37
    LOCALVARIABLE i I L4 L5 4
    LOCALVARIABLE num I L11 L12 8
    LOCALVARIABLE j I L19 L18 6
    LOCALVARIABLE i I L13 L14 5
    LOCALVARIABLE j I L27 L28 10
    LOCALVARIABLE i I L24 L26 8
    LOCALVARIABLE i I L32 L33 6
    LOCALVARIABLE this Loriginal/Solution1998; L0 L37 0
    LOCALVARIABLE nums [I L0 L37 1
    LOCALVARIABLE n I L1 L37 2
    LOCALVARIABLE f Ljava/util/Map; L3 L37 3
    // signature Ljava/util/Map<Ljava/lang/Integer;Ljava/util/List<Ljava/lang/Integer;>;>;
    // declaration: f extends java.util.Map<java.lang.Integer, java.util.List<java.lang.Integer>>
    LOCALVARIABLE mx I L8 L37 4
    LOCALVARIABLE s [I L29 L37 5
    MAXSTACK = 5
    MAXLOCALS = 11

  // access flags 0x0
  find(I)I
   L0
    LINENUMBER 47 L0
    ALOAD 0
    GETFIELD original/Solution1998.p : [I
    ILOAD 1
    IALOAD
    ILOAD 1
    IF_ICMPEQ L1
   L2
    LINENUMBER 48 L2
    ALOAD 0
    GETFIELD original/Solution1998.p : [I
    ILOAD 1
    ALOAD 0
    ALOAD 0
    GETFIELD original/Solution1998.p : [I
    ILOAD 1
    IALOAD
    INVOKEVIRTUAL original/Solution1998.find (I)I
    IASTORE
   L1
    LINENUMBER 50 L1
   FRAME FULL [original/Solution1998 I] []
    ALOAD 0
    GETFIELD original/Solution1998.p : [I
    ILOAD 1
    IALOAD
    IRETURN
   L3
    LOCALVARIABLE this Loriginal/Solution1998; L0 L3 0
    LOCALVARIABLE x I L0 L3 1
    MAXSTACK = 5
    MAXLOCALS = 2

  // access flags 0x100A
  private static synthetic lambda$gcdSort$0(Ljava/lang/Integer;)Ljava/util/List;
   L0
    LINENUMBER 27 L0
    NEW java/util/ArrayList
    DUP
    INVOKESPECIAL java/util/ArrayList.<init> ()V
    ARETURN
   L1
    LOCALVARIABLE k Ljava/lang/Integer; L0 L1 0
    MAXSTACK = 2
    MAXLOCALS = 1
}

