// class version 55.0 (55)
// access flags 0x20
class original/Solve {

  // compiled from: id_161.java
  // access flags 0x19
  public final static INNERCLASS java/lang/invoke/MethodHandles$Lookup java/lang/invoke/MethodHandles Lookup

  // access flags 0x0
  <init>()V
   L0
    LINENUMBER 3 L0
    ALOAD 0
    INVOKESPECIAL java/lang/Object.<init> ()V
    RETURN
   L1
    LOCALVARIABLE this Loriginal/Solve; L0 L1 0
    MAXSTACK = 1
    MAXLOCALS = 1

  // access flags 0x9
  public static solve(Ljava/lang/String;)Ljava/lang/String;
   L0
    LINENUMBER 33 L0
    LDC ""
    ASTORE 1
   L1
    LINENUMBER 34 L1
    ICONST_0
    ISTORE 2
   L2
    LINENUMBER 35 L2
    ICONST_0
    ISTORE 3
   L3
   FRAME FULL [java/lang/String java/lang/String I I] []
    ILOAD 3
    ALOAD 0
    INVOKEVIRTUAL java/lang/String.length ()I
    IF_ICMPGE L4
   L5
    LINENUMBER 36 L5
    ALOAD 0
    ILOAD 3
    INVOKEVIRTUAL java/lang/String.charAt (I)C
    INVOKESTATIC java/lang/Character.isLetter (C)Z
    IFEQ L6
   L7
    LINENUMBER 37 L7
    ICONST_1
    ISTORE 2
   L8
    LINENUMBER 38 L8
    ALOAD 0
    ILOAD 3
    INVOKEVIRTUAL java/lang/String.charAt (I)C
    INVOKESTATIC java/lang/Character.isUpperCase (C)Z
    IFNE L9
   L10
    LINENUMBER 39 L10
    ALOAD 1
    ALOAD 0
    ILOAD 3
    INVOKEVIRTUAL java/lang/String.charAt (I)C
    INVOKESTATIC java/lang/Character.toLowerCase (C)C
    INVOKEDYNAMIC makeConcatWithConstants(Ljava/lang/String;C)Ljava/lang/String; [
      // handle kind 0x6 : INVOKESTATIC
      java/lang/invoke/StringConcatFactory.makeConcatWithConstants(Ljava/lang/invoke/MethodHandles$Lookup;Ljava/lang/String;Ljava/lang/invoke/MethodType;Ljava/lang/String;[Ljava/lang/Object;)Ljava/lang/invoke/CallSite;
      // arguments:
      "\u0001\u0001"
    ]
    ASTORE 1
    GOTO L11
   L9
    LINENUMBER 41 L9
   FRAME FULL [java/lang/String java/lang/String I I] []
    ALOAD 1
    ALOAD 0
    ILOAD 3
    INVOKEVIRTUAL java/lang/String.charAt (I)C
    INVOKESTATIC java/lang/Character.toUpperCase (C)C
    INVOKEDYNAMIC makeConcatWithConstants(Ljava/lang/String;C)Ljava/lang/String; [
      // handle kind 0x6 : INVOKESTATIC
      java/lang/invoke/StringConcatFactory.makeConcatWithConstants(Ljava/lang/invoke/MethodHandles$Lookup;Ljava/lang/String;Ljava/lang/invoke/MethodType;Ljava/lang/String;[Ljava/lang/Object;)Ljava/lang/invoke/CallSite;
      // arguments:
      "\u0001\u0001"
    ]
    ASTORE 1
    GOTO L11
   L6
    LINENUMBER 44 L6
   FRAME FULL [java/lang/String java/lang/String I I] []
    ALOAD 1
    ALOAD 0
    ILOAD 3
    INVOKEVIRTUAL java/lang/String.charAt (I)C
    INVOKEDYNAMIC makeConcatWithConstants(Ljava/lang/String;C)Ljava/lang/String; [
      // handle kind 0x6 : INVOKESTATIC
      java/lang/invoke/StringConcatFactory.makeConcatWithConstants(Ljava/lang/invoke/MethodHandles$Lookup;Ljava/lang/String;Ljava/lang/invoke/MethodType;Ljava/lang/String;[Ljava/lang/Object;)Ljava/lang/invoke/CallSite;
      // arguments:
      "\u0001\u0001"
    ]
    ASTORE 1
   L11
    LINENUMBER 35 L11
   FRAME FULL [java/lang/String java/lang/String I I] []
    IINC 3 1
    GOTO L3
   L4
    LINENUMBER 47 L4
   FRAME FULL [java/lang/String java/lang/String I I] []
    ILOAD 2
    IFNE L12
   L13
    LINENUMBER 48 L13
    NEW java/lang/StringBuilder
    DUP
    ALOAD 1
    INVOKESPECIAL java/lang/StringBuilder.<init> (Ljava/lang/String;)V
    INVOKEVIRTUAL java/lang/StringBuilder.reverse ()Ljava/lang/StringBuilder;
    INVOKEVIRTUAL java/lang/StringBuilder.toString ()Ljava/lang/String;
    ASTORE 1
   L12
    LINENUMBER 50 L12
   FRAME FULL [java/lang/String java/lang/String I I] []
    ALOAD 1
    ARETURN
   L14
    LOCALVARIABLE i I L3 L4 3
    LOCALVARIABLE s Ljava/lang/String; L0 L14 0
    LOCALVARIABLE result Ljava/lang/String; L1 L14 1
    LOCALVARIABLE hasLetters Z L2 L14 2
    MAXSTACK = 3
    MAXLOCALS = 4
}

