// class version 55.0 (55)
// access flags 0x20
class original/NeighborSum {

  // compiled from: id_3242.java

  // access flags 0x2
  private [[I grid

  // access flags 0x12
  // signature Ljava/util/Map<Ljava/lang/Integer;[I>;
  // declaration: d extends java.util.Map<java.lang.Integer, int[]>
  private final Ljava/util/Map; d

  // access flags 0x12
  private final [[I dirs

  // access flags 0x1
  public <init>([[I)V
   L0
    LINENUMBER 10 L0
    ALOAD 0
    INVOKESPECIAL java/lang/Object.<init> ()V
   L1
    LINENUMBER 7 L1
    ALOAD 0
    NEW java/util/HashMap
    DUP
    INVOKESPECIAL java/util/HashMap.<init> ()V
    PUTFIELD original/NeighborSum.d : Ljava/util/Map;
   L2
    LINENUMBER 8 L2
    ALOAD 0
    ICONST_2
    ANEWARRAY [I
    DUP
    ICONST_0
    ICONST_5
    NEWARRAY T_INT
    DUP
    ICONST_0
    ICONST_M1
    IASTORE
    DUP
    ICONST_1
    ICONST_0
    IASTORE
    DUP
    ICONST_2
    ICONST_1
    IASTORE
    DUP
    ICONST_3
    ICONST_0
    IASTORE
    DUP
    ICONST_4
    ICONST_M1
    IASTORE
    AASTORE
    DUP
    ICONST_1
    ICONST_5
    NEWARRAY T_INT
    DUP
    ICONST_0
    ICONST_M1
    IASTORE
    DUP
    ICONST_1
    ICONST_1
    IASTORE
    DUP
    ICONST_2
    ICONST_1
    IASTORE
    DUP
    ICONST_3
    ICONST_M1
    IASTORE
    DUP
    ICONST_4
    ICONST_M1
    IASTORE
    AASTORE
    PUTFIELD original/NeighborSum.dirs : [[I
   L3
    LINENUMBER 11 L3
    ALOAD 0
    ALOAD 1
    PUTFIELD original/NeighborSum.grid : [[I
   L4
    LINENUMBER 12 L4
    ALOAD 1
    ARRAYLENGTH
    ISTORE 2
   L5
    ALOAD 1
    ICONST_0
    AALOAD
    ARRAYLENGTH
    ISTORE 3
   L6
    LINENUMBER 13 L6
    ICONST_0
    ISTORE 4
   L7
   FRAME FULL [original/NeighborSum [[I I I I] []
    ILOAD 4
    ILOAD 2
    IF_ICMPGE L8
   L9
    LINENUMBER 14 L9
    ICONST_0
    ISTORE 5
   L10
   FRAME FULL [original/NeighborSum [[I I I I I] []
    ILOAD 5
    ILOAD 3
    IF_ICMPGE L11
   L12
    LINENUMBER 15 L12
    ALOAD 0
    GETFIELD original/NeighborSum.d : Ljava/util/Map;
    ALOAD 1
    ILOAD 4
    AALOAD
    ILOAD 5
    IALOAD
    INVOKESTATIC java/lang/Integer.valueOf (I)Ljava/lang/Integer;
    ICONST_2
    NEWARRAY T_INT
    DUP
    ICONST_0
    ILOAD 4
    IASTORE
    DUP
    ICONST_1
    ILOAD 5
    IASTORE
    INVOKEINTERFACE java/util/Map.put (Ljava/lang/Object;Ljava/lang/Object;)Ljava/lang/Object; (itf)
    POP
   L13
    LINENUMBER 14 L13
    IINC 5 1
    GOTO L10
   L11
    LINENUMBER 13 L11
   FRAME FULL [original/NeighborSum [[I I I I I] []
    IINC 4 1
    GOTO L7
   L8
    LINENUMBER 18 L8
   FRAME FULL [original/NeighborSum [[I I I I] []
    RETURN
   L14
    LOCALVARIABLE j I L10 L11 5
    LOCALVARIABLE i I L7 L8 4
    LOCALVARIABLE this Loriginal/NeighborSum; L0 L14 0
    LOCALVARIABLE grid [[I L0 L14 1
    LOCALVARIABLE m I L5 L14 2
    LOCALVARIABLE n I L6 L14 3
    MAXSTACK = 8
    MAXLOCALS = 6

  // access flags 0x1
  public adjacentSum(I)I
   L0
    LINENUMBER 21 L0
    ALOAD 0
    ILOAD 1
    ICONST_0
    INVOKEVIRTUAL original/NeighborSum.cal (II)I
    IRETURN
   L1
    LOCALVARIABLE this Loriginal/NeighborSum; L0 L1 0
    LOCALVARIABLE value I L0 L1 1
    MAXSTACK = 3
    MAXLOCALS = 2

  // access flags 0x1
  public diagonalSum(I)I
   L0
    LINENUMBER 25 L0
    ALOAD 0
    ILOAD 1
    ICONST_1
    INVOKEVIRTUAL original/NeighborSum.cal (II)I
    IRETURN
   L1
    LOCALVARIABLE this Loriginal/NeighborSum; L0 L1 0
    LOCALVARIABLE value I L0 L1 1
    MAXSTACK = 3
    MAXLOCALS = 2

  // access flags 0x2
  private cal(II)I
   L0
    LINENUMBER 29 L0
    ALOAD 0
    GETFIELD original/NeighborSum.d : Ljava/util/Map;
    ILOAD 1
    INVOKESTATIC java/lang/Integer.valueOf (I)Ljava/lang/Integer;
    INVOKEINTERFACE java/util/Map.get (Ljava/lang/Object;)Ljava/lang/Object; (itf)
    CHECKCAST [I
    ASTORE 3
   L1
    LINENUMBER 30 L1
    ICONST_0
    ISTORE 4
   L2
    LINENUMBER 31 L2
    ICONST_0
    ISTORE 5
   L3
   FRAME FULL [original/NeighborSum I I [I I I] []
    ILOAD 5
    ICONST_4
    IF_ICMPGE L4
   L5
    LINENUMBER 32 L5
    ALOAD 3
    ICONST_0
    IALOAD
    ALOAD 0
    GETFIELD original/NeighborSum.dirs : [[I
    ILOAD 2
    AALOAD
    ILOAD 5
    IALOAD
    IADD
    ISTORE 6
   L6
    ALOAD 3
    ICONST_1
    IALOAD
    ALOAD 0
    GETFIELD original/NeighborSum.dirs : [[I
    ILOAD 2
    AALOAD
    ILOAD 5
    ICONST_1
    IADD
    IALOAD
    IADD
    ISTORE 7
   L7
    LINENUMBER 33 L7
    ILOAD 6
    IFLT L8
    ILOAD 6
    ALOAD 0
    GETFIELD original/NeighborSum.grid : [[I
    ARRAYLENGTH
    IF_ICMPLT L8
    ILOAD 7
    IFLT L8
    ILOAD 7
    ALOAD 0
    GETFIELD original/NeighborSum.grid : [[I
    ICONST_0
    AALOAD
    ARRAYLENGTH
    IF_ICMPGE L8
   L9
    LINENUMBER 34 L9
    ILOAD 4
    ALOAD 0
    GETFIELD original/NeighborSum.grid : [[I
    ILOAD 6
    AALOAD
    ILOAD 7
    IALOAD
    IADD
    ISTORE 4
   L8
    LINENUMBER 31 L8
   FRAME FULL [original/NeighborSum I I [I I I I I] []
    IINC 5 1
    GOTO L3
   L4
    LINENUMBER 37 L4
   FRAME FULL [original/NeighborSum I I [I I I] []
    ILOAD 4
    IRETURN
   L10
    LOCALVARIABLE x I L6 L8 6
    LOCALVARIABLE y I L7 L8 7
    LOCALVARIABLE q I L3 L4 5
    LOCALVARIABLE this Loriginal/NeighborSum; L0 L10 0
    LOCALVARIABLE value I L0 L10 1
    LOCALVARIABLE k I L0 L10 2
    LOCALVARIABLE p [I L1 L10 3
    LOCALVARIABLE s I L2 L10 4
    MAXSTACK = 4
    MAXLOCALS = 8
}

