// class version 55.0 (55)
// access flags 0x20
class original/StrongestExtension {

  // compiled from: id_153.java
  // access flags 0x19
  public final static INNERCLASS java/lang/invoke/MethodHandles$Lookup java/lang/invoke/MethodHandles Lookup

  // access flags 0x0
  <init>()V
   L0
    LINENUMBER 7 L0
    ALOAD 0
    INVOKESPECIAL java/lang/Object.<init> ()V
    RETURN
   L1
    LOCALVARIABLE this Loriginal/StrongestExtension; L0 L1 0
    MAXSTACK = 1
    MAXLOCALS = 1

  // access flags 0x9
  // signature (Ljava/lang/String;Ljava/util/List<Ljava/lang/String;>;)Ljava/lang/String;
  // declaration: java.lang.String strongestExtension(java.lang.String, java.util.List<java.lang.String>)
  public static strongestExtension(Ljava/lang/String;Ljava/util/List;)Ljava/lang/String;
   L0
    LINENUMBER 45 L0
    LDC -2147483648
    ISTORE 2
   L1
    LINENUMBER 46 L1
    LDC ""
    ASTORE 3
   L2
    LINENUMBER 47 L2
    ICONST_0
    ISTORE 4
   L3
   FRAME FULL [java/lang/String java/util/List I java/lang/String I] []
    ILOAD 4
    ALOAD 1
    INVOKEINTERFACE java/util/List.size ()I (itf)
    IF_ICMPGT L4
   L5
    LINENUMBER 48 L5
    ICONST_0
    ISTORE 5
   L6
    LINENUMBER 49 L6
    ICONST_0
    ISTORE 6
   L7
    LINENUMBER 50 L7
    ICONST_0
    ISTORE 7
   L8
   FRAME FULL [java/lang/String java/util/List I java/lang/String I I I I] []
    ILOAD 7
    ALOAD 1
    ILOAD 4
    INVOKEINTERFACE java/util/List.get (I)Ljava/lang/Object; (itf)
    CHECKCAST java/lang/String
    INVOKEVIRTUAL java/lang/String.length ()I
    IF_ICMPGE L9
   L10
    LINENUMBER 51 L10
    ALOAD 1
    ILOAD 4
    INVOKEINTERFACE java/util/List.get (I)Ljava/lang/Object; (itf)
    CHECKCAST java/lang/String
    ILOAD 7
    INVOKEVIRTUAL java/lang/String.charAt (I)C
    INVOKESTATIC java/lang/Character.isUpperCase (C)Z
    IFEQ L11
   L12
    LINENUMBER 52 L12
    IINC 5 1
    GOTO L13
   L11
    LINENUMBER 53 L11
   FRAME FULL [java/lang/String java/util/List I java/lang/String I I I I] []
    ALOAD 1
    ILOAD 4
    INVOKEINTERFACE java/util/List.get (I)Ljava/lang/Object; (itf)
    CHECKCAST java/lang/String
    ILOAD 7
    INVOKEVIRTUAL java/lang/String.charAt (I)C
    INVOKESTATIC java/lang/Character.isLowerCase (C)Z
    IFEQ L13
   L14
    LINENUMBER 54 L14
    IINC 6 1
   L13
    LINENUMBER 50 L13
   FRAME FULL [java/lang/String java/util/List I java/lang/String I I I I] []
    IINC 7 1
    GOTO L8
   L9
    LINENUMBER 57 L9
   FRAME FULL [java/lang/String java/util/List I java/lang/String I I I I] []
    ILOAD 5
    ILOAD 6
    ISUB
    ILOAD 2
    IF_ICMPLE L15
   L16
    LINENUMBER 58 L16
    ILOAD 5
    ILOAD 6
    ISUB
    ISTORE 2
   L17
    LINENUMBER 59 L17
    ALOAD 0
    ALOAD 1
    ILOAD 4
    INVOKEINTERFACE java/util/List.get (I)Ljava/lang/Object; (itf)
    CHECKCAST java/lang/String
    INVOKEDYNAMIC makeConcatWithConstants(Ljava/lang/String;Ljava/lang/String;)Ljava/lang/String; [
      // handle kind 0x6 : INVOKESTATIC
      java/lang/invoke/StringConcatFactory.makeConcatWithConstants(Ljava/lang/invoke/MethodHandles$Lookup;Ljava/lang/String;Ljava/lang/invoke/MethodType;Ljava/lang/String;[Ljava/lang/Object;)Ljava/lang/invoke/CallSite;
      // arguments:
      "\u0001.\u0001"
    ]
    ASTORE 3
   L15
    LINENUMBER 47 L15
   FRAME FULL [java/lang/String java/util/List I java/lang/String I I I I] []
    IINC 4 1
    GOTO L3
   L4
    LINENUMBER 62 L4
   FRAME FULL [java/lang/String java/util/List I java/lang/String I] []
    ALOAD 3
    ARETURN
   L18
    LOCALVARIABLE j I L8 L9 7
    LOCALVARIABLE cap I L6 L15 5
    LOCALVARIABLE sm I L7 L15 6
    LOCALVARIABLE i I L3 L4 4
    LOCALVARIABLE className Ljava/lang/String; L0 L18 0
    LOCALVARIABLE extensions Ljava/util/List; L0 L18 1
    // signature Ljava/util/List<Ljava/lang/String;>;
    // declaration: extensions extends java.util.List<java.lang.String>
    LOCALVARIABLE max I L1 L18 2
    LOCALVARIABLE result Ljava/lang/String; L2 L18 3
    MAXSTACK = 3
    MAXLOCALS = 8
}

