// class version 55.0 (55)
// access flags 0x20
class original/Solution0748 {

  // compiled from: id_0748.java

  // access flags 0x0
  <init>()V
   L0
    LINENUMBER 3 L0
    ALOAD 0
    INVOKESPECIAL java/lang/Object.<init> ()V
    RETURN
   L1
    LOCALVARIABLE this Loriginal/Solution0748; L0 L1 0
    MAXSTACK = 1
    MAXLOCALS = 1

  // access flags 0x1
  public shortestCompletingWord(Ljava/lang/String;[Ljava/lang/String;)Ljava/lang/String;
   L0
    LINENUMBER 5 L0
    BIPUSH 26
    NEWARRAY T_INT
    ASTORE 3
   L1
    LINENUMBER 6 L1
    ICONST_0
    ISTORE 4
   L2
   FRAME FULL [original/Solution0748 java/lang/String [Ljava/lang/String; [I I] []
    ILOAD 4
    ALOAD 1
    INVOKEVIRTUAL java/lang/String.length ()I
    IF_ICMPGE L3
   L4
    LINENUMBER 7 L4
    ALOAD 1
    ILOAD 4
    INVOKEVIRTUAL java/lang/String.charAt (I)C
    ISTORE 5
   L5
    LINENUMBER 8 L5
    ILOAD 5
    INVOKESTATIC java/lang/Character.isLetter (C)Z
    IFEQ L6
   L7
    LINENUMBER 9 L7
    ALOAD 3
    ILOAD 5
    INVOKESTATIC java/lang/Character.toLowerCase (C)C
    BIPUSH 97
    ISUB
    DUP2
    IALOAD
    ICONST_1
    IADD
    IASTORE
   L6
    LINENUMBER 6 L6
   FRAME FULL [original/Solution0748 java/lang/String [Ljava/lang/String; [I I I] []
    IINC 4 1
    GOTO L2
   L3
    LINENUMBER 12 L3
   FRAME FULL [original/Solution0748 java/lang/String [Ljava/lang/String; [I I] []
    LDC ""
    ASTORE 4
   L8
    LINENUMBER 13 L8
    ALOAD 2
    ASTORE 5
    ALOAD 5
    ARRAYLENGTH
    ISTORE 6
    ICONST_0
    ISTORE 7
   L9
   FRAME FULL [original/Solution0748 java/lang/String [Ljava/lang/String; [I java/lang/String [Ljava/lang/String; I I] []
    ILOAD 7
    ILOAD 6
    IF_ICMPGE L10
    ALOAD 5
    ILOAD 7
    AALOAD
    ASTORE 8
   L11
    LINENUMBER 14 L11
    ALOAD 4
    INVOKEVIRTUAL java/lang/String.isEmpty ()Z
    IFNE L12
    ALOAD 8
    INVOKEVIRTUAL java/lang/String.length ()I
    ALOAD 4
    INVOKEVIRTUAL java/lang/String.length ()I
    IF_ICMPLT L12
   L13
    LINENUMBER 15 L13
    GOTO L14
   L12
    LINENUMBER 17 L12
   FRAME FULL [original/Solution0748 java/lang/String [Ljava/lang/String; [I java/lang/String [Ljava/lang/String; I I java/lang/String] []
    BIPUSH 26
    NEWARRAY T_INT
    ASTORE 9
   L15
    LINENUMBER 18 L15
    ICONST_0
    ISTORE 10
   L16
   FRAME FULL [original/Solution0748 java/lang/String [Ljava/lang/String; [I java/lang/String [Ljava/lang/String; I I java/lang/String [I I] []
    ILOAD 10
    ALOAD 8
    INVOKEVIRTUAL java/lang/String.length ()I
    IF_ICMPGE L17
   L18
    LINENUMBER 19 L18
    ALOAD 9
    ALOAD 8
    ILOAD 10
    INVOKEVIRTUAL java/lang/String.charAt (I)C
    BIPUSH 97
    IADD
    DUP2
    IALOAD
    ICONST_1
    IADD
    IASTORE
   L19
    LINENUMBER 18 L19
    IINC 10 1
    GOTO L16
   L17
    LINENUMBER 21 L17
   FRAME FULL [original/Solution0748 java/lang/String [Ljava/lang/String; [I java/lang/String [Ljava/lang/String; I I java/lang/String [I I] []
    ICONST_1
    ISTORE 10
   L20
    LINENUMBER 22 L20
    ICONST_0
    ISTORE 11
   L21
   FRAME FULL [original/Solution0748 java/lang/String [Ljava/lang/String; [I java/lang/String [Ljava/lang/String; I I java/lang/String [I I I] []
    ILOAD 11
    BIPUSH 26
    IF_ICMPGE L22
   L23
    LINENUMBER 23 L23
    ALOAD 9
    ILOAD 11
    IALOAD
    ALOAD 3
    ILOAD 11
    IALOAD
    IF_ICMPGE L24
   L25
    LINENUMBER 24 L25
    ICONST_0
    ISTORE 10
   L26
    LINENUMBER 25 L26
    GOTO L22
   L24
    LINENUMBER 22 L24
   FRAME FULL [original/Solution0748 java/lang/String [Ljava/lang/String; [I java/lang/String [Ljava/lang/String; I I java/lang/String [I I I] []
    IINC 11 1
    GOTO L21
   L22
    LINENUMBER 28 L22
   FRAME FULL [original/Solution0748 java/lang/String [Ljava/lang/String; [I java/lang/String [Ljava/lang/String; I I java/lang/String [I I I] []
    ILOAD 10
    IFEQ L14
   L27
    LINENUMBER 29 L27
    ALOAD 8
    ASTORE 4
   L14
    LINENUMBER 13 L14
   FRAME FULL [original/Solution0748 java/lang/String [Ljava/lang/String; [I java/lang/String [Ljava/lang/String; I I java/lang/String] []
    IINC 7 1
    GOTO L9
   L10
    LINENUMBER 32 L10
   FRAME FULL [original/Solution0748 java/lang/String [Ljava/lang/String; [I java/lang/String [Ljava/lang/String; I I] []
    ALOAD 4
    ARETURN
   L28
    LOCALVARIABLE c C L5 L6 5
    LOCALVARIABLE i I L2 L3 4
    LOCALVARIABLE i I L16 L17 10
    LOCALVARIABLE i I L21 L22 11
    LOCALVARIABLE t [I L15 L14 9
    LOCALVARIABLE ok Z L20 L14 10
    LOCALVARIABLE w Ljava/lang/String; L11 L14 8
    LOCALVARIABLE this Loriginal/Solution0748; L0 L28 0
    LOCALVARIABLE licensePlate Ljava/lang/String; L0 L28 1
    LOCALVARIABLE words [Ljava/lang/String; L0 L28 2
    LOCALVARIABLE cnt [I L1 L28 3
    LOCALVARIABLE ans Ljava/lang/String; L8 L28 4
    MAXSTACK = 4
    MAXLOCALS = 12
}

