// class version 55.0 (55)
// access flags 0x20
class original/SelectWords {

  // compiled from: id_117.java

  // access flags 0x0
  <init>()V
   L0
    LINENUMBER 7 L0
    ALOAD 0
    INVOKESPECIAL java/lang/Object.<init> ()V
    RETURN
   L1
    LOCALVARIABLE this Loriginal/SelectWords; L0 L1 0
    MAXSTACK = 1
    MAXLOCALS = 1

  // access flags 0x9
  // signature (Ljava/lang/String;I)Ljava/util/List<Ljava/lang/Object;>;
  // declaration: java.util.List<java.lang.Object> selectWords(java.lang.String, int)
  public static selectWords(Ljava/lang/String;I)Ljava/util/List;
   L0
    LINENUMBER 37 L0
    NEW java/util/ArrayList
    DUP
    INVOKESPECIAL java/util/ArrayList.<init> ()V
    ASTORE 2
   L1
    LINENUMBER 38 L1
    ALOAD 0
    LDC " "
    INVOKEVIRTUAL java/lang/String.split (Ljava/lang/String;)[Ljava/lang/String;
    ASTORE 3
   L2
    LINENUMBER 39 L2
    ALOAD 3
    ASTORE 4
    ALOAD 4
    ARRAYLENGTH
    ISTORE 5
    ICONST_0
    ISTORE 6
   L3
   FRAME FULL [java/lang/String I java/util/ArrayList [Ljava/lang/String; [Ljava/lang/String; I I] []
    ILOAD 6
    ILOAD 5
    IF_ICMPGE L4
    ALOAD 4
    ILOAD 6
    AALOAD
    ASTORE 7
   L5
    LINENUMBER 40 L5
    ICONST_0
    ISTORE 8
   L6
    LINENUMBER 41 L6
    ICONST_0
    ISTORE 9
   L7
   FRAME FULL [java/lang/String I java/util/ArrayList [Ljava/lang/String; [Ljava/lang/String; I I java/lang/String I I] []
    ILOAD 9
    ALOAD 7
    INVOKEVIRTUAL java/lang/String.length ()I
    IF_ICMPLT L8
   L9
    LINENUMBER 42 L9
    ALOAD 7
    ILOAD 9
    INVOKEVIRTUAL java/lang/String.charAt (I)C
    ISTORE 10
   L10
    LINENUMBER 43 L10
    ILOAD 10
    BIPUSH 97
    IF_ICMPEQ L11
    ILOAD 10
    BIPUSH 101
    IF_ICMPEQ L11
    ILOAD 10
    BIPUSH 105
    IF_ICMPEQ L11
    ILOAD 10
    BIPUSH 111
    IF_ICMPEQ L11
    ILOAD 10
    BIPUSH 117
    IF_ICMPEQ L11
    ILOAD 10
    BIPUSH 65
    IF_ICMPEQ L11
    ILOAD 10
    BIPUSH 69
    IF_ICMPEQ L11
    ILOAD 10
    BIPUSH 73
    IF_ICMPEQ L11
    ILOAD 10
    BIPUSH 79
    IF_ICMPEQ L11
    ILOAD 10
    BIPUSH 85
    IF_ICMPEQ L11
   L12
    LINENUMBER 44 L12
    IINC 8 1
   L11
    LINENUMBER 41 L11
   FRAME FULL [java/lang/String I java/util/ArrayList [Ljava/lang/String; [Ljava/lang/String; I I java/lang/String I I I] []
    IINC 9 1
    GOTO L7
   L8
    LINENUMBER 47 L8
   FRAME FULL [java/lang/String I java/util/ArrayList [Ljava/lang/String; [Ljava/lang/String; I I java/lang/String I I] []
    ILOAD 8
    ILOAD 1
    IF_ICMPNE L13
   L14
    LINENUMBER 48 L14
    ALOAD 2
    ALOAD 7
    INVOKEINTERFACE java/util/List.add (Ljava/lang/Object;)Z (itf)
    POP
   L13
    LINENUMBER 39 L13
   FRAME FULL [java/lang/String I java/util/ArrayList [Ljava/lang/String; [Ljava/lang/String; I I java/lang/String I I] []
    IINC 6 1
    GOTO L3
   L4
    LINENUMBER 51 L4
   FRAME FULL [java/lang/String I java/util/ArrayList [Ljava/lang/String; [Ljava/lang/String; I I] []
    ALOAD 2
    ARETURN
   L15
    LOCALVARIABLE c C L10 L11 10
    LOCALVARIABLE i I L7 L8 9
    LOCALVARIABLE consonants I L6 L13 8
    LOCALVARIABLE word Ljava/lang/String; L5 L13 7
    LOCALVARIABLE s Ljava/lang/String; L0 L15 0
    LOCALVARIABLE n I L0 L15 1
    LOCALVARIABLE result Ljava/util/List; L1 L15 2
    // signature Ljava/util/List<Ljava/lang/Object;>;
    // declaration: result extends java.util.List<java.lang.Object>
    LOCALVARIABLE words [Ljava/lang/String; L2 L15 3
    MAXSTACK = 2
    MAXLOCALS = 11
}

