// class version 55.0 (55)
// access flags 0x20
class original/BelowZero {

  // compiled from: id_3.java

  // access flags 0x0
  <init>()V
   L0
    LINENUMBER 7 L0
    ALOAD 0
    INVOKESPECIAL java/lang/Object.<init> ()V
    RETURN
   L1
    LOCALVARIABLE this Loriginal/BelowZero; L0 L1 0
    MAXSTACK = 1
    MAXLOCALS = 1

  // access flags 0x9
  // signature (Ljava/util/List<Ljava/lang/Object;>;)Ljava/lang/Boolean;
  // declaration: java.lang.Boolean belowZero(java.util.List<java.lang.Object>)
  public static belowZero(Ljava/util/List;)Ljava/lang/Boolean;
   L0
    LINENUMBER 31 L0
    DCONST_0
    INVOKESTATIC java/lang/Double.valueOf (D)Ljava/lang/Double;
    ASTORE 1
   L1
    LINENUMBER 32 L1
    ALOAD 0
    INVOKEINTERFACE java/util/List.iterator ()Ljava/util/Iterator; (itf)
    ASTORE 2
   L2
   FRAME FULL [java/util/List java/lang/Double java/util/Iterator] []
    ALOAD 2
    INVOKEINTERFACE java/util/Iterator.hasNext ()Z (itf)
    IFEQ L3
    ALOAD 2
    INVOKEINTERFACE java/util/Iterator.next ()Ljava/lang/Object; (itf)
    ASTORE 3
   L4
    LINENUMBER 33 L4
    ALOAD 3
    INSTANCEOF java/lang/Double
    IFEQ L5
   L6
    LINENUMBER 34 L6
    ALOAD 1
    INVOKEVIRTUAL java/lang/Double.doubleValue ()D
    ALOAD 3
    CHECKCAST java/lang/Double
    INVOKEVIRTUAL java/lang/Double.doubleValue ()D
    DADD
    INVOKESTATIC java/lang/Double.valueOf (D)Ljava/lang/Double;
    ASTORE 1
    GOTO L7
   L5
    LINENUMBER 35 L5
   FRAME FULL [java/util/List java/lang/Double java/util/Iterator java/lang/Object] []
    ALOAD 3
    INSTANCEOF java/lang/Integer
    IFEQ L8
   L9
    LINENUMBER 36 L9
    ALOAD 1
    INVOKEVIRTUAL java/lang/Double.doubleValue ()D
    ALOAD 3
    CHECKCAST java/lang/Integer
    INVOKEVIRTUAL java/lang/Integer.intValue ()I
    I2D
    DSUB
    INVOKESTATIC java/lang/Double.valueOf (D)Ljava/lang/Double;
    ASTORE 1
    GOTO L7
   L8
    LINENUMBER 38 L8
   FRAME FULL [java/util/List java/lang/Double java/util/Iterator java/lang/Object] []
    NEW java/lang/IllegalArgumentException
    DUP
    LDC "Invalid operation type"
    INVOKESPECIAL java/lang/IllegalArgumentException.<init> (Ljava/lang/String;)V
    ATHROW
   L7
    LINENUMBER 40 L7
   FRAME FULL [java/util/List java/lang/Double java/util/Iterator java/lang/Object] []
    ALOAD 1
    INVOKEVIRTUAL java/lang/Double.doubleValue ()D
    DCONST_0
    DCMPG
    IFGE L10
   L11
    LINENUMBER 41 L11
    ICONST_1
    INVOKESTATIC java/lang/Boolean.valueOf (Z)Ljava/lang/Boolean;
    ARETURN
   L10
    LINENUMBER 43 L10
   FRAME FULL [java/util/List java/lang/Double java/util/Iterator java/lang/Object] []
    GOTO L2
   L3
    LINENUMBER 44 L3
   FRAME FULL [java/util/List java/lang/Double java/util/Iterator] []
    ICONST_0
    INVOKESTATIC java/lang/Boolean.valueOf (Z)Ljava/lang/Boolean;
    ARETURN
   L12
    LOCALVARIABLE operation Ljava/lang/Object; L4 L10 3
    LOCALVARIABLE operations Ljava/util/List; L0 L12 0
    // signature Ljava/util/List<Ljava/lang/Object;>;
    // declaration: operations extends java.util.List<java.lang.Object>
    LOCALVARIABLE balance Ljava/lang/Double; L1 L12 1
    MAXSTACK = 4
    MAXLOCALS = 4
}

