// class version 55.0 (55)
// access flags 0x20
// signature Ljava/lang/Object;Ljava/util/Comparator<Ljava/lang/Object;>;
// declaration: original/GetRow$1 implements java.util.Comparator<java.lang.Object>
class original/GetRow$1 implements java/util/Comparator {

  // compiled from: id_87.java
  NESTHOST original/GetRow
  OUTERCLASS original/GetRow getRow (Ljava/util/List;I)Ljava/util/List;
  // access flags 0x0
  INNERCLASS original/GetRow$1 null null

  // access flags 0x0
  <init>()V
   L0
    LINENUMBER 50 L0
    ALOAD 0
    INVOKESPECIAL java/lang/Object.<init> ()V
    RETURN
   L1
    LOCALVARIABLE this Loriginal/GetRow$1; L0 L1 0
    MAXSTACK = 1
    MAXLOCALS = 1

  // access flags 0x1
  public compare(Ljava/lang/Object;Ljava/lang/Object;)I
   L0
    LINENUMBER 52 L0
    ALOAD 1
    CHECKCAST java/util/List
    ASTORE 3
   L1
    LINENUMBER 53 L1
    ALOAD 2
    CHECKCAST java/util/List
    ASTORE 4
   L2
    LINENUMBER 54 L2
    ALOAD 3
    ICONST_0
    INVOKEINTERFACE java/util/List.get (I)Ljava/lang/Object; (itf)
    CHECKCAST java/lang/Integer
    INVOKEVIRTUAL java/lang/Integer.intValue ()I
    ISTORE 5
   L3
    LINENUMBER 55 L3
    ALOAD 4
    ICONST_0
    INVOKEINTERFACE java/util/List.get (I)Ljava/lang/Object; (itf)
    CHECKCAST java/lang/Integer
    INVOKEVIRTUAL java/lang/Integer.intValue ()I
    ISTORE 6
   L4
    LINENUMBER 56 L4
    ILOAD 5
    ILOAD 6
    IF_ICMPNE L5
   L6
    LINENUMBER 57 L6
    ILOAD 5
    ILOAD 6
    ISUB
    IRETURN
   L5
    LINENUMBER 59 L5
   FRAME FULL [original/GetRow$1 java/lang/Object java/lang/Object java/util/List java/util/List I I] []
    ALOAD 3
    ICONST_1
    INVOKEINTERFACE java/util/List.get (I)Ljava/lang/Object; (itf)
    CHECKCAST java/lang/Integer
    INVOKEVIRTUAL java/lang/Integer.intValue ()I
    ISTORE 7
   L7
    LINENUMBER 60 L7
    ALOAD 4
    ICONST_1
    INVOKEINTERFACE java/util/List.get (I)Ljava/lang/Object; (itf)
    CHECKCAST java/lang/Integer
    INVOKEVIRTUAL java/lang/Integer.intValue ()I
    ISTORE 8
   L8
    LINENUMBER 61 L8
    ILOAD 8
    ILOAD 7
    ISUB
    IRETURN
   L9
    LOCALVARIABLE this Loriginal/GetRow$1; L0 L9 0
    LOCALVARIABLE o1 Ljava/lang/Object; L0 L9 1
    LOCALVARIABLE o2 Ljava/lang/Object; L0 L9 2
    LOCALVARIABLE c1 Ljava/util/List; L1 L9 3
    // signature Ljava/util/List<Ljava/lang/Object;>;
    // declaration: c1 extends java.util.List<java.lang.Object>
    LOCALVARIABLE c2 Ljava/util/List; L2 L9 4
    // signature Ljava/util/List<Ljava/lang/Object;>;
    // declaration: c2 extends java.util.List<java.lang.Object>
    LOCALVARIABLE row1 I L3 L9 5
    LOCALVARIABLE row2 I L4 L9 6
    LOCALVARIABLE col1 I L7 L9 7
    LOCALVARIABLE col2 I L8 L9 8
    MAXSTACK = 2
    MAXLOCALS = 9
}

