// class version 55.0 (55)
// access flags 0x20
class original/CountNums {

  // compiled from: id_108.java

  // access flags 0x0
  <init>()V
   L0
    LINENUMBER 7 L0
    ALOAD 0
    INVOKESPECIAL java/lang/Object.<init> ()V
    RETURN
   L1
    LOCALVARIABLE this Loriginal/CountNums; L0 L1 0
    MAXSTACK = 1
    MAXLOCALS = 1

  // access flags 0x9
  // signature (Ljava/util/List<Ljava/lang/Object;>;)I
  // declaration: int countNums(java.util.List<java.lang.Object>)
  public static countNums(Ljava/util/List;)I
   L0
    LINENUMBER 35 L0
    ICONST_0
    ISTORE 1
   L1
    LINENUMBER 36 L1
    ICONST_0
    ISTORE 2
   L2
   FRAME FULL [java/util/List I I] []
    ILOAD 2
    ALOAD 0
    INVOKEINTERFACE java/util/List.size ()I (itf)
    IF_ICMPGE L3
   L4
    LINENUMBER 37 L4
    ICONST_0
    ISTORE 3
   L5
    LINENUMBER 38 L5
    ALOAD 0
    ILOAD 2
    INVOKEINTERFACE java/util/List.get (I)Ljava/lang/Object; (itf)
    CHECKCAST java/lang/Integer
    INVOKEVIRTUAL java/lang/Integer.intValue ()I
    ISTORE 4
   L6
    LINENUMBER 39 L6
    ILOAD 4
    IFGE L7
    ICONST_1
    GOTO L8
   L7
   FRAME FULL [java/util/List I I I I] []
    ICONST_0
   L8
   FRAME FULL [java/util/List I I I I] [I]
    ISTORE 5
   L9
    LINENUMBER 40 L9
    ILOAD 5
    IFEQ L10
   L11
    LINENUMBER 41 L11
    ILOAD 4
    INEG
    ISTORE 4
   L10
    LINENUMBER 43 L10
   FRAME FULL [java/util/List I I I I I] []
    ILOAD 4
    IFEQ L12
   L13
    LINENUMBER 44 L13
    ILOAD 5
    IFNE L14
    ILOAD 4
    BIPUSH 10
    IDIV
    IFNE L14
   L15
    LINENUMBER 45 L15
    ILOAD 3
    ILOAD 4
    BIPUSH 10
    IREM
    ISUB
    ISTORE 3
    GOTO L16
   L14
    LINENUMBER 47 L14
   FRAME FULL [java/util/List I I I I I] []
    ILOAD 3
    ILOAD 4
    BIPUSH 10
    IREM
    IADD
    ISTORE 3
   L16
    LINENUMBER 49 L16
   FRAME FULL [java/util/List I I I I I] []
    ILOAD 4
    BIPUSH 10
    IDIV
    ISTORE 4
    GOTO L10
   L12
    LINENUMBER 52 L12
   FRAME FULL [java/util/List I I I I I] []
    ILOAD 3
    IFLE L17
   L18
    LINENUMBER 53 L18
    IINC 1 1
   L17
    LINENUMBER 36 L17
   FRAME FULL [java/util/List I I I I I] []
    IINC 2 1
    GOTO L2
   L3
    LINENUMBER 56 L3
   FRAME FULL [java/util/List I I] []
    ILOAD 1
    IRETURN
   L19
    LOCALVARIABLE sum I L5 L17 3
    LOCALVARIABLE num I L6 L17 4
    LOCALVARIABLE isNegative Z L9 L17 5
    LOCALVARIABLE i I L2 L3 2
    LOCALVARIABLE arr Ljava/util/List; L0 L19 0
    // signature Ljava/util/List<Ljava/lang/Object;>;
    // declaration: arr extends java.util.List<java.lang.Object>
    LOCALVARIABLE count I L1 L19 1
    MAXSTACK = 3
    MAXLOCALS = 6
}

