// class version 55.0 (55)
// access flags 0x20
class original/IsMultiplyPrime {

  // compiled from: id_75.java

  // access flags 0x0
  <init>()V
   L0
    LINENUMBER 4 L0
    ALOAD 0
    INVOKESPECIAL java/lang/Object.<init> ()V
    RETURN
   L1
    LOCALVARIABLE this Loriginal/IsMultiplyPrime; L0 L1 0
    MAXSTACK = 1
    MAXLOCALS = 1

  // access flags 0x9
  public static isMultiplyPrime(I)Ljava/lang/Boolean;
   L0
    LINENUMBER 35 L0
    ICONST_0
    ISTORE 1
   L1
    LINENUMBER 36 L1
    ICONST_2
    ISTORE 2
   L2
   FRAME FULL [I I I] []
    ILOAD 2
    ILOAD 0
    IF_ICMPGE L3
   L4
    LINENUMBER 37 L4
    ILOAD 0
    ILOAD 2
    IREM
    IFNE L5
   L6
    LINENUMBER 38 L6
    IINC 1 1
   L7
    LINENUMBER 39 L7
    ILOAD 0
    ILOAD 2
    IDIV
    ISTORE 0
   L8
    LINENUMBER 40 L8
    IINC 2 -1
   L5
    LINENUMBER 36 L5
   FRAME FULL [I I I] []
    IINC 2 1
    GOTO L2
   L3
    LINENUMBER 43 L3
   FRAME FULL [I I I] []
    ILOAD 1
    ICONST_3
    IF_ICMPNE L9
    ICONST_1
    GOTO L10
   L9
   FRAME FULL [I I I] []
    ICONST_0
   L10
   FRAME FULL [I I I] [I]
    INVOKESTATIC java/lang/Boolean.valueOf (Z)Ljava/lang/Boolean;
    ARETURN
   L11
    LOCALVARIABLE i I L2 L3 2
    LOCALVARIABLE a I L0 L11 0
    LOCALVARIABLE count I L1 L11 1
    MAXSTACK = 2
    MAXLOCALS = 3
}

