// class version 55.0 (55)
// access flags 0x20
class original/ValidDate {

  // compiled from: id_124.java

  // access flags 0x0
  <init>()V
   L0
    LINENUMBER 4 L0
    ALOAD 0
    INVOKESPECIAL java/lang/Object.<init> ()V
    RETURN
   L1
    LOCALVARIABLE this Loriginal/ValidDate; L0 L1 0
    MAXSTACK = 1
    MAXLOCALS = 1

  // access flags 0x9
  public static validDate(Ljava/lang/String;)Ljava/lang/Boolean;
   L0
    LINENUMBER 59 L0
    ALOAD 0
    INVOKEVIRTUAL java/lang/String.length ()I
    BIPUSH 10
    IF_ICMPEQ L1
   L2
    LINENUMBER 60 L2
    ICONST_0
    INVOKESTATIC java/lang/Boolean.valueOf (Z)Ljava/lang/Boolean;
    ARETURN
   L1
    LINENUMBER 62 L1
   FRAME FULL [java/lang/String] []
    ALOAD 0
    LDC "-"
    INVOKEVIRTUAL java/lang/String.split (Ljava/lang/String;)[Ljava/lang/String;
    ASTORE 1
   L3
    LINENUMBER 63 L3
    ALOAD 1
    ARRAYLENGTH
    ICONST_3
    IF_ICMPEQ L4
   L5
    LINENUMBER 64 L5
    ICONST_0
    INVOKESTATIC java/lang/Boolean.valueOf (Z)Ljava/lang/Boolean;
    ARETURN
   L4
    LINENUMBER 66 L4
   FRAME FULL [java/lang/String [Ljava/lang/String;] []
    ALOAD 1
    ICONST_0
    AALOAD
    INVOKESTATIC java/lang/Integer.parseInt (Ljava/lang/String;)I
    ISTORE 2
   L6
    LINENUMBER 67 L6
    ALOAD 1
    ICONST_1
    AALOAD
    INVOKESTATIC java/lang/Integer.parseInt (Ljava/lang/String;)I
    ISTORE 3
   L7
    LINENUMBER 68 L7
    ALOAD 1
    ICONST_2
    AALOAD
    INVOKESTATIC java/lang/Integer.parseInt (Ljava/lang/String;)I
    ISTORE 4
   L8
    LINENUMBER 69 L8
    ILOAD 2
    ICONST_1
    IF_ICMPLT L9
    ILOAD 2
    BIPUSH 12
    IF_ICMPLE L10
   L9
    LINENUMBER 70 L9
   FRAME FULL [java/lang/String [Ljava/lang/String; I I I] []
    ICONST_0
    INVOKESTATIC java/lang/Boolean.valueOf (Z)Ljava/lang/Boolean;
    ARETURN
   L10
    LINENUMBER 72 L10
   FRAME FULL [java/lang/String [Ljava/lang/String; I I I] []
    ILOAD 2
    ICONST_2
    IF_ICMPNE L11
   L12
    LINENUMBER 73 L12
    ILOAD 3
    ICONST_1
    IF_ICMPLT L13
    ILOAD 3
    BIPUSH 29
    IF_ICMPLE L14
   L13
    LINENUMBER 74 L13
   FRAME FULL [java/lang/String [Ljava/lang/String; I I I] []
    ICONST_0
    INVOKESTATIC java/lang/Boolean.valueOf (Z)Ljava/lang/Boolean;
    ARETURN
   L11
    LINENUMBER 76 L11
   FRAME FULL [java/lang/String [Ljava/lang/String; I I I] []
    ILOAD 2
    ICONST_4
    IF_ICMPEQ L15
    ILOAD 2
    BIPUSH 6
    IF_ICMPEQ L15
    ILOAD 2
    BIPUSH 9
    IF_ICMPEQ L15
    ILOAD 2
    BIPUSH 11
    IF_ICMPNE L16
   L15
    LINENUMBER 77 L15
   FRAME FULL [java/lang/String [Ljava/lang/String; I I I] []
    ILOAD 3
    ICONST_1
    IF_ICMPLT L17
    ILOAD 3
    BIPUSH 30
    IF_ICMPLE L14
   L17
    LINENUMBER 78 L17
   FRAME FULL [java/lang/String [Ljava/lang/String; I I I] []
    ICONST_0
    INVOKESTATIC java/lang/Boolean.valueOf (Z)Ljava/lang/Boolean;
    ARETURN
   L16
    LINENUMBER 81 L16
   FRAME FULL [java/lang/String [Ljava/lang/String; I I I] []
    ILOAD 3
    ICONST_1
    IF_ICMPLT L18
    ILOAD 3
    BIPUSH 31
    IF_ICMPLE L14
   L18
    LINENUMBER 82 L18
   FRAME FULL [java/lang/String [Ljava/lang/String; I I I] []
    ICONST_0
    INVOKESTATIC java/lang/Boolean.valueOf (Z)Ljava/lang/Boolean;
    ARETURN
   L14
    LINENUMBER 85 L14
   FRAME FULL [java/lang/String [Ljava/lang/String; I I I] []
    ICONST_1
    INVOKESTATIC java/lang/Boolean.valueOf (Z)Ljava/lang/Boolean;
    POP
    ICONST_0
    INVOKESTATIC java/lang/Boolean.valueOf (Z)Ljava/lang/Boolean;
    ARETURN
   L19
    LOCALVARIABLE date Ljava/lang/String; L0 L19 0
    LOCALVARIABLE dateArr [Ljava/lang/String; L3 L19 1
    LOCALVARIABLE month I L6 L19 2
    LOCALVARIABLE day I L7 L19 3
    LOCALVARIABLE year I L8 L19 4
    MAXSTACK = 2
    MAXLOCALS = 5
}

