// class version 55.0 (55)
// access flags 0x20
class original/Solution2459 {

  // compiled from: id_2459.java

  // access flags 0x0
  <init>()V
   L0
    LINENUMBER 3 L0
    ALOAD 0
    INVOKESPECIAL java/lang/Object.<init> ()V
    RETURN
   L1
    LOCALVARIABLE this Loriginal/Solution2459; L0 L1 0
    MAXSTACK = 1
    MAXLOCALS = 1

  // access flags 0x1
  public sortArray([I)I
   L0
    LINENUMBER 5 L0
    ALOAD 1
    ARRAYLENGTH
    ISTORE 2
   L1
    LINENUMBER 6 L1
    ILOAD 2
    NEWARRAY T_INT
    ASTORE 3
   L2
    LINENUMBER 7 L2
    ICONST_0
    ISTORE 4
   L3
   FRAME FULL [original/Solution2459 [I I [I I] []
    ILOAD 4
    ILOAD 2
    IF_ICMPGE L4
   L5
    LINENUMBER 8 L5
    ALOAD 3
    ILOAD 4
    ALOAD 1
    ILOAD 4
    IALOAD
    ICONST_1
    ISUB
    ILOAD 2
    IADD
    ILOAD 2
    IREM
    IASTORE
   L6
    LINENUMBER 7 L6
    IINC 4 1
    GOTO L3
   L4
    LINENUMBER 10 L4
   FRAME FULL [original/Solution2459 [I I [I I] []
    ALOAD 0
    ALOAD 1
    ICONST_0
    INVOKEVIRTUAL original/Solution2459.f ([II)I
    ISTORE 4
   L7
    LINENUMBER 11 L7
    ALOAD 0
    ALOAD 3
    ILOAD 2
    ICONST_1
    ISUB
    INVOKEVIRTUAL original/Solution2459.f ([II)I
    ISTORE 5
   L8
    LINENUMBER 12 L8
    ILOAD 4
    ILOAD 5
    INVOKESTATIC java/lang/Math.min (II)I
    POP
    ICONST_0
    IRETURN
   L9
    LOCALVARIABLE i I L3 L4 4
    LOCALVARIABLE this Loriginal/Solution2459; L0 L9 0
    LOCALVARIABLE nums [I L0 L9 1
    LOCALVARIABLE n I L1 L9 2
    LOCALVARIABLE arr [I L2 L9 3
    LOCALVARIABLE a I L7 L9 4
    LOCALVARIABLE b I L8 L9 5
    MAXSTACK = 4
    MAXLOCALS = 6

  // access flags 0x2
  private f([II)I
   L0
    LINENUMBER 16 L0
    ALOAD 1
    ARRAYLENGTH
    NEWARRAY T_BOOLEAN
    ASTORE 3
   L1
    LINENUMBER 17 L1
    ICONST_0
    ISTORE 4
   L2
    LINENUMBER 18 L2
    ICONST_0
    ISTORE 5
   L3
   FRAME FULL [original/Solution2459 [I I [Z I I] []
    ILOAD 5
    ALOAD 1
    ARRAYLENGTH
    IF_ICMPGE L4
   L5
    LINENUMBER 19 L5
    ILOAD 5
    ALOAD 1
    ILOAD 5
    IALOAD
    IF_ICMPEQ L6
    ALOAD 3
    ILOAD 5
    BALOAD
    IFEQ L7
   L8
    LINENUMBER 20 L8
    GOTO L6
   L7
    LINENUMBER 22 L7
   FRAME FULL [original/Solution2459 [I I [Z I I] []
    IINC 4 1
   L9
    LINENUMBER 23 L9
    ALOAD 1
    ILOAD 5
    IALOAD
    ISTORE 6
   L10
    LINENUMBER 24 L10
   FRAME FULL [original/Solution2459 [I I [Z I I I] []
    ALOAD 3
    ILOAD 6
    BALOAD
    IFNE L6
   L11
    LINENUMBER 25 L11
    ALOAD 3
    ILOAD 6
    ICONST_1
    BASTORE
   L12
    LINENUMBER 26 L12
    IINC 4 1
   L13
    LINENUMBER 27 L13
    ALOAD 1
    ILOAD 6
    IALOAD
    ISTORE 6
    GOTO L10
   L6
    LINENUMBER 18 L6
   FRAME FULL [original/Solution2459 [I I [Z I I] []
    IINC 5 1
    GOTO L3
   L4
    LINENUMBER 30 L4
   FRAME FULL [original/Solution2459 [I I [Z I I] []
    ALOAD 1
    ILOAD 2
    IALOAD
    ILOAD 2
    IF_ICMPEQ L14
   L15
    LINENUMBER 31 L15
    IINC 4 -2
   L14
    LINENUMBER 33 L14
   FRAME FULL [original/Solution2459 [I I [Z I I] []
    ILOAD 4
    IRETURN
   L16
    LOCALVARIABLE j I L10 L6 6
    LOCALVARIABLE i I L3 L4 5
    LOCALVARIABLE this Loriginal/Solution2459; L0 L16 0
    LOCALVARIABLE nums [I L0 L16 1
    LOCALVARIABLE k I L0 L16 2
    LOCALVARIABLE vis [Z L1 L16 3
    LOCALVARIABLE cnt I L2 L16 4
    MAXSTACK = 3
    MAXLOCALS = 7
}

