// class version 55.0 (55)
// access flags 0x20
class original/Fib4 {

  // compiled from: id_46.java

  // access flags 0x0
  <init>()V
   L0
    LINENUMBER 3 L0
    ALOAD 0
    INVOKESPECIAL java/lang/Object.<init> ()V
    RETURN
   L1
    LOCALVARIABLE this Loriginal/Fib4; L0 L1 0
    MAXSTACK = 1
    MAXLOCALS = 1

  // access flags 0x9
  public static fib4(I)I
   L0
    LINENUMBER 29 L0
    ILOAD 0
    ICONST_2
    IF_ICMPGE L1
   L2
    LINENUMBER 30 L2
    ICONST_0
    IRETURN
   L1
    LINENUMBER 32 L1
   FRAME FULL [I] []
    ILOAD 0
    ICONST_2
    IF_ICMPNE L3
   L4
    LINENUMBER 33 L4
    ICONST_2
    IRETURN
   L3
    LINENUMBER 35 L3
   FRAME FULL [I] []
    ICONST_0
    ISTORE 1
   L5
    LINENUMBER 36 L5
    ICONST_0
    ISTORE 2
   L6
    LINENUMBER 37 L6
    ICONST_2
    ISTORE 3
   L7
    LINENUMBER 38 L7
    ICONST_0
    ISTORE 4
   L8
    LINENUMBER 39 L8
    ICONST_0
    ISTORE 5
   L9
    LINENUMBER 40 L9
    ICONST_4
    ISTORE 6
   L10
   FRAME FULL [I I I I I I I] []
    ILOAD 6
    ILOAD 0
    IF_ICMPGT L11
   L12
    LINENUMBER 41 L12
    ILOAD 1
    ILOAD 2
    IADD
    ILOAD 3
    IADD
    ILOAD 4
    ISUB
    ISTORE 5
   L13
    LINENUMBER 42 L13
    ILOAD 2
    ISTORE 1
   L14
    LINENUMBER 43 L14
    ILOAD 3
    ISTORE 2
   L15
    LINENUMBER 44 L15
    ILOAD 4
    ISTORE 3
   L16
    LINENUMBER 45 L16
    ILOAD 5
    ISTORE 4
   L17
    LINENUMBER 40 L17
    IINC 6 1
    GOTO L10
   L11
    LINENUMBER 47 L11
   FRAME FULL [I I I I I I I] []
    ILOAD 5
    IRETURN
   L18
    LOCALVARIABLE i I L10 L11 6
    LOCALVARIABLE n I L0 L18 0
    LOCALVARIABLE a I L5 L18 1
    LOCALVARIABLE b I L6 L18 2
    LOCALVARIABLE c I L7 L18 3
    LOCALVARIABLE d I L8 L18 4
    LOCALVARIABLE e I L9 L18 5
    MAXSTACK = 2
    MAXLOCALS = 7
}

