// class version 55.0 (55)
// access flags 0x20
class original/Solution1595 {

  // compiled from: id_1595.java

  // access flags 0x0
  <init>()V
   L0
    LINENUMBER 5 L0
    ALOAD 0
    INVOKESPECIAL java/lang/Object.<init> ()V
    RETURN
   L1
    LOCALVARIABLE this Loriginal/Solution1595; L0 L1 0
    MAXSTACK = 1
    MAXLOCALS = 1

  // access flags 0x1
  // signature (Ljava/util/List<Ljava/util/List<Ljava/lang/Integer;>;>;)I
  // declaration: int connectTwoGroups(java.util.List<java.util.List<java.lang.Integer>>)
  public connectTwoGroups(Ljava/util/List;)I
   L0
    LINENUMBER 7 L0
    ALOAD 1
    INVOKEINTERFACE java/util/List.size ()I (itf)
    ISTORE 2
   L1
    ALOAD 1
    ICONST_0
    INVOKEINTERFACE java/util/List.get (I)Ljava/lang/Object; (itf)
    CHECKCAST java/util/List
    INVOKEINTERFACE java/util/List.size ()I (itf)
    ISTORE 3
   L2
    LINENUMBER 8 L2
    LDC 1073741824
    ISTORE 4
   L3
    LINENUMBER 9 L3
    ILOAD 2
    ICONST_1
    IADD
    ICONST_1
    ILOAD 3
    ISHL
    MULTIANEWARRAY [[I 2
    ASTORE 5
   L4
    LINENUMBER 10 L4
    ALOAD 5
    ASTORE 6
    ALOAD 6
    ARRAYLENGTH
    ISTORE 7
    ICONST_0
    ISTORE 8
   L5
   FRAME FULL [original/Solution1595 java/util/List I I I [[I [[I I I] []
    ILOAD 8
    ILOAD 7
    IF_ICMPGE L6
    ALOAD 6
    ILOAD 8
    AALOAD
    ASTORE 9
   L7
    LINENUMBER 11 L7
    ALOAD 9
    LDC 1073741824
    INVOKESTATIC java/util/Arrays.fill ([II)V
   L8
    LINENUMBER 10 L8
    IINC 8 1
    GOTO L5
   L6
    LINENUMBER 13 L6
   FRAME FULL [original/Solution1595 java/util/List I I I [[I [[I I I] []
    ALOAD 5
    ICONST_0
    AALOAD
    ICONST_0
    ICONST_0
    IASTORE
   L9
    LINENUMBER 14 L9
    ICONST_1
    ISTORE 6
   L10
   FRAME FULL [original/Solution1595 java/util/List I I I [[I I I I] []
    ILOAD 6
    ILOAD 2
    IF_ICMPGT L11
   L12
    LINENUMBER 15 L12
    ICONST_0
    ISTORE 7
   L13
   FRAME FULL [original/Solution1595 java/util/List I I I [[I I I I] []
    ILOAD 7
    ICONST_1
    ILOAD 3
    ISHL
    IF_ICMPGE L14
   L15
    LINENUMBER 16 L15
    ICONST_0
    ISTORE 8
   L16
   FRAME FULL [original/Solution1595 java/util/List I I I [[I I I I] []
    ILOAD 8
    ILOAD 3
    IF_ICMPGE L17
   L18
    LINENUMBER 17 L18
    ILOAD 7
    ILOAD 8
    ISHR
    ICONST_1
    IAND
    ICONST_1
    IF_ICMPNE L19
   L20
    LINENUMBER 18 L20
    ALOAD 1
    ILOAD 6
    ICONST_1
    ISUB
    INVOKEINTERFACE java/util/List.get (I)Ljava/lang/Object; (itf)
    CHECKCAST java/util/List
    ILOAD 8
    INVOKEINTERFACE java/util/List.get (I)Ljava/lang/Object; (itf)
    CHECKCAST java/lang/Integer
    INVOKEVIRTUAL java/lang/Integer.intValue ()I
    ISTORE 9
   L21
    LINENUMBER 19 L21
    ALOAD 5
    ILOAD 6
    AALOAD
    ILOAD 7
    ALOAD 5
    ILOAD 6
    AALOAD
    ILOAD 7
    IALOAD
    ALOAD 5
    ILOAD 6
    AALOAD
    ILOAD 7
    ICONST_1
    ILOAD 8
    ISHL
    IXOR
    IALOAD
    ILOAD 9
    IADD
    INVOKESTATIC java/lang/Math.min (II)I
    IASTORE
   L22
    LINENUMBER 20 L22
    ALOAD 5
    ILOAD 6
    AALOAD
    ILOAD 7
    ALOAD 5
    ILOAD 6
    AALOAD
    ILOAD 7
    IALOAD
    ALOAD 5
    ILOAD 6
    ICONST_1
    ISUB
    AALOAD
    ILOAD 7
    IALOAD
    ILOAD 9
    IADD
    INVOKESTATIC java/lang/Math.min (II)I
    IASTORE
   L23
    LINENUMBER 21 L23
    ALOAD 5
    ILOAD 6
    AALOAD
    ILOAD 7
    ALOAD 5
    ILOAD 6
    AALOAD
    ILOAD 7
    IALOAD
    ALOAD 5
    ILOAD 6
    ICONST_1
    ISUB
    AALOAD
    ILOAD 7
    ICONST_1
    ILOAD 8
    ISHR
    IXOR
    IALOAD
    ILOAD 9
    IADD
    INVOKESTATIC java/lang/Math.min (II)I
    IASTORE
   L19
    LINENUMBER 16 L19
   FRAME FULL [original/Solution1595 java/util/List I I I [[I I I I] []
    IINC 8 1
    GOTO L16
   L17
    LINENUMBER 15 L17
   FRAME FULL [original/Solution1595 java/util/List I I I [[I I I I] []
    IINC 7 1
    GOTO L13
   L14
    LINENUMBER 14 L14
   FRAME FULL [original/Solution1595 java/util/List I I I [[I I I I] []
    IINC 6 1
    GOTO L10
   L11
    LINENUMBER 26 L11
   FRAME FULL [original/Solution1595 java/util/List I I I [[I I I I] []
    ALOAD 5
    ILOAD 2
    AALOAD
    ICONST_1
    ILOAD 3
    ISHL
    ICONST_1
    ISUB
    IALOAD
    IRETURN
   L24
    LOCALVARIABLE g [I L7 L8 9
    LOCALVARIABLE c I L21 L19 9
    LOCALVARIABLE k I L16 L17 8
    LOCALVARIABLE j I L13 L14 7
    LOCALVARIABLE i I L10 L11 6
    LOCALVARIABLE this Loriginal/Solution1595; L0 L24 0
    LOCALVARIABLE cost Ljava/util/List; L0 L24 1
    // signature Ljava/util/List<Ljava/util/List<Ljava/lang/Integer;>;>;
    // declaration: cost extends java.util.List<java.util.List<java.lang.Integer>>
    LOCALVARIABLE m I L1 L24 2
    LOCALVARIABLE n I L2 L24 3
    LOCALVARIABLE inf I L3 L24 4
    LOCALVARIABLE f [[I L4 L24 5
    MAXSTACK = 7
    MAXLOCALS = 10
}

