// class version 55.0 (55)
// access flags 0x20
class original/Solution1449 {

  // compiled from: id_1449.java

  // access flags 0x0
  <init>()V
   L0
    LINENUMBER 4 L0
    ALOAD 0
    INVOKESPECIAL java/lang/Object.<init> ()V
    RETURN
   L1
    LOCALVARIABLE this Loriginal/Solution1449; L0 L1 0
    MAXSTACK = 1
    MAXLOCALS = 1

  // access flags 0x1
  public largestNumber([II)Ljava/lang/String;
   L0
    LINENUMBER 6 L0
    LDC 1073741824
    ISTORE 3
   L1
    LINENUMBER 7 L1
    BIPUSH 10
    ILOAD 2
    ICONST_1
    IADD
    MULTIANEWARRAY [[I 2
    ASTORE 4
   L2
    LINENUMBER 8 L2
    BIPUSH 10
    ILOAD 2
    ICONST_1
    IADD
    MULTIANEWARRAY [[I 2
    ASTORE 5
   L3
    LINENUMBER 9 L3
    ALOAD 4
    ASTORE 6
    ALOAD 6
    ARRAYLENGTH
    ISTORE 7
    ICONST_0
    ISTORE 8
   L4
   FRAME FULL [original/Solution1449 [I I I [[I [[I [[I I I] []
    ILOAD 8
    ILOAD 7
    IF_ICMPGE L5
    ALOAD 6
    ILOAD 8
    AALOAD
    ASTORE 9
   L6
    LINENUMBER 10 L6
    ALOAD 9
    LDC -1073741824
    INVOKESTATIC java/util/Arrays.fill ([II)V
   L7
    LINENUMBER 9 L7
    IINC 8 1
    GOTO L4
   L5
    LINENUMBER 12 L5
   FRAME FULL [original/Solution1449 [I I I [[I [[I [[I I I] []
    ALOAD 4
    ICONST_0
    AALOAD
    ICONST_0
    ICONST_0
    IASTORE
   L8
    LINENUMBER 13 L8
    ICONST_1
    ISTORE 6
   L9
   FRAME FULL [original/Solution1449 [I I I [[I [[I I I I] []
    ILOAD 6
    BIPUSH 9
    IF_ICMPGT L10
   L11
    LINENUMBER 14 L11
    ALOAD 1
    ILOAD 6
    ICONST_1
    ISUB
    IALOAD
    ISTORE 7
   L12
    LINENUMBER 15 L12
    ICONST_0
    ISTORE 8
   L13
   FRAME FULL [original/Solution1449 [I I I [[I [[I I I I] []
    ILOAD 8
    ILOAD 2
    IF_ICMPGT L14
   L15
    LINENUMBER 16 L15
    ILOAD 8
    ILOAD 7
    IF_ICMPLT L16
    ALOAD 4
    ILOAD 6
    AALOAD
    ILOAD 8
    ILOAD 7
    ISUB
    IALOAD
    ICONST_1
    ISUB
    ALOAD 4
    ILOAD 6
    ICONST_1
    ISUB
    AALOAD
    ILOAD 8
    IALOAD
    IF_ICMPGE L17
   L16
    LINENUMBER 17 L16
   FRAME FULL [original/Solution1449 [I I I [[I [[I I I I] []
    ALOAD 4
    ILOAD 6
    AALOAD
    ILOAD 8
    ALOAD 4
    ILOAD 6
    ICONST_1
    ISUB
    AALOAD
    ILOAD 8
    IALOAD
    IASTORE
   L18
    LINENUMBER 18 L18
    ALOAD 5
    ILOAD 6
    AALOAD
    ILOAD 8
    ILOAD 8
    IASTORE
    GOTO L19
   L17
    LINENUMBER 20 L17
   FRAME FULL [original/Solution1449 [I I I [[I [[I I I I] []
    ALOAD 4
    ILOAD 6
    AALOAD
    ILOAD 8
    ALOAD 4
    ILOAD 6
    AALOAD
    ILOAD 8
    ILOAD 7
    ISUB
    IALOAD
    ICONST_1
    IADD
    IASTORE
   L20
    LINENUMBER 21 L20
    ALOAD 5
    ILOAD 6
    AALOAD
    ILOAD 8
    ILOAD 8
    ILOAD 7
    ISUB
    IASTORE
   L19
    LINENUMBER 15 L19
   FRAME FULL [original/Solution1449 [I I I [[I [[I I I I] []
    IINC 8 1
    GOTO L13
   L14
    LINENUMBER 13 L14
   FRAME FULL [original/Solution1449 [I I I [[I [[I I I I] []
    IINC 6 1
    GOTO L9
   L10
    LINENUMBER 25 L10
   FRAME FULL [original/Solution1449 [I I I [[I [[I I I I] []
    ALOAD 4
    BIPUSH 9
    AALOAD
    ILOAD 2
    IALOAD
    IFGE L21
   L22
    LINENUMBER 26 L22
    LDC "0"
    ARETURN
   L21
    LINENUMBER 28 L21
   FRAME FULL [original/Solution1449 [I I I [[I [[I I I I] []
    NEW java/lang/StringBuilder
    DUP
    INVOKESPECIAL java/lang/StringBuilder.<init> ()V
    ASTORE 6
   L23
    LINENUMBER 29 L23
    BIPUSH 9
    ISTORE 7
   L24
    ILOAD 2
    ISTORE 8
   L25
   FRAME FULL [original/Solution1449 [I I I [[I [[I java/lang/StringBuilder I I] []
    ILOAD 7
    IFLE L26
   L27
    LINENUMBER 30 L27
    ILOAD 8
    ALOAD 5
    ILOAD 7
    AALOAD
    ILOAD 8
    IALOAD
    IF_ICMPNE L28
   L29
    LINENUMBER 31 L29
    IINC 7 -1
    GOTO L25
   L28
    LINENUMBER 33 L28
   FRAME FULL [original/Solution1449 [I I I [[I [[I java/lang/StringBuilder I I] []
    ALOAD 6
    ILOAD 7
    INVOKEVIRTUAL java/lang/StringBuilder.append (I)Ljava/lang/StringBuilder;
    POP
   L30
    LINENUMBER 34 L30
    ALOAD 5
    ILOAD 7
    AALOAD
    ILOAD 8
    IALOAD
    ISTORE 8
    GOTO L25
   L26
    LINENUMBER 37 L26
   FRAME FULL [original/Solution1449 [I I I [[I [[I java/lang/StringBuilder I I] []
    ALOAD 6
    INVOKEVIRTUAL java/lang/StringBuilder.toString ()Ljava/lang/String;
    ARETURN
   L31
    LOCALVARIABLE e [I L6 L7 9
    LOCALVARIABLE j I L13 L14 8
    LOCALVARIABLE c I L12 L14 7
    LOCALVARIABLE i I L9 L10 6
    LOCALVARIABLE i I L24 L26 7
    LOCALVARIABLE j I L25 L26 8
    LOCALVARIABLE this Loriginal/Solution1449; L0 L31 0
    LOCALVARIABLE cost [I L0 L31 1
    LOCALVARIABLE target I L0 L31 2
    LOCALVARIABLE inf I L1 L31 3
    LOCALVARIABLE f [[I L2 L31 4
    LOCALVARIABLE g [[I L3 L31 5
    LOCALVARIABLE sb Ljava/lang/StringBuilder; L23 L31 6
    MAXSTACK = 5
    MAXLOCALS = 10
}

