// class version 55.0 (55)
// access flags 0x20
class original/SumSquares1 {

  // compiled from: id_142.java

  // access flags 0x0
  <init>()V
   L0
    LINENUMBER 8 L0
    ALOAD 0
    INVOKESPECIAL java/lang/Object.<init> ()V
    RETURN
   L1
    LOCALVARIABLE this Loriginal/SumSquares1; L0 L1 0
    MAXSTACK = 1
    MAXLOCALS = 1

  // access flags 0x9
  // signature (Ljava/util/List<Ljava/lang/Object;>;)I
  // declaration: int sumSquares(java.util.List<java.lang.Object>)
  public static sumSquares(Ljava/util/List;)I
   L0
    LINENUMBER 44 L0
    NEW java/util/ArrayList
    DUP
    INVOKESPECIAL java/util/ArrayList.<init> ()V
    ASTORE 1
   L1
    LINENUMBER 45 L1
    ICONST_0
    ISTORE 2
   L2
   FRAME FULL [java/util/List java/util/ArrayList I] []
    ILOAD 2
    ALOAD 0
    INVOKEINTERFACE java/util/List.size ()I (itf)
    IF_ICMPGE L3
   L4
    LINENUMBER 46 L4
    ILOAD 2
    ICONST_3
    IREM
    IFNE L5
   L6
    LINENUMBER 47 L6
    ALOAD 1
    ALOAD 0
    ILOAD 2
    INVOKEINTERFACE java/util/List.get (I)Ljava/lang/Object; (itf)
    CHECKCAST java/lang/Integer
    INVOKEVIRTUAL java/lang/Integer.intValue ()I
    ALOAD 0
    ILOAD 2
    INVOKEINTERFACE java/util/List.get (I)Ljava/lang/Object; (itf)
    CHECKCAST java/lang/Integer
    INVOKEVIRTUAL java/lang/Integer.intValue ()I
    IDIV
    INVOKESTATIC java/lang/Integer.valueOf (I)Ljava/lang/Integer;
    INVOKEINTERFACE java/util/List.add (Ljava/lang/Object;)Z (itf)
    POP
    GOTO L7
   L5
    LINENUMBER 48 L5
   FRAME FULL [java/util/List java/util/ArrayList I] []
    ILOAD 2
    ICONST_4
    IREM
    IFNE L8
    ILOAD 2
    ICONST_3
    IREM
    IFEQ L8
   L9
    LINENUMBER 49 L9
    ALOAD 1
    ALOAD 0
    ILOAD 2
    INVOKEINTERFACE java/util/List.get (I)Ljava/lang/Object; (itf)
    CHECKCAST java/lang/Integer
    INVOKEVIRTUAL java/lang/Integer.intValue ()I
    ALOAD 0
    ILOAD 2
    INVOKEINTERFACE java/util/List.get (I)Ljava/lang/Object; (itf)
    CHECKCAST java/lang/Integer
    INVOKEVIRTUAL java/lang/Integer.intValue ()I
    IMUL
    ALOAD 0
    ILOAD 2
    INVOKEINTERFACE java/util/List.get (I)Ljava/lang/Object; (itf)
    CHECKCAST java/lang/Integer
    INVOKEVIRTUAL java/lang/Integer.intValue ()I
    IMUL
    INVOKESTATIC java/lang/Integer.valueOf (I)Ljava/lang/Integer;
    INVOKEINTERFACE java/util/List.add (Ljava/lang/Object;)Z (itf)
    POP
    GOTO L7
   L8
    LINENUMBER 51 L8
   FRAME FULL [java/util/List java/util/ArrayList I] []
    ALOAD 1
    ALOAD 0
    ILOAD 2
    INVOKEINTERFACE java/util/List.get (I)Ljava/lang/Object; (itf)
    CHECKCAST java/lang/Integer
    INVOKEVIRTUAL java/lang/Integer.intValue ()I
    INVOKESTATIC java/lang/Integer.valueOf (I)Ljava/lang/Integer;
    INVOKEINTERFACE java/util/List.add (Ljava/lang/Object;)Z (itf)
    POP
   L7
    LINENUMBER 45 L7
   FRAME FULL [java/util/List java/util/ArrayList I] []
    IINC 2 1
    GOTO L2
   L3
    LINENUMBER 54 L3
   FRAME FULL [java/util/List java/util/ArrayList I] []
    ICONST_0
    ISTORE 2
   L10
    LINENUMBER 55 L10
    ICONST_0
    ISTORE 3
   L11
   FRAME FULL [java/util/List java/util/ArrayList I I] []
    ILOAD 3
    ALOAD 1
    INVOKEINTERFACE java/util/List.size ()I (itf)
    IF_ICMPGE L12
   L13
    LINENUMBER 56 L13
    ILOAD 2
    ALOAD 1
    ILOAD 3
    INVOKEINTERFACE java/util/List.get (I)Ljava/lang/Object; (itf)
    CHECKCAST java/lang/Integer
    INVOKEVIRTUAL java/lang/Integer.intValue ()I
    IADD
    ISTORE 2
   L14
    LINENUMBER 55 L14
    IINC 3 1
    GOTO L11
   L12
    LINENUMBER 58 L12
   FRAME FULL [java/util/List java/util/ArrayList I I] []
    ILOAD 2
    IRETURN
   L15
    LOCALVARIABLE i I L2 L3 2
    LOCALVARIABLE i I L11 L12 3
    LOCALVARIABLE lst Ljava/util/List; L0 L15 0
    // signature Ljava/util/List<Ljava/lang/Object;>;
    // declaration: lst extends java.util.List<java.lang.Object>
    LOCALVARIABLE result Ljava/util/List; L1 L15 1
    // signature Ljava/util/List<Ljava/lang/Integer;>;
    // declaration: result extends java.util.List<java.lang.Integer>
    LOCALVARIABLE sum I L10 L15 2
    MAXSTACK = 4
    MAXLOCALS = 4
}

