// class version 55.0 (55)
// access flags 0x20
class original/Solution3219 {

  // compiled from: id_3219.java

  // access flags 0x0
  <init>()V
   L0
    LINENUMBER 4 L0
    ALOAD 0
    INVOKESPECIAL java/lang/Object.<init> ()V
    RETURN
   L1
    LOCALVARIABLE this Loriginal/Solution3219; L0 L1 0
    MAXSTACK = 1
    MAXLOCALS = 1

  // access flags 0x1
  public minimumCost(II[I[I)J
   L0
    LINENUMBER 6 L0
    ALOAD 3
    INVOKESTATIC java/util/Arrays.sort ([I)V
   L1
    LINENUMBER 7 L1
    ALOAD 4
    INVOKESTATIC java/util/Arrays.sort ([I)V
   L2
    LINENUMBER 8 L2
    LCONST_0
    LSTORE 5
   L3
    LINENUMBER 9 L3
    ILOAD 1
    ICONST_2
    ISUB
    ISTORE 7
   L4
    ILOAD 2
    ICONST_2
    ISUB
    ISTORE 8
   L5
    LINENUMBER 10 L5
    ICONST_1
    ISTORE 9
   L6
    ICONST_1
    ISTORE 10
   L7
    LINENUMBER 11 L7
   FRAME FULL [original/Solution3219 I I [I [I J I I I I] []
    ILOAD 7
    IFGE L8
    ILOAD 8
    IFLT L9
   L8
    LINENUMBER 12 L8
   FRAME FULL [original/Solution3219 I I [I [I J I I I I] []
    ILOAD 8
    IFGE L10
    ILOAD 7
    IFLT L11
    ALOAD 3
    ILOAD 7
    IALOAD
    ALOAD 4
    ILOAD 8
    IALOAD
    IF_ICMPLE L11
   L10
    LINENUMBER 13 L10
   FRAME FULL [original/Solution3219 I I [I [I J I I I I] []
    LLOAD 5
    LCONST_1
    ALOAD 3
    ILOAD 7
    IINC 7 -1
    IALOAD
    I2L
    LMUL
    ILOAD 10
    I2L
    LMUL
    LADD
    LSTORE 5
   L12
    LINENUMBER 14 L12
    IINC 9 1
    GOTO L7
   L11
    LINENUMBER 16 L11
   FRAME FULL [original/Solution3219 I I [I [I J I I I I] []
    LLOAD 5
    LCONST_1
    ALOAD 4
    ILOAD 8
    IINC 8 -1
    IALOAD
    I2L
    LMUL
    ILOAD 9
    I2L
    LMUL
    LADD
    LSTORE 5
   L13
    LINENUMBER 17 L13
    IINC 10 1
    GOTO L7
   L9
    LINENUMBER 20 L9
   FRAME FULL [original/Solution3219 I I [I [I J I I I I] []
    LLOAD 5
    LRETURN
   L14
    LOCALVARIABLE this Loriginal/Solution3219; L0 L14 0
    LOCALVARIABLE m I L0 L14 1
    LOCALVARIABLE n I L0 L14 2
    LOCALVARIABLE horizontalCut [I L0 L14 3
    LOCALVARIABLE verticalCut [I L0 L14 4
    LOCALVARIABLE ans J L3 L14 5
    LOCALVARIABLE i I L4 L14 7
    LOCALVARIABLE j I L5 L14 8
    LOCALVARIABLE h I L6 L14 9
    LOCALVARIABLE v I L7 L14 10
    MAXSTACK = 6
    MAXLOCALS = 11
}

