// class version 55.0 (55)
// access flags 0x20
class original/HowManyTimes {

  // compiled from: id_18.java

  // access flags 0x0
  <init>()V
   L0
    LINENUMBER 4 L0
    ALOAD 0
    INVOKESPECIAL java/lang/Object.<init> ()V
    RETURN
   L1
    LOCALVARIABLE this Loriginal/HowManyTimes; L0 L1 0
    MAXSTACK = 1
    MAXLOCALS = 1

  // access flags 0x9
  public static howManyTimes(Ljava/lang/String;Ljava/lang/String;)I
   L0
    LINENUMBER 24 L0
    ICONST_0
    ISTORE 2
   L1
    LINENUMBER 25 L1
    ICONST_0
    ISTORE 3
   L2
    LINENUMBER 26 L2
   FRAME FULL [java/lang/String java/lang/String I I] []
    ILOAD 3
    ALOAD 0
    INVOKEVIRTUAL java/lang/String.length ()I
    IF_ICMPLT L3
   L4
    LINENUMBER 27 L4
    ALOAD 0
    ALOAD 1
    ILOAD 3
    INVOKEVIRTUAL java/lang/String.indexOf (Ljava/lang/String;I)I
    ISTORE 3
   L5
    LINENUMBER 28 L5
    ILOAD 3
    ICONST_M1
    IF_ICMPNE L6
   L7
    LINENUMBER 29 L7
    GOTO L3
   L6
    LINENUMBER 31 L6
   FRAME FULL [java/lang/String java/lang/String I I] []
    IINC 2 1
   L8
    LINENUMBER 32 L8
    IINC 3 1
    GOTO L2
   L3
    LINENUMBER 34 L3
   FRAME FULL [java/lang/String java/lang/String I I] []
    ILOAD 2
    IRETURN
   L9
    LOCALVARIABLE string Ljava/lang/String; L0 L9 0
    LOCALVARIABLE substring Ljava/lang/String; L0 L9 1
    LOCALVARIABLE count I L1 L9 2
    LOCALVARIABLE index I L2 L9 3
    MAXSTACK = 3
    MAXLOCALS = 4
}

