// class version 55.0 (55)
// access flags 0x20
class original/Solution1436 {

  // compiled from: id_1436.java

  // access flags 0x0
  <init>()V
   L0
    LINENUMBER 6 L0
    ALOAD 0
    INVOKESPECIAL java/lang/Object.<init> ()V
    RETURN
   L1
    LOCALVARIABLE this Loriginal/Solution1436; L0 L1 0
    MAXSTACK = 1
    MAXLOCALS = 1

  // access flags 0x1
  // signature (Ljava/util/List<Ljava/util/List<Ljava/lang/String;>;>;)Ljava/lang/String;
  // declaration: java.lang.String destCity(java.util.List<java.util.List<java.lang.String>>)
  public destCity(Ljava/util/List;)Ljava/lang/String;
   L0
    LINENUMBER 8 L0
    NEW java/util/HashSet
    DUP
    INVOKESPECIAL java/util/HashSet.<init> ()V
    ASTORE 2
   L1
    LINENUMBER 9 L1
    ALOAD 1
    INVOKEINTERFACE java/util/List.iterator ()Ljava/util/Iterator; (itf)
    ASTORE 3
   L2
   FRAME FULL [original/Solution1436 java/util/List java/util/HashSet java/util/Iterator] []
    ALOAD 3
    INVOKEINTERFACE java/util/Iterator.hasNext ()Z (itf)
    IFEQ L3
    ALOAD 3
    INVOKEINTERFACE java/util/Iterator.next ()Ljava/lang/Object; (itf)
    CHECKCAST java/util/List
    ASTORE 4
   L4
    LINENUMBER 10 L4
    ALOAD 2
    ALOAD 4
    ICONST_0
    INVOKEINTERFACE java/util/List.get (I)Ljava/lang/Object; (itf)
    CHECKCAST java/lang/String
    INVOKEINTERFACE java/util/Set.add (Ljava/lang/Object;)Z (itf)
    POP
   L5
    LINENUMBER 11 L5
    GOTO L2
   L3
    LINENUMBER 12 L3
   FRAME FULL [original/Solution1436 java/util/List java/util/HashSet java/util/Iterator] []
    ICONST_0
    ISTORE 3
   L6
    LINENUMBER 13 L6
   FRAME FULL [original/Solution1436 java/util/List java/util/HashSet I] []
    ALOAD 1
    ILOAD 3
    INVOKEINTERFACE java/util/List.get (I)Ljava/lang/Object; (itf)
    CHECKCAST java/util/List
    ICONST_1
    INVOKEINTERFACE java/util/List.get (I)Ljava/lang/Object; (itf)
    CHECKCAST java/lang/String
    ASTORE 4
   L7
    LINENUMBER 14 L7
    ALOAD 2
    ALOAD 4
    INVOKEINTERFACE java/util/Set.contains (Ljava/lang/Object;)Z (itf)
    IFNE L8
   L9
    LINENUMBER 15 L9
    ALOAD 4
    POP
    LDC ""
    ARETURN
   L8
    LINENUMBER 12 L8
   FRAME FULL [original/Solution1436 java/util/List java/util/HashSet I java/lang/String] []
    IINC 3 1
    GOTO L6
   L10
    LOCALVARIABLE p Ljava/util/List; L4 L5 4
    // signature Ljava/util/List<Ljava/lang/String;>;
    // declaration: p extends java.util.List<java.lang.String>
    LOCALVARIABLE b Ljava/lang/String; L7 L8 4
    LOCALVARIABLE i I L6 L10 3
    LOCALVARIABLE this Loriginal/Solution1436; L0 L10 0
    LOCALVARIABLE paths Ljava/util/List; L0 L10 1
    // signature Ljava/util/List<Ljava/util/List<Ljava/lang/String;>;>;
    // declaration: paths extends java.util.List<java.util.List<java.lang.String>>
    LOCALVARIABLE s Ljava/util/Set; L1 L10 2
    // signature Ljava/util/Set<Ljava/lang/String;>;
    // declaration: s extends java.util.Set<java.lang.String>
    MAXSTACK = 3
    MAXLOCALS = 5
}

