// class version 55.0 (55)
// access flags 0x20
class original/Solution1102 {

  // compiled from: id_1102.java
  // access flags 0x19
  public final static INNERCLASS java/lang/invoke/MethodHandles$Lookup java/lang/invoke/MethodHandles Lookup

  // access flags 0x2
  private [I p

  // access flags 0x0
  <init>()V
   L0
    LINENUMBER 5 L0
    ALOAD 0
    INVOKESPECIAL java/lang/Object.<init> ()V
    RETURN
   L1
    LOCALVARIABLE this Loriginal/Solution1102; L0 L1 0
    MAXSTACK = 1
    MAXLOCALS = 1

  // access flags 0x1
  public maximumMinimumPath([[I)I
   L0
    LINENUMBER 9 L0
    ALOAD 1
    ARRAYLENGTH
    ISTORE 2
   L1
    ALOAD 1
    ICONST_0
    AALOAD
    ARRAYLENGTH
    ISTORE 3
   L2
    LINENUMBER 10 L2
    ALOAD 0
    ILOAD 2
    ILOAD 3
    IMUL
    NEWARRAY T_INT
    PUTFIELD original/Solution1102.p : [I
   L3
    LINENUMBER 11 L3
    NEW java/util/ArrayList
    DUP
    INVOKESPECIAL java/util/ArrayList.<init> ()V
    ASTORE 4
   L4
    LINENUMBER 12 L4
    ICONST_0
    ISTORE 5
   L5
   FRAME FULL [original/Solution1102 [[I I I java/util/ArrayList I] []
    ILOAD 5
    ILOAD 2
    IF_ICMPGE L6
   L7
    LINENUMBER 13 L7
    ICONST_0
    ISTORE 6
   L8
   FRAME FULL [original/Solution1102 [[I I I java/util/ArrayList I I] []
    ILOAD 6
    ILOAD 3
    IF_ICMPGE L9
   L10
    LINENUMBER 14 L10
    ALOAD 4
    ICONST_3
    NEWARRAY T_INT
    DUP
    ICONST_0
    ALOAD 1
    ILOAD 5
    AALOAD
    ILOAD 6
    IALOAD
    IASTORE
    DUP
    ICONST_1
    ILOAD 5
    IASTORE
    DUP
    ICONST_2
    ILOAD 6
    IASTORE
    INVOKEINTERFACE java/util/List.add (Ljava/lang/Object;)Z (itf)
    POP
   L11
    LINENUMBER 15 L11
    ALOAD 0
    GETFIELD original/Solution1102.p : [I
    ILOAD 5
    ILOAD 3
    IMUL
    ILOAD 6
    IADD
    ILOAD 5
    ILOAD 3
    IMUL
    ILOAD 6
    IADD
    IASTORE
   L12
    LINENUMBER 13 L12
    IINC 6 1
    GOTO L8
   L9
    LINENUMBER 12 L9
   FRAME FULL [original/Solution1102 [[I I I java/util/ArrayList I I] []
    IINC 5 1
    GOTO L5
   L6
    LINENUMBER 18 L6
   FRAME FULL [original/Solution1102 [[I I I java/util/ArrayList I] []
    ALOAD 4
    INVOKEDYNAMIC compare()Ljava/util/Comparator; [
      // handle kind 0x6 : INVOKESTATIC
      java/lang/invoke/LambdaMetafactory.metafactory(Ljava/lang/invoke/MethodHandles$Lookup;Ljava/lang/String;Ljava/lang/invoke/MethodType;Ljava/lang/invoke/MethodType;Ljava/lang/invoke/MethodHandle;Ljava/lang/invoke/MethodType;)Ljava/lang/invoke/CallSite;
      // arguments:
      (Ljava/lang/Object;Ljava/lang/Object;)I, 
      // handle kind 0x6 : INVOKESTATIC
      original/Solution1102.lambda$maximumMinimumPath$0([I[I)I, 
      ([I[I)I
    ]
    INVOKEINTERFACE java/util/List.sort (Ljava/util/Comparator;)V (itf)
   L13
    LINENUMBER 19 L13
    ILOAD 2
    ILOAD 3
    MULTIANEWARRAY [[Z 2
    ASTORE 5
   L14
    LINENUMBER 20 L14
    ICONST_5
    NEWARRAY T_INT
    DUP
    ICONST_0
    ICONST_M1
    IASTORE
    DUP
    ICONST_1
    ICONST_0
    IASTORE
    DUP
    ICONST_2
    ICONST_1
    IASTORE
    DUP
    ICONST_3
    ICONST_0
    IASTORE
    DUP
    ICONST_4
    ICONST_M1
    IASTORE
    ASTORE 6
   L15
    LINENUMBER 21 L15
    ICONST_0
    ISTORE 7
   L16
    LINENUMBER 22 L16
    ICONST_0
    ISTORE 8
   L17
   FRAME FULL [original/Solution1102 [[I I I java/util/ArrayList [[Z [I I I] []
    ALOAD 0
    ICONST_0
    INVOKEVIRTUAL original/Solution1102.find (I)I
    ALOAD 0
    ILOAD 2
    ILOAD 3
    IMUL
    ICONST_1
    ISUB
    INVOKEVIRTUAL original/Solution1102.find (I)I
    IF_ICMPEQ L18
   L19
    LINENUMBER 23 L19
    ALOAD 4
    ILOAD 8
    INVOKEINTERFACE java/util/List.get (I)Ljava/lang/Object; (itf)
    CHECKCAST [I
    ASTORE 9
   L20
    LINENUMBER 24 L20
    ALOAD 5
    ALOAD 9
    ICONST_1
    IALOAD
    AALOAD
    ALOAD 9
    ICONST_2
    IALOAD
    ICONST_1
    BASTORE
   L21
    LINENUMBER 25 L21
    ALOAD 9
    ICONST_0
    IALOAD
    ISTORE 7
   L22
    LINENUMBER 26 L22
    ICONST_0
    ISTORE 10
   L23
   FRAME FULL [original/Solution1102 [[I I I java/util/ArrayList [[Z [I I I [I I] []
    ILOAD 10
    ICONST_4
    IF_ICMPGE L24
   L25
    LINENUMBER 27 L25
    ALOAD 9
    ICONST_1
    IALOAD
    ALOAD 6
    ILOAD 10
    IALOAD
    IADD
    ISTORE 11
   L26
    ALOAD 9
    ICONST_2
    IALOAD
    ALOAD 6
    ILOAD 10
    ICONST_1
    IADD
    IALOAD
    IADD
    ISTORE 12
   L27
    LINENUMBER 28 L27
    ILOAD 11
    IFLT L28
    ILOAD 11
    ILOAD 2
    IF_ICMPGE L28
    ILOAD 12
    IFLT L28
    ILOAD 12
    ILOAD 3
    IF_ICMPGE L28
    ALOAD 5
    ILOAD 11
    AALOAD
    ILOAD 12
    BALOAD
    IFEQ L28
   L29
    LINENUMBER 29 L29
    ALOAD 0
    GETFIELD original/Solution1102.p : [I
    ALOAD 0
    ILOAD 11
    ILOAD 3
    IMUL
    ILOAD 12
    IADD
    INVOKEVIRTUAL original/Solution1102.find (I)I
    ALOAD 0
    ALOAD 9
    ICONST_1
    IALOAD
    ILOAD 3
    IDIV
    ALOAD 9
    ICONST_2
    IALOAD
    IADD
    INVOKEVIRTUAL original/Solution1102.find (I)I
    IASTORE
   L28
    LINENUMBER 26 L28
   FRAME FULL [original/Solution1102 [[I I I java/util/ArrayList [[Z [I I I [I I I I] []
    IINC 10 1
    GOTO L23
   L24
    LINENUMBER 22 L24
   FRAME FULL [original/Solution1102 [[I I I java/util/ArrayList [[Z [I I I [I I] []
    IINC 8 1
    GOTO L17
   L18
    LINENUMBER 33 L18
   FRAME FULL [original/Solution1102 [[I I I java/util/ArrayList [[Z [I I I] []
    ILOAD 7
    IRETURN
   L30
    LOCALVARIABLE j I L8 L9 6
    LOCALVARIABLE i I L5 L6 5
    LOCALVARIABLE x I L26 L28 11
    LOCALVARIABLE y I L27 L28 12
    LOCALVARIABLE k I L23 L24 10
    LOCALVARIABLE t [I L20 L24 9
    LOCALVARIABLE i I L17 L18 8
    LOCALVARIABLE this Loriginal/Solution1102; L0 L30 0
    LOCALVARIABLE grid [[I L0 L30 1
    LOCALVARIABLE m I L1 L30 2
    LOCALVARIABLE n I L2 L30 3
    LOCALVARIABLE q Ljava/util/List; L4 L30 4
    // signature Ljava/util/List<[I>;
    // declaration: q extends java.util.List<int[]>
    LOCALVARIABLE vis [[Z L14 L30 5
    LOCALVARIABLE dirs [I L15 L30 6
    LOCALVARIABLE ans I L16 L30 7
    MAXSTACK = 6
    MAXLOCALS = 13

  // access flags 0x2
  private find(I)I
   L0
    LINENUMBER 37 L0
    ALOAD 0
    GETFIELD original/Solution1102.p : [I
    ILOAD 1
    IALOAD
    ILOAD 1
    IF_ICMPEQ L1
   L2
    LINENUMBER 38 L2
    ALOAD 0
    GETFIELD original/Solution1102.p : [I
    ILOAD 1
    ALOAD 0
    ALOAD 0
    GETFIELD original/Solution1102.p : [I
    ILOAD 1
    IALOAD
    INVOKEVIRTUAL original/Solution1102.find (I)I
    IASTORE
   L1
    LINENUMBER 40 L1
   FRAME FULL [original/Solution1102 I] []
    ALOAD 0
    GETFIELD original/Solution1102.p : [I
    ILOAD 1
    IALOAD
    IRETURN
   L3
    LOCALVARIABLE this Loriginal/Solution1102; L0 L3 0
    LOCALVARIABLE x I L0 L3 1
    MAXSTACK = 5
    MAXLOCALS = 2

  // access flags 0x100A
  private static synthetic lambda$maximumMinimumPath$0([I[I)I
   L0
    LINENUMBER 18 L0
    ALOAD 1
    ICONST_0
    IALOAD
    ALOAD 0
    ICONST_0
    IALOAD
    ISUB
    IRETURN
   L1
    LOCALVARIABLE a [I L0 L1 0
    LOCALVARIABLE b [I L0 L1 1
    MAXSTACK = 3
    MAXLOCALS = 2
}

