// class version 55.0 (55)
// access flags 0x20
class original/Solution2557 {

  // compiled from: id_2557.java

  // access flags 0x0
  <init>()V
   L0
    LINENUMBER 8 L0
    ALOAD 0
    INVOKESPECIAL java/lang/Object.<init> ()V
    RETURN
   L1
    LOCALVARIABLE this Loriginal/Solution2557; L0 L1 0
    MAXSTACK = 1
    MAXLOCALS = 1

  // access flags 0x1
  public maxCount([IIJ)I
   L0
    LINENUMBER 10 L0
    NEW java/util/HashSet
    DUP
    INVOKESPECIAL java/util/HashSet.<init> ()V
    ASTORE 5
   L1
    LINENUMBER 11 L1
    ALOAD 5
    ICONST_0
    INVOKESTATIC java/lang/Integer.valueOf (I)Ljava/lang/Integer;
    INVOKEINTERFACE java/util/Set.add (Ljava/lang/Object;)Z (itf)
    POP
   L2
    LINENUMBER 12 L2
    ALOAD 5
    ILOAD 2
    ICONST_1
    ISUB
    INVOKESTATIC java/lang/Integer.valueOf (I)Ljava/lang/Integer;
    INVOKEINTERFACE java/util/Set.add (Ljava/lang/Object;)Z (itf)
    POP
   L3
    LINENUMBER 13 L3
    ALOAD 1
    ASTORE 6
    ALOAD 6
    ARRAYLENGTH
    ISTORE 7
    ICONST_0
    ISTORE 8
   L4
   FRAME FULL [original/Solution2557 [I I J java/util/HashSet [I I I] []
    ILOAD 8
    ILOAD 7
    IF_ICMPGE L5
    ALOAD 6
    ILOAD 8
    IALOAD
    ISTORE 9
   L6
    LINENUMBER 14 L6
    ALOAD 5
    ILOAD 9
    INVOKESTATIC java/lang/Integer.valueOf (I)Ljava/lang/Integer;
    INVOKEINTERFACE java/util/Set.add (Ljava/lang/Object;)Z (itf)
    POP
   L7
    LINENUMBER 13 L7
    IINC 8 1
    GOTO L4
   L5
    LINENUMBER 16 L5
   FRAME FULL [original/Solution2557 [I I J java/util/HashSet [I I I] []
    NEW java/util/ArrayList
    DUP
    ALOAD 5
    INVOKESPECIAL java/util/ArrayList.<init> (Ljava/util/Collection;)V
    ASTORE 6
   L8
    LINENUMBER 17 L8
    ALOAD 6
    INVOKESTATIC java/util/Collections.sort (Ljava/util/List;)V
   L9
    LINENUMBER 18 L9
    ICONST_0
    ISTORE 7
   L10
    LINENUMBER 19 L10
    ICONST_1
    ISTORE 8
   L11
   FRAME FULL [original/Solution2557 [I I J java/util/HashSet java/util/ArrayList I I] []
    ILOAD 8
    ALOAD 6
    INVOKEINTERFACE java/util/List.size ()I (itf)
    IF_ICMPGE L12
   L13
    LINENUMBER 20 L13
    ALOAD 6
    ILOAD 8
    ICONST_1
    ISUB
    INVOKEINTERFACE java/util/List.get (I)Ljava/lang/Object; (itf)
    CHECKCAST java/lang/Integer
    INVOKEVIRTUAL java/lang/Integer.intValue ()I
    ISTORE 9
   L14
    ALOAD 6
    ILOAD 8
    INVOKEINTERFACE java/util/List.get (I)Ljava/lang/Object; (itf)
    CHECKCAST java/lang/Integer
    INVOKEVIRTUAL java/lang/Integer.intValue ()I
    ISTORE 10
   L15
    LINENUMBER 21 L15
    ICONST_0
    ISTORE 11
   L16
    ILOAD 10
    ILOAD 9
    ISUB
    ICONST_1
    ISUB
    ISTORE 12
   L17
    LINENUMBER 22 L17
   FRAME FULL [original/Solution2557 [I I J java/util/HashSet java/util/ArrayList I I I I I I] []
    ILOAD 11
    ILOAD 12
    IF_ICMPGE L18
   L19
    LINENUMBER 23 L19
    ILOAD 11
    ILOAD 12
    IADD
    ICONST_1
    IADD
    ICONST_1
    IUSHR
    ISTORE 13
   L20
    LINENUMBER 24 L20
    ILOAD 9
    ICONST_1
    IADD
    ILOAD 9
    IADD
    ILOAD 13
    IADD
    I2L
    LCONST_1
    LMUL
    ILOAD 13
    I2L
    LMUL
    LDC 2L
    LDIV
    LLOAD 3
    LCMP
    IFGT L21
   L22
    LINENUMBER 25 L22
    ILOAD 13
    ISTORE 11
    GOTO L23
   L21
    LINENUMBER 27 L21
   FRAME FULL [original/Solution2557 [I I J java/util/HashSet java/util/ArrayList I I I I I I I] []
    ILOAD 13
    ICONST_1
    ISUB
    ISTORE 12
   L23
    LINENUMBER 29 L23
   FRAME FULL [original/Solution2557 [I I J java/util/HashSet java/util/ArrayList I I I I I I I] []
    GOTO L17
   L18
    LINENUMBER 30 L18
   FRAME FULL [original/Solution2557 [I I J java/util/HashSet java/util/ArrayList I I I I I I] []
    ILOAD 7
    ILOAD 11
    IADD
    ISTORE 7
   L24
    LINENUMBER 31 L24
    LLOAD 3
    ILOAD 9
    ICONST_1
    IADD
    ILOAD 9
    IADD
    ILOAD 11
    IADD
    I2L
    LCONST_1
    LMUL
    ILOAD 11
    I2L
    LMUL
    LDC 2L
    LDIV
    LSUB
    LSTORE 3
   L25
    LINENUMBER 32 L25
    LLOAD 3
    LCONST_0
    LCMP
    IFGT L26
   L27
    LINENUMBER 33 L27
    GOTO L12
   L26
    LINENUMBER 19 L26
   FRAME FULL [original/Solution2557 [I I J java/util/HashSet java/util/ArrayList I I I I I I] []
    IINC 8 1
    GOTO L11
   L12
    LINENUMBER 36 L12
   FRAME FULL [original/Solution2557 [I I J java/util/HashSet java/util/ArrayList I I] []
    ILOAD 7
    IRETURN
   L28
    LOCALVARIABLE x I L6 L7 9
    LOCALVARIABLE mid I L20 L23 13
    LOCALVARIABLE i I L14 L26 9
    LOCALVARIABLE j I L15 L26 10
    LOCALVARIABLE left I L16 L26 11
    LOCALVARIABLE right I L17 L26 12
    LOCALVARIABLE k I L11 L12 8
    LOCALVARIABLE this Loriginal/Solution2557; L0 L28 0
    LOCALVARIABLE banned [I L0 L28 1
    LOCALVARIABLE n I L0 L28 2
    LOCALVARIABLE maxSum J L0 L28 3
    LOCALVARIABLE black Ljava/util/Set; L1 L28 5
    // signature Ljava/util/Set<Ljava/lang/Integer;>;
    // declaration: black extends java.util.Set<java.lang.Integer>
    LOCALVARIABLE ban Ljava/util/List; L8 L28 6
    // signature Ljava/util/List<Ljava/lang/Integer;>;
    // declaration: ban extends java.util.List<java.lang.Integer>
    LOCALVARIABLE ans I L10 L28 7
    MAXSTACK = 6
    MAXLOCALS = 14
}

