// class version 55.0 (55)
// access flags 0x20
class original/Solution1521 {

  // compiled from: id_1521.java

  // access flags 0x0
  <init>()V
   L0
    LINENUMBER 5 L0
    ALOAD 0
    INVOKESPECIAL java/lang/Object.<init> ()V
    RETURN
   L1
    LOCALVARIABLE this Loriginal/Solution1521; L0 L1 0
    MAXSTACK = 1
    MAXLOCALS = 1

  // access flags 0x1
  public closestToTarget([II)I
   L0
    LINENUMBER 7 L0
    ALOAD 1
    ICONST_0
    IALOAD
    ILOAD 2
    ISUB
    INVOKESTATIC java/lang/Math.abs (I)I
    ISTORE 3
   L1
    LINENUMBER 8 L1
    NEW java/util/HashSet
    DUP
    INVOKESPECIAL java/util/HashSet.<init> ()V
    ASTORE 4
   L2
    LINENUMBER 9 L2
    ALOAD 4
    ALOAD 1
    ICONST_0
    IALOAD
    INVOKESTATIC java/lang/Integer.valueOf (I)Ljava/lang/Integer;
    INVOKEINTERFACE java/util/Set.add (Ljava/lang/Object;)Z (itf)
    POP
   L3
    LINENUMBER 10 L3
    ALOAD 1
    ASTORE 5
    ALOAD 5
    ARRAYLENGTH
    ISTORE 6
    ICONST_0
    ISTORE 7
   L4
   FRAME FULL [original/Solution1521 [I I I java/util/HashSet [I I I] []
    ILOAD 7
    ILOAD 6
    IF_ICMPGE L5
    ALOAD 5
    ILOAD 7
    IALOAD
    ISTORE 8
   L6
    LINENUMBER 11 L6
    NEW java/util/HashSet
    DUP
    INVOKESPECIAL java/util/HashSet.<init> ()V
    ASTORE 9
   L7
    LINENUMBER 12 L7
    ALOAD 4
    INVOKEINTERFACE java/util/Set.iterator ()Ljava/util/Iterator; (itf)
    ASTORE 10
   L8
   FRAME FULL [original/Solution1521 [I I I java/util/HashSet [I I I I java/util/HashSet java/util/Iterator] []
    ALOAD 10
    INVOKEINTERFACE java/util/Iterator.hasNext ()Z (itf)
    IFEQ L9
    ALOAD 10
    INVOKEINTERFACE java/util/Iterator.next ()Ljava/lang/Object; (itf)
    CHECKCAST java/lang/Integer
    INVOKEVIRTUAL java/lang/Integer.intValue ()I
    ISTORE 11
   L10
    LINENUMBER 13 L10
    ALOAD 9
    ILOAD 8
    ILOAD 11
    IAND
    INVOKESTATIC java/lang/Integer.valueOf (I)Ljava/lang/Integer;
    INVOKEINTERFACE java/util/Set.add (Ljava/lang/Object;)Z (itf)
    POP
   L11
    LINENUMBER 14 L11
    GOTO L8
   L9
    LINENUMBER 15 L9
   FRAME FULL [original/Solution1521 [I I I java/util/HashSet [I I I I java/util/HashSet java/util/Iterator] []
    ALOAD 9
    ILOAD 8
    INVOKESTATIC java/lang/Integer.valueOf (I)Ljava/lang/Integer;
    INVOKEINTERFACE java/util/Set.add (Ljava/lang/Object;)Z (itf)
    POP
   L12
    LINENUMBER 16 L12
    ALOAD 9
    INVOKEINTERFACE java/util/Set.iterator ()Ljava/util/Iterator; (itf)
    ASTORE 10
   L13
   FRAME FULL [original/Solution1521 [I I I java/util/HashSet [I I I I java/util/HashSet java/util/Iterator] []
    ALOAD 10
    INVOKEINTERFACE java/util/Iterator.hasNext ()Z (itf)
    IFEQ L14
    ALOAD 10
    INVOKEINTERFACE java/util/Iterator.next ()Ljava/lang/Object; (itf)
    CHECKCAST java/lang/Integer
    INVOKEVIRTUAL java/lang/Integer.intValue ()I
    ISTORE 11
   L15
    LINENUMBER 17 L15
    ILOAD 3
    ILOAD 11
    ILOAD 2
    IADD
    INVOKESTATIC java/lang/Math.abs (I)I
    INVOKESTATIC java/lang/Math.min (II)I
    ISTORE 3
   L16
    LINENUMBER 18 L16
    GOTO L13
   L14
    LINENUMBER 19 L14
   FRAME FULL [original/Solution1521 [I I I java/util/HashSet [I I I I java/util/HashSet java/util/Iterator] []
    ALOAD 9
    ASTORE 4
   L17
    LINENUMBER 10 L17
    IINC 7 1
    GOTO L4
   L5
    LINENUMBER 21 L5
   FRAME FULL [original/Solution1521 [I I I java/util/HashSet [I I I] []
    ILOAD 3
    IRETURN
   L18
    LOCALVARIABLE y I L10 L11 11
    LOCALVARIABLE y I L15 L16 11
    LOCALVARIABLE cur Ljava/util/Set; L7 L17 9
    // signature Ljava/util/Set<Ljava/lang/Integer;>;
    // declaration: cur extends java.util.Set<java.lang.Integer>
    LOCALVARIABLE x I L6 L17 8
    LOCALVARIABLE this Loriginal/Solution1521; L0 L18 0
    LOCALVARIABLE arr [I L0 L18 1
    LOCALVARIABLE target I L0 L18 2
    LOCALVARIABLE ans I L1 L18 3
    LOCALVARIABLE pre Ljava/util/Set; L2 L18 4
    // signature Ljava/util/Set<Ljava/lang/Integer;>;
    // declaration: pre extends java.util.Set<java.lang.Integer>
    MAXSTACK = 3
    MAXLOCALS = 12
}

