// class version 55.0 (55)
// access flags 0x20
class original/Solution0943 {

  // compiled from: id_0943.java

  // access flags 0x0
  <init>()V
   L0
    LINENUMBER 9 L0
    ALOAD 0
    INVOKESPECIAL java/lang/Object.<init> ()V
    RETURN
   L1
    LOCALVARIABLE this Loriginal/Solution0943; L0 L1 0
    MAXSTACK = 1
    MAXLOCALS = 1

  // access flags 0x1
  public shortestSuperstring([Ljava/lang/String;)Ljava/lang/String;
   L0
    LINENUMBER 11 L0
    ALOAD 1
    ARRAYLENGTH
    ISTORE 2
   L1
    LINENUMBER 12 L1
    ILOAD 2
    ILOAD 2
    MULTIANEWARRAY [[I 2
    ASTORE 3
   L2
    LINENUMBER 13 L2
    ICONST_0
    ISTORE 4
   L3
   FRAME FULL [original/Solution0943 [Ljava/lang/String; I [[I I] []
    ILOAD 4
    ILOAD 2
    IF_ICMPLT L4
   L5
    LINENUMBER 14 L5
    ALOAD 1
    ILOAD 4
    AALOAD
    ASTORE 5
   L6
    LINENUMBER 15 L6
    ICONST_0
    ISTORE 6
   L7
   FRAME FULL [original/Solution0943 [Ljava/lang/String; I [[I I java/lang/String I] []
    ILOAD 6
    ILOAD 2
    IF_ICMPGE L8
   L9
    LINENUMBER 16 L9
    ALOAD 1
    ILOAD 6
    AALOAD
    ASTORE 7
   L10
    LINENUMBER 17 L10
    ILOAD 4
    ILOAD 6
    IF_ICMPEQ L11
   L12
    LINENUMBER 18 L12
    ALOAD 5
    INVOKEVIRTUAL java/lang/String.length ()I
    ALOAD 7
    INVOKEVIRTUAL java/lang/String.length ()I
    INVOKESTATIC java/lang/Math.min (II)I
    ISTORE 8
   L13
   FRAME FULL [original/Solution0943 [Ljava/lang/String; I [[I I java/lang/String I java/lang/String I] []
    ILOAD 8
    IFLE L11
   L14
    LINENUMBER 19 L14
    ALOAD 5
    ALOAD 5
    INVOKEVIRTUAL java/lang/String.length ()I
    ILOAD 8
    ISUB
    INVOKEVIRTUAL java/lang/String.substring (I)Ljava/lang/String;
    ALOAD 7
    ICONST_0
    ILOAD 8
    INVOKEVIRTUAL java/lang/String.substring (II)Ljava/lang/String;
    INVOKEVIRTUAL java/lang/String.equals (Ljava/lang/Object;)Z
    IFEQ L15
   L16
    LINENUMBER 20 L16
    ALOAD 3
    ILOAD 4
    AALOAD
    ILOAD 6
    ILOAD 8
    IASTORE
   L17
    LINENUMBER 21 L17
    GOTO L11
   L15
    LINENUMBER 18 L15
   FRAME FULL [original/Solution0943 [Ljava/lang/String; I [[I I java/lang/String I java/lang/String I] []
    IINC 8 -1
    GOTO L13
   L11
    LINENUMBER 15 L11
   FRAME FULL [original/Solution0943 [Ljava/lang/String; I [[I I java/lang/String I java/lang/String] []
    IINC 6 1
    GOTO L7
   L8
    LINENUMBER 13 L8
   FRAME FULL [original/Solution0943 [Ljava/lang/String; I [[I I java/lang/String I] []
    IINC 4 1
    GOTO L3
   L4
    LINENUMBER 27 L4
   FRAME FULL [original/Solution0943 [Ljava/lang/String; I [[I I] []
    ICONST_1
    ILOAD 2
    ISHL
    ILOAD 2
    MULTIANEWARRAY [[I 2
    ASTORE 4
   L18
    LINENUMBER 28 L18
    ICONST_1
    ILOAD 2
    ISHL
    ILOAD 2
    MULTIANEWARRAY [[I 2
    ASTORE 5
   L19
    LINENUMBER 29 L19
    ICONST_0
    ISTORE 6
   L20
   FRAME FULL [original/Solution0943 [Ljava/lang/String; I [[I [[I [[I I] []
    ILOAD 6
    ICONST_1
    ILOAD 2
    ISHL
    IF_ICMPGE L21
   L22
    LINENUMBER 30 L22
    ALOAD 5
    ILOAD 6
    AALOAD
    ICONST_M1
    INVOKESTATIC java/util/Arrays.fill ([II)V
   L23
    LINENUMBER 31 L23
    ICONST_0
    ISTORE 7
   L24
   FRAME FULL [original/Solution0943 [Ljava/lang/String; I [[I [[I [[I I I] []
    ILOAD 7
    ILOAD 2
    IF_ICMPGE L25
   L26
    LINENUMBER 32 L26
    ILOAD 6
    ILOAD 7
    ISHR
    ICONST_1
    IAND
    ICONST_1
    IF_ICMPNE L27
   L28
    LINENUMBER 33 L28
    ILOAD 6
    ICONST_1
    ILOAD 7
    ISHL
    IXOR
    ISTORE 8
   L29
    LINENUMBER 34 L29
    ICONST_0
    ISTORE 9
   L30
   FRAME FULL [original/Solution0943 [Ljava/lang/String; I [[I [[I [[I I I I I] []
    ILOAD 9
    ILOAD 2
    IF_ICMPGE L27
   L31
    LINENUMBER 35 L31
    ILOAD 8
    ILOAD 9
    ISHR
    ICONST_1
    IAND
    ICONST_1
    IF_ICMPNE L32
   L33
    LINENUMBER 36 L33
    ALOAD 4
    ILOAD 8
    AALOAD
    ILOAD 9
    IALOAD
    ALOAD 3
    ILOAD 9
    AALOAD
    ILOAD 7
    IALOAD
    IADD
    ISTORE 10
   L34
    LINENUMBER 37 L34
    ILOAD 10
    ALOAD 4
    ILOAD 6
    AALOAD
    ILOAD 7
    IALOAD
    IF_ICMPLE L32
   L35
    LINENUMBER 38 L35
    ALOAD 4
    ILOAD 6
    AALOAD
    ILOAD 7
    ILOAD 10
    IASTORE
   L36
    LINENUMBER 39 L36
    ALOAD 5
    ILOAD 6
    AALOAD
    ILOAD 7
    ILOAD 9
    IASTORE
   L32
    LINENUMBER 34 L32
   FRAME FULL [original/Solution0943 [Ljava/lang/String; I [[I [[I [[I I I I I] []
    IINC 9 1
    GOTO L30
   L27
    LINENUMBER 31 L27
   FRAME FULL [original/Solution0943 [Ljava/lang/String; I [[I [[I [[I I I] []
    IINC 7 1
    GOTO L24
   L25
    LINENUMBER 29 L25
   FRAME FULL [original/Solution0943 [Ljava/lang/String; I [[I [[I [[I I I] []
    IINC 6 1
    GOTO L20
   L21
    LINENUMBER 46 L21
   FRAME FULL [original/Solution0943 [Ljava/lang/String; I [[I [[I [[I I] []
    ICONST_0
    ISTORE 6
   L37
    LINENUMBER 47 L37
    ICONST_0
    ISTORE 7
   L38
   FRAME FULL [original/Solution0943 [Ljava/lang/String; I [[I [[I [[I I I] []
    ILOAD 7
    ILOAD 2
    IF_ICMPGE L39
   L40
    LINENUMBER 48 L40
    ALOAD 4
    ICONST_1
    ILOAD 2
    ISHL
    ICONST_1
    ISUB
    AALOAD
    ILOAD 7
    IALOAD
    ALOAD 4
    ICONST_1
    ILOAD 2
    ISHL
    ICONST_1
    ISUB
    AALOAD
    ILOAD 6
    IALOAD
    IF_ICMPLE L41
   L42
    LINENUMBER 49 L42
    ILOAD 7
    ISTORE 6
   L41
    LINENUMBER 47 L41
   FRAME FULL [original/Solution0943 [Ljava/lang/String; I [[I [[I [[I I I] []
    IINC 7 1
    GOTO L38
   L39
    LINENUMBER 52 L39
   FRAME FULL [original/Solution0943 [Ljava/lang/String; I [[I [[I [[I I I] []
    NEW java/util/ArrayList
    DUP
    INVOKESPECIAL java/util/ArrayList.<init> ()V
    ASTORE 7
   L43
    LINENUMBER 53 L43
    ALOAD 7
    ILOAD 6
    INVOKESTATIC java/lang/Integer.valueOf (I)Ljava/lang/Integer;
    INVOKEINTERFACE java/util/List.add (Ljava/lang/Object;)Z (itf)
    POP
   L44
    LINENUMBER 54 L44
    ICONST_1
    ILOAD 2
    ISHL
    ICONST_1
    ISUB
    ISTORE 8
   L45
   FRAME FULL [original/Solution0943 [Ljava/lang/String; I [[I [[I [[I I java/util/ArrayList I] []
    ALOAD 5
    ILOAD 8
    AALOAD
    ILOAD 6
    IALOAD
    ICONST_M1
    IF_ICMPEQ L46
   L47
    LINENUMBER 55 L47
    ILOAD 8
    ISTORE 9
   L48
    LINENUMBER 56 L48
    ILOAD 8
    ICONST_1
    ILOAD 6
    ISHL
    IXOR
    ISTORE 8
   L49
    LINENUMBER 57 L49
    ALOAD 5
    ILOAD 9
    AALOAD
    ILOAD 6
    IALOAD
    ISTORE 6
   L50
    LINENUMBER 58 L50
    ALOAD 7
    ILOAD 6
    INVOKESTATIC java/lang/Integer.valueOf (I)Ljava/lang/Integer;
    INVOKEINTERFACE java/util/List.add (Ljava/lang/Object;)Z (itf)
    POP
   L51
    LINENUMBER 59 L51
    GOTO L45
   L46
    LINENUMBER 60 L46
   FRAME FULL [original/Solution0943 [Ljava/lang/String; I [[I [[I [[I I java/util/ArrayList I] []
    NEW java/util/HashSet
    DUP
    ALOAD 7
    INVOKESPECIAL java/util/HashSet.<init> (Ljava/util/Collection;)V
    ASTORE 8
   L52
    LINENUMBER 61 L52
    ICONST_0
    ISTORE 9
   L53
   FRAME FULL [original/Solution0943 [Ljava/lang/String; I [[I [[I [[I I java/util/ArrayList java/util/HashSet I] []
    ILOAD 9
    ILOAD 2
    IF_ICMPGE L54
   L55
    LINENUMBER 62 L55
    ALOAD 8
    ILOAD 9
    INVOKESTATIC java/lang/Integer.valueOf (I)Ljava/lang/Integer;
    INVOKEINTERFACE java/util/Set.contains (Ljava/lang/Object;)Z (itf)
    IFNE L56
   L57
    LINENUMBER 63 L57
    ALOAD 7
    ILOAD 9
    INVOKESTATIC java/lang/Integer.valueOf (I)Ljava/lang/Integer;
    INVOKEINTERFACE java/util/List.add (Ljava/lang/Object;)Z (itf)
    POP
   L56
    LINENUMBER 61 L56
   FRAME FULL [original/Solution0943 [Ljava/lang/String; I [[I [[I [[I I java/util/ArrayList java/util/HashSet I] []
    IINC 9 1
    GOTO L53
   L54
    LINENUMBER 66 L54
   FRAME FULL [original/Solution0943 [Ljava/lang/String; I [[I [[I [[I I java/util/ArrayList java/util/HashSet I] []
    ALOAD 7
    INVOKESTATIC java/util/Collections.reverse (Ljava/util/List;)V
   L58
    LINENUMBER 67 L58
    NEW java/lang/StringBuilder
    DUP
    ALOAD 1
    ALOAD 7
    ICONST_0
    INVOKEINTERFACE java/util/List.get (I)Ljava/lang/Object; (itf)
    CHECKCAST java/lang/Integer
    INVOKEVIRTUAL java/lang/Integer.intValue ()I
    AALOAD
    INVOKESPECIAL java/lang/StringBuilder.<init> (Ljava/lang/String;)V
    ASTORE 9
   L59
    LINENUMBER 68 L59
    ICONST_1
    ISTORE 10
   L60
   FRAME FULL [original/Solution0943 [Ljava/lang/String; I [[I [[I [[I I java/util/ArrayList java/util/HashSet java/lang/StringBuilder I] []
    ILOAD 10
    ILOAD 2
    IF_ICMPGE L61
   L62
    LINENUMBER 69 L62
    ALOAD 3
    ALOAD 7
    ILOAD 10
    ICONST_1
    ISUB
    INVOKEINTERFACE java/util/List.get (I)Ljava/lang/Object; (itf)
    CHECKCAST java/lang/Integer
    INVOKEVIRTUAL java/lang/Integer.intValue ()I
    AALOAD
    ALOAD 7
    ILOAD 10
    INVOKEINTERFACE java/util/List.get (I)Ljava/lang/Object; (itf)
    CHECKCAST java/lang/Integer
    INVOKEVIRTUAL java/lang/Integer.intValue ()I
    IALOAD
    ISTORE 11
   L63
    LINENUMBER 70 L63
    ALOAD 9
    ALOAD 1
    ALOAD 7
    ILOAD 10
    INVOKEINTERFACE java/util/List.get (I)Ljava/lang/Object; (itf)
    CHECKCAST java/lang/Integer
    INVOKEVIRTUAL java/lang/Integer.intValue ()I
    AALOAD
    ILOAD 11
    INVOKEVIRTUAL java/lang/String.substring (I)Ljava/lang/String;
    INVOKEVIRTUAL java/lang/StringBuilder.append (Ljava/lang/String;)Ljava/lang/StringBuilder;
    POP
   L64
    LINENUMBER 68 L64
    IINC 10 1
    GOTO L60
   L61
    LINENUMBER 72 L61
   FRAME FULL [original/Solution0943 [Ljava/lang/String; I [[I [[I [[I I java/util/ArrayList java/util/HashSet java/lang/StringBuilder I] []
    ALOAD 9
    INVOKEVIRTUAL java/lang/StringBuilder.toString ()Ljava/lang/String;
    ARETURN
   L65
    LOCALVARIABLE k I L13 L11 8
    LOCALVARIABLE b Ljava/lang/String; L10 L11 7
    LOCALVARIABLE j I L7 L8 6
    LOCALVARIABLE a Ljava/lang/String; L6 L8 5
    LOCALVARIABLE i I L3 L4 4
    LOCALVARIABLE v I L34 L32 10
    LOCALVARIABLE k I L30 L27 9
    LOCALVARIABLE pi I L29 L27 8
    LOCALVARIABLE j I L24 L25 7
    LOCALVARIABLE i I L20 L21 6
    LOCALVARIABLE i I L38 L39 7
    LOCALVARIABLE k I L48 L51 9
    LOCALVARIABLE i I L45 L46 8
    LOCALVARIABLE i I L53 L54 9
    LOCALVARIABLE k I L63 L64 11
    LOCALVARIABLE i I L60 L61 10
    LOCALVARIABLE this Loriginal/Solution0943; L0 L65 0
    LOCALVARIABLE words [Ljava/lang/String; L0 L65 1
    LOCALVARIABLE n I L1 L65 2
    LOCALVARIABLE g [[I L2 L65 3
    LOCALVARIABLE dp [[I L18 L65 4
    LOCALVARIABLE p [[I L19 L65 5
    LOCALVARIABLE j I L37 L65 6
    LOCALVARIABLE arr Ljava/util/List; L43 L65 7
    // signature Ljava/util/List<Ljava/lang/Integer;>;
    // declaration: arr extends java.util.List<java.lang.Integer>
    LOCALVARIABLE vis Ljava/util/Set; L52 L65 8
    // signature Ljava/util/Set<Ljava/lang/Integer;>;
    // declaration: vis extends java.util.Set<java.lang.Integer>
    LOCALVARIABLE ans Ljava/lang/StringBuilder; L59 L65 9
    MAXSTACK = 5
    MAXLOCALS = 12
}

