// class version 55.0 (55)
// access flags 0x20
class original/Exchange {

  // compiled from: id_110.java

  // access flags 0x0
  <init>()V
   L0
    LINENUMBER 6 L0
    ALOAD 0
    INVOKESPECIAL java/lang/Object.<init> ()V
    RETURN
   L1
    LOCALVARIABLE this Loriginal/Exchange; L0 L1 0
    MAXSTACK = 1
    MAXLOCALS = 1

  // access flags 0x9
  // signature (Ljava/util/List<Ljava/lang/Integer;>;Ljava/util/List<Ljava/lang/Integer;>;)Ljava/lang/String;
  // declaration: java.lang.String exchange(java.util.List<java.lang.Integer>, java.util.List<java.lang.Integer>)
  public static exchange(Ljava/util/List;Ljava/util/List;)Ljava/lang/String;
   L0
    LINENUMBER 36 L0
    ICONST_0
    ISTORE 2
   L1
    LINENUMBER 37 L1
    ICONST_0
    ISTORE 3
   L2
   FRAME FULL [java/util/List java/util/List I I] []
    ILOAD 3
    ALOAD 0
    INVOKEINTERFACE java/util/List.size ()I (itf)
    IF_ICMPGE L3
   L4
    LINENUMBER 38 L4
    ALOAD 0
    ILOAD 3
    INVOKEINTERFACE java/util/List.get (I)Ljava/lang/Object; (itf)
    CHECKCAST java/lang/Integer
    INVOKEVIRTUAL java/lang/Integer.intValue ()I
    ICONST_2
    IREM
    IFEQ L5
   L6
    LINENUMBER 39 L6
    IINC 2 1
   L5
    LINENUMBER 37 L5
   FRAME FULL [java/util/List java/util/List I I] []
    IINC 3 1
    GOTO L2
   L3
    LINENUMBER 42 L3
   FRAME FULL [java/util/List java/util/List I I] []
    ICONST_0
    ISTORE 3
   L7
   FRAME FULL [java/util/List java/util/List I I] []
    ILOAD 3
    ALOAD 1
    INVOKEINTERFACE java/util/List.size ()I (itf)
    IF_ICMPLT L8
   L9
    LINENUMBER 43 L9
    ALOAD 1
    ILOAD 3
    INVOKEINTERFACE java/util/List.get (I)Ljava/lang/Object; (itf)
    CHECKCAST java/lang/Integer
    INVOKEVIRTUAL java/lang/Integer.intValue ()I
    ICONST_2
    IREM
    IFNE L10
   L11
    LINENUMBER 44 L11
    IINC 2 -1
   L10
    LINENUMBER 42 L10
   FRAME FULL [java/util/List java/util/List I I] []
    IINC 3 1
    GOTO L7
   L8
    LINENUMBER 47 L8
   FRAME FULL [java/util/List java/util/List I I] []
    ILOAD 2
    IFGT L12
   L13
    LINENUMBER 48 L13
    LDC "YES"
    ARETURN
   L12
    LINENUMBER 50 L12
   FRAME FULL [java/util/List java/util/List I I] []
    LDC "NO"
    ARETURN
   L14
    LOCALVARIABLE i I L2 L3 3
    LOCALVARIABLE i I L7 L8 3
    LOCALVARIABLE lst1 Ljava/util/List; L0 L14 0
    // signature Ljava/util/List<Ljava/lang/Integer;>;
    // declaration: lst1 extends java.util.List<java.lang.Integer>
    LOCALVARIABLE lst2 Ljava/util/List; L0 L14 1
    // signature Ljava/util/List<Ljava/lang/Integer;>;
    // declaration: lst2 extends java.util.List<java.lang.Integer>
    LOCALVARIABLE count I L1 L14 2
    MAXSTACK = 2
    MAXLOCALS = 4
}

