// class version 55.0 (55)
// access flags 0x20
class original/Solution2024 {

  // compiled from: id_2024.java

  // access flags 0x2
  private [C s

  // access flags 0x2
  private I k

  // access flags 0x0
  <init>()V
   L0
    LINENUMBER 3 L0
    ALOAD 0
    INVOKESPECIAL java/lang/Object.<init> ()V
    RETURN
   L1
    LOCALVARIABLE this Loriginal/Solution2024; L0 L1 0
    MAXSTACK = 1
    MAXLOCALS = 1

  // access flags 0x1
  public maxConsecutiveAnswers(Ljava/lang/String;I)I
   L0
    LINENUMBER 8 L0
    ALOAD 0
    ALOAD 1
    INVOKEVIRTUAL java/lang/String.toCharArray ()[C
    PUTFIELD original/Solution2024.s : [C
   L1
    LINENUMBER 9 L1
    ALOAD 0
    ILOAD 2
    PUTFIELD original/Solution2024.k : I
   L2
    LINENUMBER 10 L2
    ALOAD 0
    BIPUSH 84
    INVOKEVIRTUAL original/Solution2024.f (C)I
    ALOAD 0
    BIPUSH 70
    INVOKEVIRTUAL original/Solution2024.f (C)I
    INVOKESTATIC java/lang/Math.max (II)I
    IRETURN
   L3
    LOCALVARIABLE this Loriginal/Solution2024; L0 L3 0
    LOCALVARIABLE answerKey Ljava/lang/String; L0 L3 1
    LOCALVARIABLE k I L0 L3 2
    MAXSTACK = 3
    MAXLOCALS = 3

  // access flags 0x2
  private f(C)I
   L0
    LINENUMBER 14 L0
    ICONST_0
    ISTORE 2
   L1
    ICONST_0
    ISTORE 3
   L2
    LINENUMBER 15 L2
    ALOAD 0
    GETFIELD original/Solution2024.s : [C
    ASTORE 4
    ALOAD 4
    ARRAYLENGTH
    ISTORE 5
    ICONST_0
    ISTORE 6
   L3
   FRAME FULL [original/Solution2024 I I I [C I I] []
    ILOAD 6
    ILOAD 5
    IF_ICMPGE L4
    ALOAD 4
    ILOAD 6
    CALOAD
    ISTORE 7
   L5
    LINENUMBER 16 L5
    ILOAD 3
    ILOAD 7
    ILOAD 1
    IF_ICMPEQ L6
    ICONST_1
    GOTO L7
   L6
   FRAME FULL [original/Solution2024 I I I [C I I I] [I]
    ICONST_0
   L7
   FRAME FULL [original/Solution2024 I I I [C I I I] [I I]
    IADD
    ISTORE 3
   L8
    LINENUMBER 17 L8
    ILOAD 3
    ALOAD 0
    GETFIELD original/Solution2024.k : I
    IF_ICMPLE L9
   L10
    LINENUMBER 18 L10
    ILOAD 3
    ALOAD 0
    GETFIELD original/Solution2024.s : [C
    ILOAD 2
    IINC 2 1
    CALOAD
    ILOAD 1
    IF_ICMPNE L11
    ICONST_1
    GOTO L12
   L11
   FRAME FULL [original/Solution2024 I I I [C I I I] [I]
    ICONST_0
   L12
   FRAME FULL [original/Solution2024 I I I [C I I I] [I I]
    ISUB
    ISTORE 3
   L9
    LINENUMBER 15 L9
   FRAME FULL [original/Solution2024 I I I [C I I I] []
    IINC 6 1
    GOTO L3
   L4
    LINENUMBER 21 L4
   FRAME FULL [original/Solution2024 I I I [C I I] []
    ALOAD 0
    GETFIELD original/Solution2024.s : [C
    ARRAYLENGTH
    ILOAD 2
    ISUB
    IRETURN
   L13
    LOCALVARIABLE ch C L5 L9 7
    LOCALVARIABLE this Loriginal/Solution2024; L0 L13 0
    LOCALVARIABLE c C L0 L13 1
    LOCALVARIABLE l I L1 L13 2
    LOCALVARIABLE cnt I L2 L13 3
    MAXSTACK = 3
    MAXLOCALS = 8
}

