// class version 55.0 (55)
// access flags 0x20
class original/Solution1129 {

  // compiled from: id_1129.java
  // access flags 0x19
  public final static INNERCLASS java/lang/invoke/MethodHandles$Lookup java/lang/invoke/MethodHandles Lookup

  // access flags 0x0
  <init>()V
   L0
    LINENUMBER 8 L0
    ALOAD 0
    INVOKESPECIAL java/lang/Object.<init> ()V
    RETURN
   L1
    LOCALVARIABLE this Loriginal/Solution1129; L0 L1 0
    MAXSTACK = 1
    MAXLOCALS = 1

  // access flags 0x1
  public shortestAlternatingPaths(I[[I[[I)[I
   L0
    LINENUMBER 10 L0
    ICONST_2
    ILOAD 1
    MULTIANEWARRAY [[Ljava/util/List; 2
    ASTORE 4
   L1
    LINENUMBER 11 L1
    ALOAD 4
    ASTORE 5
    ALOAD 5
    ARRAYLENGTH
    ISTORE 6
    ICONST_0
    ISTORE 7
   L2
   FRAME FULL [original/Solution1129 I [[I [[I [[Ljava/util/List; [[Ljava/util/List; I I] []
    ILOAD 7
    ILOAD 6
    IF_ICMPGE L3
    ALOAD 5
    ILOAD 7
    AALOAD
    ASTORE 8
   L4
    LINENUMBER 12 L4
    ALOAD 8
    INVOKEDYNAMIC apply()Ljava/util/function/IntFunction; [
      // handle kind 0x6 : INVOKESTATIC
      java/lang/invoke/LambdaMetafactory.metafactory(Ljava/lang/invoke/MethodHandles$Lookup;Ljava/lang/String;Ljava/lang/invoke/MethodType;Ljava/lang/invoke/MethodType;Ljava/lang/invoke/MethodHandle;Ljava/lang/invoke/MethodType;)Ljava/lang/invoke/CallSite;
      // arguments:
      (I)Ljava/lang/Object;, 
      // handle kind 0x6 : INVOKESTATIC
      original/Solution1129.lambda$shortestAlternatingPaths$0(I)Ljava/util/List;, 
      (I)Ljava/util/List;
    ]
    INVOKESTATIC java/util/Arrays.setAll ([Ljava/lang/Object;Ljava/util/function/IntFunction;)V
   L5
    LINENUMBER 11 L5
    IINC 7 1
    GOTO L2
   L3
    LINENUMBER 14 L3
   FRAME FULL [original/Solution1129 I [[I [[I [[Ljava/util/List; [[Ljava/util/List; I I] []
    ALOAD 2
    ASTORE 5
    ALOAD 5
    ARRAYLENGTH
    ISTORE 6
    ICONST_0
    ISTORE 7
   L6
   FRAME FULL [original/Solution1129 I [[I [[I [[Ljava/util/List; [[I I I] []
    ILOAD 7
    ILOAD 6
    IF_ICMPGE L7
    ALOAD 5
    ILOAD 7
    AALOAD
    ASTORE 8
   L8
    LINENUMBER 15 L8
    ALOAD 4
    ICONST_0
    AALOAD
    ALOAD 8
    ICONST_0
    IALOAD
    AALOAD
    ALOAD 8
    ICONST_1
    IALOAD
    INVOKESTATIC java/lang/Integer.valueOf (I)Ljava/lang/Integer;
    INVOKEINTERFACE java/util/List.add (Ljava/lang/Object;)Z (itf)
    POP
   L9
    LINENUMBER 14 L9
    IINC 7 1
    GOTO L6
   L7
    LINENUMBER 17 L7
   FRAME FULL [original/Solution1129 I [[I [[I [[Ljava/util/List; [[I I I] []
    ALOAD 3
    ASTORE 5
    ALOAD 5
    ARRAYLENGTH
    ISTORE 6
    ICONST_0
    ISTORE 7
   L10
   FRAME FULL [original/Solution1129 I [[I [[I [[Ljava/util/List; [[I I I] []
    ILOAD 7
    ILOAD 6
    IF_ICMPGE L11
    ALOAD 5
    ILOAD 7
    AALOAD
    ASTORE 8
   L12
    LINENUMBER 18 L12
    ALOAD 4
    ICONST_1
    AALOAD
    ALOAD 8
    ICONST_0
    IALOAD
    AALOAD
    ALOAD 8
    ICONST_1
    IALOAD
    INVOKESTATIC java/lang/Integer.valueOf (I)Ljava/lang/Integer;
    INVOKEINTERFACE java/util/List.add (Ljava/lang/Object;)Z (itf)
    POP
   L13
    LINENUMBER 17 L13
    IINC 7 1
    GOTO L10
   L11
    LINENUMBER 20 L11
   FRAME FULL [original/Solution1129 I [[I [[I [[Ljava/util/List; [[I I I] []
    NEW java/util/ArrayDeque
    DUP
    INVOKESPECIAL java/util/ArrayDeque.<init> ()V
    ASTORE 5
   L14
    LINENUMBER 21 L14
    ALOAD 5
    ICONST_2
    NEWARRAY T_INT
    DUP
    ICONST_0
    ICONST_0
    IASTORE
    DUP
    ICONST_1
    ICONST_0
    IASTORE
    INVOKEINTERFACE java/util/Deque.offer (Ljava/lang/Object;)Z (itf)
    POP
   L15
    LINENUMBER 22 L15
    ALOAD 5
    ICONST_2
    NEWARRAY T_INT
    DUP
    ICONST_0
    ICONST_0
    IASTORE
    DUP
    ICONST_1
    ICONST_1
    IASTORE
    INVOKEINTERFACE java/util/Deque.offer (Ljava/lang/Object;)Z (itf)
    POP
   L16
    LINENUMBER 23 L16
    ILOAD 1
    ICONST_2
    MULTIANEWARRAY [[Z 2
    ASTORE 6
   L17
    LINENUMBER 24 L17
    ILOAD 1
    NEWARRAY T_INT
    ASTORE 7
   L18
    LINENUMBER 25 L18
    ALOAD 7
    ICONST_M1
    INVOKESTATIC java/util/Arrays.fill ([II)V
   L19
    LINENUMBER 26 L19
    ICONST_0
    ISTORE 8
   L20
    LINENUMBER 27 L20
   FRAME FULL [original/Solution1129 I [[I [[I [[Ljava/util/List; java/util/ArrayDeque [[Z [I I] []
    ALOAD 5
    INVOKEINTERFACE java/util/Deque.isEmpty ()Z (itf)
    IFNE L21
   L22
    LINENUMBER 28 L22
    ALOAD 5
    INVOKEINTERFACE java/util/Deque.size ()I (itf)
    ISTORE 9
   L23
   FRAME FULL [original/Solution1129 I [[I [[I [[Ljava/util/List; java/util/ArrayDeque [[Z [I I I] []
    ILOAD 9
    IFLE L24
   L25
    LINENUMBER 29 L25
    ALOAD 5
    INVOKEINTERFACE java/util/Deque.poll ()Ljava/lang/Object; (itf)
    CHECKCAST [I
    ASTORE 10
   L26
    LINENUMBER 30 L26
    ALOAD 10
    ICONST_0
    IALOAD
    ISTORE 11
   L27
    ALOAD 10
    ICONST_1
    IALOAD
    ISTORE 12
   L28
    LINENUMBER 31 L28
    ALOAD 7
    ILOAD 11
    IALOAD
    ICONST_M1
    IF_ICMPNE L29
   L30
    LINENUMBER 32 L30
    ALOAD 7
    ILOAD 11
    ILOAD 8
    IASTORE
   L29
    LINENUMBER 34 L29
   FRAME FULL [original/Solution1129 I [[I [[I [[Ljava/util/List; java/util/ArrayDeque [[Z [I I I [I I I] []
    ALOAD 6
    ILOAD 11
    AALOAD
    ILOAD 12
    ICONST_1
    BASTORE
   L31
    LINENUMBER 35 L31
    ILOAD 12
    ICONST_1
    IXOR
    ISTORE 12
   L32
    LINENUMBER 36 L32
    ALOAD 4
    ILOAD 12
    AALOAD
    ILOAD 11
    AALOAD
    INVOKEINTERFACE java/util/List.iterator ()Ljava/util/Iterator; (itf)
    ASTORE 13
   L33
   FRAME FULL [original/Solution1129 I [[I [[I [[Ljava/util/List; java/util/ArrayDeque [[Z [I I I [I I I java/util/Iterator] []
    ALOAD 13
    INVOKEINTERFACE java/util/Iterator.hasNext ()Z (itf)
    IFEQ L34
    ALOAD 13
    INVOKEINTERFACE java/util/Iterator.next ()Ljava/lang/Object; (itf)
    CHECKCAST java/lang/Integer
    INVOKEVIRTUAL java/lang/Integer.intValue ()I
    ISTORE 14
   L35
    LINENUMBER 37 L35
    ALOAD 6
    ILOAD 14
    AALOAD
    ILOAD 12
    BALOAD
    IFNE L36
   L37
    LINENUMBER 38 L37
    ALOAD 5
    ICONST_2
    NEWARRAY T_INT
    DUP
    ICONST_0
    ILOAD 14
    IASTORE
    DUP
    ICONST_1
    ILOAD 12
    IASTORE
    INVOKEINTERFACE java/util/Deque.offer (Ljava/lang/Object;)Z (itf)
    POP
   L36
    LINENUMBER 40 L36
   FRAME FULL [original/Solution1129 I [[I [[I [[Ljava/util/List; java/util/ArrayDeque [[Z [I I I [I I I java/util/Iterator I] []
    GOTO L33
   L34
    LINENUMBER 28 L34
   FRAME FULL [original/Solution1129 I [[I [[I [[Ljava/util/List; java/util/ArrayDeque [[Z [I I I [I I I java/util/Iterator] []
    IINC 9 -1
    GOTO L23
   L24
    LINENUMBER 42 L24
   FRAME FULL [original/Solution1129 I [[I [[I [[Ljava/util/List; java/util/ArrayDeque [[Z [I I I] []
    IINC 8 -1
    GOTO L20
   L21
    LINENUMBER 44 L21
   FRAME FULL [original/Solution1129 I [[I [[I [[Ljava/util/List; java/util/ArrayDeque [[Z [I I] []
    ALOAD 7
    ARETURN
   L38
    LOCALVARIABLE f [Ljava/util/List; L4 L5 8
    // signature [Ljava/util/List<Ljava/lang/Integer;>;
    // declaration: f extends java.util.List<java.lang.Integer>[]
    LOCALVARIABLE e [I L8 L9 8
    LOCALVARIABLE e [I L12 L13 8
    LOCALVARIABLE j I L35 L36 14
    LOCALVARIABLE p [I L26 L34 10
    LOCALVARIABLE i I L27 L34 11
    LOCALVARIABLE c I L28 L34 12
    LOCALVARIABLE k I L23 L24 9
    LOCALVARIABLE this Loriginal/Solution1129; L0 L38 0
    LOCALVARIABLE n I L0 L38 1
    LOCALVARIABLE redEdges [[I L0 L38 2
    LOCALVARIABLE blueEdges [[I L0 L38 3
    LOCALVARIABLE g [[Ljava/util/List; L1 L38 4
    // signature [[Ljava/util/List<Ljava/lang/Integer;>;
    // declaration: g extends java.util.List<java.lang.Integer>[][]
    LOCALVARIABLE q Ljava/util/Deque; L14 L38 5
    // signature Ljava/util/Deque<[I>;
    // declaration: q extends java.util.Deque<int[]>
    LOCALVARIABLE vis [[Z L17 L38 6
    LOCALVARIABLE ans [I L18 L38 7
    LOCALVARIABLE d I L20 L38 8
    MAXSTACK = 5
    MAXLOCALS = 15

  // access flags 0x100A
  private static synthetic lambda$shortestAlternatingPaths$0(I)Ljava/util/List;
   L0
    LINENUMBER 12 L0
    NEW java/util/ArrayList
    DUP
    INVOKESPECIAL java/util/ArrayList.<init> ()V
    ARETURN
   L1
    LOCALVARIABLE k I L0 L1 0
    MAXSTACK = 2
    MAXLOCALS = 1
}

