// class version 55.0 (55)
// access flags 0x20
class original/SortThird {

  // compiled from: id_33.java

  // access flags 0x0
  <init>()V
   L0
    LINENUMBER 8 L0
    ALOAD 0
    INVOKESPECIAL java/lang/Object.<init> ()V
    RETURN
   L1
    LOCALVARIABLE this Loriginal/SortThird; L0 L1 0
    MAXSTACK = 1
    MAXLOCALS = 1

  // access flags 0x9
  // signature (Ljava/util/List<Ljava/lang/Integer;>;)Ljava/util/List<Ljava/lang/Integer;>;
  // declaration: java.util.List<java.lang.Integer> sortThird(java.util.List<java.lang.Integer>)
  public static sortThird(Ljava/util/List;)Ljava/util/List;
   L0
    LINENUMBER 34 L0
    NEW java/util/ArrayList
    DUP
    ALOAD 0
    INVOKESPECIAL java/util/ArrayList.<init> (Ljava/util/Collection;)V
    ASTORE 1
   L1
    LINENUMBER 35 L1
    ICONST_0
    ISTORE 2
   L2
   FRAME FULL [java/util/List java/util/ArrayList I] []
    ILOAD 2
    ALOAD 0
    INVOKEINTERFACE java/util/List.size ()I (itf)
    IF_ICMPLT L3
   L4
    LINENUMBER 36 L4
    ILOAD 2
    ICONST_3
    IREM
    IFNE L5
   L6
    LINENUMBER 37 L6
    NEW java/util/ArrayList
    DUP
    INVOKESPECIAL java/util/ArrayList.<init> ()V
    ASTORE 3
   L7
    LINENUMBER 38 L7
    ICONST_0
    ISTORE 4
   L8
   FRAME FULL [java/util/List java/util/ArrayList I java/util/ArrayList I] []
    ILOAD 4
    ALOAD 0
    INVOKEINTERFACE java/util/List.size ()I (itf)
    IF_ICMPGE L9
   L10
    LINENUMBER 39 L10
    ILOAD 4
    ICONST_3
    IREM
    IFNE L11
   L12
    LINENUMBER 40 L12
    ALOAD 3
    ALOAD 0
    ILOAD 4
    INVOKEINTERFACE java/util/List.get (I)Ljava/lang/Object; (itf)
    CHECKCAST java/lang/Integer
    INVOKEINTERFACE java/util/List.add (Ljava/lang/Object;)Z (itf)
    POP
   L11
    LINENUMBER 38 L11
   FRAME FULL [java/util/List java/util/ArrayList I java/util/ArrayList I] []
    IINC 4 1
    GOTO L8
   L9
    LINENUMBER 43 L9
   FRAME FULL [java/util/List java/util/ArrayList I java/util/ArrayList I] []
    ALOAD 3
    INVOKESTATIC java/util/Collections.sort (Ljava/util/List;)V
   L13
    LINENUMBER 44 L13
    ALOAD 1
    ILOAD 2
    ALOAD 3
    ILOAD 2
    ICONST_3
    IDIV
    INVOKEINTERFACE java/util/List.get (I)Ljava/lang/Object; (itf)
    CHECKCAST java/lang/Integer
    INVOKEINTERFACE java/util/List.set (ILjava/lang/Object;)Ljava/lang/Object; (itf)
    POP
   L5
    LINENUMBER 35 L5
   FRAME FULL [java/util/List java/util/ArrayList I] []
    IINC 2 1
    GOTO L2
   L3
    LINENUMBER 47 L3
   FRAME FULL [java/util/List java/util/ArrayList I] []
    ALOAD 1
    ARETURN
   L14
    LOCALVARIABLE j I L8 L9 4
    LOCALVARIABLE subl Ljava/util/List; L7 L5 3
    // signature Ljava/util/List<Ljava/lang/Integer;>;
    // declaration: subl extends java.util.List<java.lang.Integer>
    LOCALVARIABLE i I L2 L3 2
    LOCALVARIABLE l Ljava/util/List; L0 L14 0
    // signature Ljava/util/List<Ljava/lang/Integer;>;
    // declaration: l extends java.util.List<java.lang.Integer>
    LOCALVARIABLE l2 Ljava/util/List; L1 L14 1
    // signature Ljava/util/List<Ljava/lang/Integer;>;
    // declaration: l2 extends java.util.List<java.lang.Integer>
    MAXSTACK = 5
    MAXLOCALS = 5
}

