// class version 55.0 (55)
// access flags 0x20
class original/EvenOddCount {

  // compiled from: id_155.java

  // access flags 0x0
  <init>()V
   L0
    LINENUMBER 8 L0
    ALOAD 0
    INVOKESPECIAL java/lang/Object.<init> ()V
    RETURN
   L1
    LOCALVARIABLE this Loriginal/EvenOddCount; L0 L1 0
    MAXSTACK = 1
    MAXLOCALS = 1

  // access flags 0x9
  // signature (I)Ljava/util/List<Ljava/lang/Integer;>;
  // declaration: java.util.List<java.lang.Integer> evenOddCount(int)
  public static evenOddCount(I)Ljava/util/List;
   L0
    LINENUMBER 34 L0
    ICONST_0
    ISTORE 1
   L1
    LINENUMBER 35 L1
    ICONST_0
    ISTORE 2
   L2
    LINENUMBER 36 L2
    ILOAD 0
    IFNE L3
   L4
    LINENUMBER 37 L4
    IINC 1 1
   L3
    LINENUMBER 39 L3
   FRAME FULL [I I I] []
    ILOAD 0
    IFEQ L5
   L6
    LINENUMBER 40 L6
    ILOAD 0
    ICONST_2
    IREM
    IFNE L7
   L8
    LINENUMBER 41 L8
    IINC 1 1
    GOTO L9
   L7
    LINENUMBER 43 L7
   FRAME FULL [I I I] []
    IINC 2 1
   L9
    LINENUMBER 45 L9
   FRAME FULL [I I I] []
    ILOAD 0
    BIPUSH 10
    IDIV
    ISTORE 0
    GOTO L3
   L5
    LINENUMBER 47 L5
   FRAME FULL [I I I] []
    ICONST_2
    ANEWARRAY java/lang/Integer
    DUP
    ICONST_0
    ILOAD 1
    INVOKESTATIC java/lang/Integer.valueOf (I)Ljava/lang/Integer;
    AASTORE
    DUP
    ICONST_1
    ILOAD 2
    INVOKESTATIC java/lang/Integer.valueOf (I)Ljava/lang/Integer;
    AASTORE
    INVOKESTATIC java/util/Arrays.asList ([Ljava/lang/Object;)Ljava/util/List;
    POP
    INVOKESTATIC java/util/Collections.emptyList ()Ljava/util/List;
    ARETURN
   L10
    LOCALVARIABLE num I L0 L10 0
    LOCALVARIABLE even I L1 L10 1
    LOCALVARIABLE odd I L2 L10 2
    MAXSTACK = 4
    MAXLOCALS = 3
}

