// class version 55.0 (55)
// access flags 0x20
class original/Solution2954 {

  // compiled from: id_2954.java

  // access flags 0x1A
  private final static I MOD = 1000000007

  // access flags 0x1A
  private final static I MX = 100000

  // access flags 0x1A
  private final static [I FAC

  // access flags 0x0
  <init>()V
   L0
    LINENUMBER 3 L0
    ALOAD 0
    INVOKESPECIAL java/lang/Object.<init> ()V
    RETURN
   L1
    LOCALVARIABLE this Loriginal/Solution2954; L0 L1 0
    MAXSTACK = 1
    MAXLOCALS = 1

  // access flags 0x1
  public numberOfSequence(I[I)I
   L0
    LINENUMBER 16 L0
    ALOAD 2
    ARRAYLENGTH
    ISTORE 3
   L1
    LINENUMBER 17 L1
    ILOAD 3
    ICONST_1
    IADD
    NEWARRAY T_INT
    ASTORE 4
   L2
    LINENUMBER 18 L2
    ALOAD 4
    ICONST_0
    ALOAD 2
    ICONST_0
    IALOAD
    IASTORE
   L3
    LINENUMBER 19 L3
    ALOAD 4
    ILOAD 3
    ILOAD 1
    ALOAD 2
    ILOAD 3
    ICONST_1
    ISUB
    IALOAD
    ISUB
    ICONST_1
    ISUB
    IASTORE
   L4
    LINENUMBER 20 L4
    ICONST_1
    ISTORE 5
   L5
   FRAME FULL [original/Solution2954 I [I I [I I] []
    ILOAD 5
    ILOAD 3
    IF_ICMPGE L6
   L7
    LINENUMBER 21 L7
    ALOAD 4
    ILOAD 5
    ALOAD 2
    ILOAD 5
    IALOAD
    ALOAD 2
    ILOAD 5
    ICONST_1
    ISUB
    IALOAD
    ISUB
    ICONST_1
    ISUB
    IASTORE
   L8
    LINENUMBER 20 L8
    IINC 5 1
    GOTO L5
   L6
    LINENUMBER 23 L6
   FRAME FULL [original/Solution2954 I [I I [I] []
    ICONST_0
    ISTORE 5
   L9
    LINENUMBER 24 L9
    ALOAD 4
    ASTORE 6
    ALOAD 6
    ARRAYLENGTH
    ISTORE 7
    ICONST_0
    ISTORE 8
   L10
   FRAME FULL [original/Solution2954 I [I I [I I [I I I] []
    ILOAD 8
    ILOAD 7
    IF_ICMPGE L11
    ALOAD 6
    ILOAD 8
    IALOAD
    ISTORE 9
   L12
    LINENUMBER 25 L12
    ILOAD 5
    ILOAD 9
    IADD
    ISTORE 5
   L13
    LINENUMBER 24 L13
    IINC 8 1
    GOTO L10
   L11
    LINENUMBER 27 L11
   FRAME FULL [original/Solution2954 I [I I [I I] []
    GETSTATIC original/Solution2954.FAC : [I
    ILOAD 5
    IALOAD
    ISTORE 6
   L14
    LINENUMBER 28 L14
    ALOAD 4
    ASTORE 7
    ALOAD 7
    ARRAYLENGTH
    ISTORE 8
    ICONST_0
    ISTORE 9
   L15
   FRAME FULL [original/Solution2954 I [I I [I I I [I I I] []
    ILOAD 9
    ILOAD 8
    IF_ICMPGE L16
    ALOAD 7
    ILOAD 9
    IALOAD
    ISTORE 10
   L17
    LINENUMBER 29 L17
    ILOAD 10
    IFLE L18
   L19
    LINENUMBER 30 L19
    ILOAD 6
    I2L
    ALOAD 0
    GETSTATIC original/Solution2954.FAC : [I
    ILOAD 10
    IALOAD
    I2L
    LDC 1000000005L
    INVOKEVIRTUAL original/Solution2954.qpow (JJ)I
    I2L
    LMUL
    LDC 1000000007L
    LREM
    L2I
    ISTORE 6
   L18
    LINENUMBER 28 L18
   FRAME FULL [original/Solution2954 I [I I [I I I [I I I] []
    IINC 9 1
    GOTO L15
   L16
    LINENUMBER 33 L16
   FRAME FULL [original/Solution2954 I [I I [I I I] []
    ICONST_1
    ISTORE 7
   L20
   FRAME FULL [original/Solution2954 I [I I [I I I I] []
    ILOAD 7
    ALOAD 4
    ARRAYLENGTH
    ICONST_1
    ISUB
    IF_ICMPGE L21
   L22
    LINENUMBER 34 L22
    ALOAD 4
    ILOAD 7
    IALOAD
    ICONST_1
    IF_ICMPLE L23
   L24
    LINENUMBER 35 L24
    ILOAD 6
    I2L
    ALOAD 0
    LDC 2L
    ALOAD 4
    ILOAD 7
    IALOAD
    ICONST_1
    ISUB
    I2L
    INVOKEVIRTUAL original/Solution2954.qpow (JJ)I
    I2L
    LMUL
    LDC 1000000007L
    LREM
    L2I
    ISTORE 6
   L23
    LINENUMBER 33 L23
   FRAME FULL [original/Solution2954 I [I I [I I I I] []
    IINC 7 1
    GOTO L20
   L21
    LINENUMBER 38 L21
   FRAME FULL [original/Solution2954 I [I I [I I I] []
    ILOAD 6
    IRETURN
   L25
    LOCALVARIABLE i I L5 L6 5
    LOCALVARIABLE x I L12 L13 9
    LOCALVARIABLE x I L17 L18 10
    LOCALVARIABLE i I L20 L21 7
    LOCALVARIABLE this Loriginal/Solution2954; L0 L25 0
    LOCALVARIABLE n I L0 L25 1
    LOCALVARIABLE sick [I L0 L25 2
    LOCALVARIABLE m I L1 L25 3
    LOCALVARIABLE nums [I L2 L25 4
    LOCALVARIABLE s I L9 L25 5
    LOCALVARIABLE ans I L14 L25 6
    MAXSTACK = 7
    MAXLOCALS = 11

  // access flags 0x2
  private qpow(JJ)I
   L0
    LINENUMBER 42 L0
    LCONST_1
    LSTORE 5
   L1
    LINENUMBER 43 L1
   FRAME FULL [original/Solution2954 J J J] []
    LLOAD 3
    LCONST_0
    LCMP
    IFLE L2
   L3
    LINENUMBER 44 L3
    LLOAD 3
    LCONST_1
    LAND
    LCONST_1
    LCMP
    IFNE L4
   L5
    LINENUMBER 45 L5
    LLOAD 5
    LLOAD 1
    LMUL
    LDC 1000000007L
    LREM
    LSTORE 5
   L4
    LINENUMBER 47 L4
   FRAME FULL [original/Solution2954 J J J] []
    LLOAD 1
    LLOAD 1
    LMUL
    LDC 1000000007L
    LREM
    LSTORE 1
   L6
    LINENUMBER 43 L6
    LLOAD 3
    ICONST_1
    LSHR
    LSTORE 3
    GOTO L1
   L2
    LINENUMBER 49 L2
   FRAME FULL [original/Solution2954 J J J] []
    LLOAD 5
    L2I
    IRETURN
   L7
    LOCALVARIABLE this Loriginal/Solution2954; L0 L7 0
    LOCALVARIABLE a J L0 L7 1
    LOCALVARIABLE n J L0 L7 3
    LOCALVARIABLE ans J L1 L7 5
    MAXSTACK = 4
    MAXLOCALS = 7

  // access flags 0x8
  static <clinit>()V
   L0
    LINENUMBER 6 L0
    LDC 100001
    NEWARRAY T_INT
    PUTSTATIC original/Solution2954.FAC : [I
   L1
    LINENUMBER 9 L1
    GETSTATIC original/Solution2954.FAC : [I
    ICONST_0
    ICONST_1
    IASTORE
   L2
    LINENUMBER 10 L2
    ICONST_1
    ISTORE 0
   L3
   FRAME FULL [I] []
    ILOAD 0
    LDC 100000
    IF_ICMPGT L4
   L5
    LINENUMBER 11 L5
    GETSTATIC original/Solution2954.FAC : [I
    ILOAD 0
    GETSTATIC original/Solution2954.FAC : [I
    ILOAD 0
    ICONST_1
    ISUB
    IALOAD
    I2L
    ILOAD 0
    I2L
    LMUL
    LDC 1000000007L
    LREM
    L2I
    IASTORE
   L6
    LINENUMBER 10 L6
    IINC 0 1
    GOTO L3
   L4
    LINENUMBER 13 L4
   FRAME FULL [] []
    RETURN
    LOCALVARIABLE i I L3 L4 0
    MAXSTACK = 6
    MAXLOCALS = 1
}

