// class version 55.0 (55)
// access flags 0x20
class original/Iscube {

  // compiled from: id_77.java

  // access flags 0x0
  <init>()V
   L0
    LINENUMBER 4 L0
    ALOAD 0
    INVOKESPECIAL java/lang/Object.<init> ()V
    RETURN
   L1
    LOCALVARIABLE this Loriginal/Iscube; L0 L1 0
    MAXSTACK = 1
    MAXLOCALS = 1

  // access flags 0x9
  public static iscube(I)Ljava/lang/Boolean;
   L0
    LINENUMBER 35 L0
    ILOAD 0
    IFGE L1
   L2
    LINENUMBER 36 L2
    ILOAD 0
    INEG
    INVOKESTATIC original/Iscube.iscube (I)Ljava/lang/Boolean;
    ARETURN
   L1
    LINENUMBER 38 L1
   FRAME FULL [I] []
    ICONST_0
    ISTORE 1
   L3
    LINENUMBER 39 L3
   FRAME FULL [I I] []
    ILOAD 1
    ILOAD 1
    IMUL
    ILOAD 1
    IMUL
    ILOAD 0
    IF_ICMPGE L4
   L5
    LINENUMBER 40 L5
    IINC 1 1
    GOTO L3
   L4
    LINENUMBER 42 L4
   FRAME FULL [I I] []
    ILOAD 1
    ILOAD 1
    IDIV
    ILOAD 1
    IMUL
    ILOAD 0
    IF_ICMPNE L6
    ICONST_1
    GOTO L7
   L6
   FRAME FULL [I I] []
    ICONST_0
   L7
   FRAME FULL [I I] [I]
    INVOKESTATIC java/lang/Boolean.valueOf (Z)Ljava/lang/Boolean;
    ARETURN
   L8
    LOCALVARIABLE a I L0 L8 0
    LOCALVARIABLE i I L3 L8 1
    MAXSTACK = 2
    MAXLOCALS = 2
}

