// class version 55.0 (55)
// access flags 0x20
class original/Solution1478 {

  // compiled from: id_1478.java

  // access flags 0x0
  <init>()V
   L0
    LINENUMBER 4 L0
    ALOAD 0
    INVOKESPECIAL java/lang/Object.<init> ()V
    RETURN
   L1
    LOCALVARIABLE this Loriginal/Solution1478; L0 L1 0
    MAXSTACK = 1
    MAXLOCALS = 1

  // access flags 0x1
  public minDistance([II)I
   L0
    LINENUMBER 6 L0
    ALOAD 1
    INVOKESTATIC java/util/Arrays.sort ([I)V
   L1
    LINENUMBER 7 L1
    ALOAD 1
    ARRAYLENGTH
    ISTORE 3
   L2
    LINENUMBER 8 L2
    ILOAD 3
    ILOAD 3
    MULTIANEWARRAY [[I 2
    ASTORE 4
   L3
    LINENUMBER 9 L3
    ILOAD 3
    ICONST_2
    ISUB
    ISTORE 5
   L4
   FRAME FULL [original/Solution1478 [I I I [[I I] []
    ILOAD 5
    IFLT L5
   L6
    LINENUMBER 10 L6
    ILOAD 5
    ICONST_1
    IADD
    ISTORE 6
   L7
   FRAME FULL [original/Solution1478 [I I I [[I I I] []
    ILOAD 6
    ILOAD 3
    IF_ICMPGE L8
   L9
    LINENUMBER 11 L9
    ALOAD 4
    ILOAD 5
    AALOAD
    ILOAD 6
    ALOAD 4
    ILOAD 5
    ICONST_1
    IADD
    AALOAD
    ILOAD 6
    ICONST_1
    ISUB
    IALOAD
    ALOAD 1
    ILOAD 6
    IALOAD
    IADD
    ALOAD 1
    ILOAD 5
    IALOAD
    ISUB
    IASTORE
   L10
    LINENUMBER 10 L10
    IINC 6 1
    GOTO L7
   L8
    LINENUMBER 9 L8
   FRAME FULL [original/Solution1478 [I I I [[I I I] []
    IINC 5 -1
    GOTO L4
   L5
    LINENUMBER 14 L5
   FRAME FULL [original/Solution1478 [I I I [[I I] []
    ILOAD 3
    ILOAD 2
    ICONST_1
    IADD
    MULTIANEWARRAY [[I 2
    ASTORE 5
   L11
    LINENUMBER 15 L11
    LDC 1073741824
    ISTORE 6
   L12
    LINENUMBER 16 L12
    ALOAD 5
    ASTORE 7
    ALOAD 7
    ARRAYLENGTH
    ISTORE 8
    ICONST_0
    ISTORE 9
   L13
   FRAME FULL [original/Solution1478 [I I I [[I [[I I [[I I I] []
    ILOAD 9
    ILOAD 8
    IF_ICMPGE L14
    ALOAD 7
    ILOAD 9
    AALOAD
    ASTORE 10
   L15
    LINENUMBER 17 L15
    ALOAD 10
    LDC 1073741824
    INVOKESTATIC java/util/Arrays.fill ([II)V
   L16
    LINENUMBER 16 L16
    IINC 9 1
    GOTO L13
   L14
    LINENUMBER 19 L14
   FRAME FULL [original/Solution1478 [I I I [[I [[I I [[I I I] []
    ICONST_0
    ISTORE 7
   L17
   FRAME FULL [original/Solution1478 [I I I [[I [[I I I I I] []
    ILOAD 7
    ILOAD 3
    IF_ICMPGE L18
   L19
    LINENUMBER 20 L19
    ALOAD 5
    ILOAD 7
    AALOAD
    ICONST_1
    ALOAD 4
    ICONST_0
    AALOAD
    ILOAD 7
    IALOAD
    IASTORE
   L20
    LINENUMBER 21 L20
    ICONST_2
    ISTORE 8
   L21
   FRAME FULL [original/Solution1478 [I I I [[I [[I I I I I] []
    ILOAD 8
    ILOAD 2
    IF_ICMPGT L22
    ILOAD 8
    ILOAD 7
    ICONST_1
    IADD
    IF_ICMPGT L22
   L23
    LINENUMBER 22 L23
    ICONST_0
    ISTORE 9
   L24
   FRAME FULL [original/Solution1478 [I I I [[I [[I I I I I] []
    ILOAD 9
    ILOAD 7
    IF_ICMPGE L25
   L26
    LINENUMBER 23 L26
    ALOAD 5
    ILOAD 7
    AALOAD
    ILOAD 8
    ALOAD 5
    ILOAD 7
    AALOAD
    ILOAD 8
    IALOAD
    ALOAD 5
    ILOAD 9
    AALOAD
    ILOAD 8
    ICONST_1
    IADD
    IALOAD
    ALOAD 4
    ILOAD 9
    ICONST_1
    IADD
    AALOAD
    ILOAD 7
    IALOAD
    IADD
    INVOKESTATIC java/lang/Math.min (II)I
    IASTORE
   L27
    LINENUMBER 22 L27
    IINC 9 1
    GOTO L24
   L25
    LINENUMBER 21 L25
   FRAME FULL [original/Solution1478 [I I I [[I [[I I I I I] []
    IINC 8 1
    GOTO L21
   L22
    LINENUMBER 19 L22
   FRAME FULL [original/Solution1478 [I I I [[I [[I I I I I] []
    IINC 7 1
    GOTO L17
   L18
    LINENUMBER 27 L18
   FRAME FULL [original/Solution1478 [I I I [[I [[I I I I I] []
    ALOAD 5
    ILOAD 3
    ICONST_1
    ISUB
    AALOAD
    ILOAD 2
    IALOAD
    IRETURN
   L28
    LOCALVARIABLE j I L7 L8 6
    LOCALVARIABLE i I L4 L5 5
    LOCALVARIABLE e [I L15 L16 10
    LOCALVARIABLE p I L24 L25 9
    LOCALVARIABLE j I L21 L22 8
    LOCALVARIABLE i I L17 L18 7
    LOCALVARIABLE this Loriginal/Solution1478; L0 L28 0
    LOCALVARIABLE houses [I L0 L28 1
    LOCALVARIABLE k I L0 L28 2
    LOCALVARIABLE n I L2 L28 3
    LOCALVARIABLE g [[I L3 L28 4
    LOCALVARIABLE f [[I L11 L28 5
    LOCALVARIABLE inf I L12 L28 6
    MAXSTACK = 7
    MAXLOCALS = 11
}

